Workbook

Sheet Staffing
B2: Insert the Logos
A4: IP Name
A5: Improving Sustainability and Resilience for Food Production System in Karamoja
A6: LIST OF THE PROJECT MEMBERS OF STAFF
B7: Name | C7: Gender | D7: Function | E7: Place | F7: Telephone Number | G7: Remarks

Sheet FFS groups
A2: ID | B2: Vendor No | C2: IPName | D2: Project | E2: District | F2: Subcounty | G2: Parish | H2: Host Village | I2: Registered group name | J2: FFS Status | K2: Formed with support from | L2: Year Formed | M2: GPS_Eastings | N2: GPS_Northings | Q2: Contact person | R2: Phone number | S2: Old facilitator | T2: New Facilitator | U2: Sex | V2: Contact details | W2: Membership at formation | Z2: Current registered members | AC2: Group identity/legal records | AL2: Financial/phyisical records | AQ2: Learning activities/production records | AY2: Livelihood diversification activities | BH2: Seed multiplication | BU2: Sustainability mechanisms
O3: GPS_Eastings | P3: GPS_Northings | V3: Phone | W3: Male | X3: Female | Z3: Male2 | AA3: Female3 | AB3: Total4 | AC3: Group has a profile | AD3: Group is registered? | AE3: Registering institution | AF3: Registration certificate # | AG3: Date of Issue | AH3: Expiry date | AI3: Constitution | AJ3: Members register | AK3: Minute book | AL3: Bank account | AM3: Cash book | AN3: Savings & credit ledger | AO3: Assets inventory/ register | AP3: VSL Box | AQ3: Season-long learning calender | AR3: Group Action Plan | AS3: Conducted validation studies | AT3: Type of study enterprise | AU3: Main production problem addressed by the study | AV3: Main solutions tested | AW3: Status of the comparative study | AX3: Technology/practice selected for scaling up based on the study | AY3: Type of livelihood interventions supported | AZ3: Types of inputs provided | BA3: Units of measure | BB3: Qty of inputs | BC3: Unit cost of inputs (UGX) | BD3: Total cost (UGX) | BE3: Input beneficiary type | BF3: # of beneficiaries | BG3: Actual/expected yield/revenue | BH3: Type of crop seed provided | BI3: Variety | BJ3: Units of measure5 | BK3: Qty of inputs6 | BL3: Unit cost of inputs7 | BM3: Total cost (UGX)8 | BN3: Input beneficiary type9 | BO3: # of beneficiaries10 | BP3: Qty of seed planted | BQ3: Area planted | BR3: Expected yeld (specify units) | BS3: Actual yeld (specify units) | BT3: How are other group members benefiting from the seeds | BU3: Group has been linked to other opportunities? | BV3: Type of goods or services the group has been linked to (List) | BW3: Types of organizations offering the good or services | BX3: List the names of the institutions linked to the group | BY3: Has the group registered any success stories? | BZ3: # of success stories documented | CA3: Types of success stories documented (List) | CB3: # of documented success stories submitted to FAO | CC3: Types of success stories submitted to FAO (List)2
A4: AMUD-AMUD01
A5: KOT-KOT02
A6: KOT-KOT03
A7: KOT-KOT04
A8: KOT-KOT05
A9: KOT-KOT06
A10: KOT-KOT07
A11: KOT-KOT08
A12: KOT-KOT09
A13: KOT-KOT10
A14: KOT-KOT11
A15: KOT-KOT12
... A66: KOT-PAN31
W67: 686 | X67: 1214 | Y67: 1900

Sheet Sub County-beneficiaries 
A1: ID | B1: DISTRICT | C1: Sub county | D1: Parish | E1: Home Village | F1: Group Name | G1: Name Of Beneficiary | H1: Sex | I1: Year of data collection | J1: Birth year if NIN is correct | K1: Calculated age if NIN is correct | L1: Calculated birth year existing age. | M1: Age | N1: Age group | O1: Updated NIN | P1: NIN length | Q1: Contacts | R1: ccDesignation | S1: Other positions held in the community | T1: Highest level of educ | U1: Marital status | V1: Hh head? | W1: Vulnerabiity status | X1: HH size | Y1: # of adults in hh | Z1: # of children <18 years in hh | AA1: # of boys <18 years in school | AB1: # of girls < 18 years in school | AC1: Level of education for children < 18 years | AD1: Main productive assets possessed at start of the project | AE1: Uses SLM/CSA practices | AF1: Type of land SLM/CSA is being practiced | AG1: Types of SLM/CSA technologies practiced at hh | AH1: Qty of SLM structured created | AI1: Estimated area of land technologies have been applied | AJ1: Estimated increase in crop yields (specify crop and increase in yield) | AK1: Other observed benefits from application of SLM/CSA technologies | AL1: Main productive assets acquired during the course of the project2

Sheet Sub County-II-beneficiaries 
A1: ID | B1: DISTRICT | C1: Sub county | D1: Parish | E1: Home Village | F1: Group Name | G1: Name Of Beneficiary | H1: Sex | I1: Year of data collection | J1: Birth year if NIN is correct | K1: Calculated age if NIN is correct | L1: Calculated birth year existing age. | M1: Age | N1: Age group | O1: Updated NIN | P1: NIN length | Q1: Contacts | R1: ccDesignation | S1: Other positions held in the community | T1: Highest level of educ | U1: Marital status | V1: Hh head? | W1: Vulnerabiity status | X1: HH size | Y1: # of adults in hh | Z1: # of children <18 years in hh | AA1: # of boys <18 years in school | AB1: # of girls < 18 years in school | AC1: Level of education for children < 18 years | AD1: Main productive assets possessed at start of the project | AE1: Uses SLM/CSA practices | AF1: Type of land SLM/CSA is being practiced | AG1: Types of SLM/CSA technologies practiced at hh | AH1: Qty of SLM structured created | AI1: Estimated area of land technologies have been applied | AJ1: Estimated increase in crop yields (specify crop and increase in yield) | AK1: Other observed benefits from application of SLM/CSA technologies | AL1: Main productive assets acquired during the course of the project2

Sheet Sub County III-beneficiaries
A1: ID | B1: DISTRICT | C1: Sub county | D1: Parish | E1: Home Village | F1: Group Name | G1: Name Of Beneficiary | H1: Sex | I1: Year of data collection | J1: Birth year if NIN is correct | K1: Calculated age if NIN is correct | L1: Calculated birth year existing age. | M1: Age | N1: Age group | O1: Updated NIN | P1: NIN length | Q1: Contacts | R1: ccDesignation | S1: Other positions held in the community | T1: Highest level of educ | U1: Marital status | V1: Hh head? | W1: Vulnerabiity status | X1: HH size | Y1: # of adults in hh | Z1: # of children <18 years in hh | AA1: # of boys <18 years in school | AB1: # of girls < 18 years in school | AC1: Level of education for children < 18 years | AD1: Main productive assets possessed at start of the project | AE1: Uses SLM/CSA practices | AF1: Type of land SLM/CSA is being practiced | AG1: Types of SLM/CSA technologies practiced at hh | AH1: Qty of SLM structured created | AI1: Estimated area of land technologies have been applied | AJ1: Estimated increase in crop yields (specify crop and increase in yield) | AK1: Other observed benefits from application of SLM/CSA technologies | AL1: Main productive assets acquired during the course of the project2

Sheet Sub County IV-Beneficiaries
A1: ID | B1: District | C1: Sub county | D1: Parish | E1: Home Village | F1: FFS Group Name | G1: Beneficiary Name | H1: Sex | I1: Year of data collection | J1: Birth year if NIN is correct | K1: Calculated age if NIN is correct | L1: Calculated birth year existing age. | M1: Age | N1: Age group | O1: Updated NIN | P1: NIN length | Q1: Contacts | R1: Designation | S1: Other positions held in the community | T1: Highest level of educ | U1: Marital status | V1: Hh head? | W1: Vulnerabiity status | X1: HH size | Y1: # of adults in hh | Z1: # of children <18 years in hh | AA1: # of boys <18 years in school | AB1: # of girls < 18 years in school | AC1: Level of education for children < 18 years | AD1: Main productive assets possessed at start of the project | AE1: Uses SLM/CSA practices | AF1: Type of land SLM/CSA is being practiced | AG1: Types of SLM/CSA technologies practiced at hh | AH1: Qty of SLM structured created | AI1: Estimated area of land technologies have been applied | AJ1: Estimated increase in crop yields (specify crop and increase in yield) | AK1: Other observed benefits from application of SLM/CSA technologies | AL1: Main productive assets acquired during the course of the project2 | AM1: Type of land SLM/CSA is being practiced | AN1: Types of SLM/CSA technologies practiced at hh | AO1: Qty of SLM structured created | AP1: Estimated area of land technologies have been applied | AQ1: Estimated increase in crop yields (specify crop and increase in yield) | AR1: Other observed benefits from application of SLM/CSA technologies | AS1: Main productive assets acquired during the course of the project2
I942: 2021

Sheet indv savings
J2: Main reason for saving | K2: Main source (s) of income for saving saved | L2: Cycle 1 Action Audit and share out summary | V2: Monthly savings for cycle 2 (UGX)
L3: Share/stamp value (UGX) | M3: Total # of shares bought during the cycle | N3: Total # of shared redeemed | O3: Net # of shares at the end of the cycle | P3: Profits per share | Q3: New share value plus profits | R3: Total amout to be paid out to each member | S3: #/value of share carried forward to next cycle | T3: Total Welfare contributions | V3: Share/stamp value (UGX) | W3: Month 1 | AB3: Month 2 | AF3: Month 3 | AJ3: Month 4 | AN3: Month 5 | AR3: Month 6 | AV3: Month 7 | AZ3: Month 8 | BD3: Month 9 | BH3: Month 10 | BL3: Month 11 | BP3: Month 12 | BT3: Action Audit and share out summary
A4: ID No | B4: District | C4: Sub county | D4: Parish | E4: Home Village | F4: Group Name | G4: Name Of Beneficiary | H4: Sex | I4: NIN | U4: NEW CYCLE OR OLD CYCLE IF NOT SHARED OUT | W4: Date | X4: # of shares at start of the month | Y4: Shares bought during the month | Z4: Redeemed during the month | AA4: Net shares at end of the month | AB4: # of shares at start of the month | AC4: Shares bought during the month | AD4: Redeemed during the month | AE4: Net shares at end of the month | AF4: # of shares at start of the month | AG4: Shares bought during the month | AH4: Redeemed during the month | AI4: Net shares at end of the month | AJ4: # of shares at start of the month | AK4: Shares bought during the month | AL4: Redeemed during the month | AM4: Net shares at end of the month | AN4: # of shares at start of the month | AO4: Shares bought during the month | AP4: # of shares at start of the month | AQ4: Net shares at end of the month | AR4: # of shares at start of the month | AS4: Shares bought during the month | AT4: Redeemed during the month | AU4: Net shares at end of the month | AV4: # of shares at start of the month | AW4: Shares bought during the month | AX4: Redeemed during the month | AY4: Net shares at end of the month | AZ4: # of shares at start of the month | BA4: Shares bought during the month | BB4: Redeemed during the month | BC4: Net shares at end of the month | BD4: # of shares at start of the month | BE4: Shares bought during the month | BF4: Redeemed during the month | BG4: Net shares at end of the month | BH4: # of shares at start of the month | BI4: Shares bought during the month | BJ4: 0 | BK4: Net # of shares at the end of the cycle | BL4: # of shares at start of the month | BM4: Shares bought during the month | BN4: 0 | BO4: Net # of shares at the end of the cycle | BP4: # of shares at start of the month | BQ4: Shares bought during the month | BR4: Redeemed during the month | BS4: Net # of shares at the end of the cycle | BT4: Net # of shares at the end of the cycle | BU4: Profits per share | BV4: New share value plus profits | BW4: Total amout to be paid out to each member | BX4: Date for share out | BY4: #/value of share carried forward to next cycle | BZ4: Welfare contribution

Sheet Group-Savings
K67: 686 | L67: 1214 | M67: 1900 | O67: 117 | P67: 363 | Q67: 540 | R67: 32.61 | T67: 26633 | AC67: =Z67-AB67 -> 0 | AE67: =AC67/V67 -> #DIV/0! | AJ67: =S67+AE67 -> #DIV/0! | AL67: =AJ67*V67 -> #DIV/0! | AN67: =AL67-AM67 -> #DIV/0! | AO67: 0 | AW67: =SUM(AU67:AV67) -> 0 | BB67: =(AY67+AZ67)-BA67 -> 0 | BD67: =BB67 -> 0 | BG67: =(BD67+BE67)-BF67 -> 0 | BI67: =BG67 -> 0 | BL67: =(BI67+BJ67)-BK67 -> 0 | BN67: =BL67 -> 0 | BQ67: =(BN67+BO67)-BP67 -> 0 | BS67: =BQ67 -> 0 | BV67: =(BS67+BT67)-BU67 -> 0 | BX67: =BV67 -> 0 | CA67: =(BX67+BY67)-BZ67 -> 0 | CC67: =CA67 -> 0 | CF67: =(CC67+CD67)-CE67 -> 0 | CH67: =CF67 -> 0 | CK67: =(CH67+CI67)-CJ67 -> 0 | CM67: =CK67 -> 0 | CP67: =(CM67+CN67)-CO67 -> 0 | CR67: =CP67 -> 0 | CU67: =(CR67+CS67)-CT67 -> 0 | CW67: =CU67 -> 0 | CZ67: =(CW67+CX67)-CY67 -> 0 | DB67: =CZ67 -> 0 | DE67: =(DB67+DC67)-DD67 -> 0 | DI67: =DE67 -> 0 | DJ67: =DI67*AX67 -> 0 | DM67: =DK67+DL67 -> 0 | DP67: =DM67-DO67 -> 0
N68: Actuals | O68: 217 | P68: 653 | Q68: 870 | T68: 41688

Sheet Group-Loans
AM1: Kotido sub county
A2: ID No | B2: LoA | C2: IPName | D2: Project | E2: District | F2: Subcounty | G2: Parish | H2: Village | I2: FFS Name | K2: Group membership | N2: Savings start Date | O2: # of Weeks | P2: Members Saving | S2: Interest Rate (%) | AA2: CYCLE 2 OR CYCLE 1 IF NOT SHARED OUT | AB2: Start date for loaning | AC2: # Members borrowing | AG2: Month 1 | AM2: Month 2 | AS2: Month 3 | AY2: Month 4 | BE2: Month 5 | BK2: Month 6 | BQ2: Month 7 | BW2: Month 8 | CC2: Month 9 | CI2: Month 10 | CO2: Month 11 | CU2: Month 12 | DA2: Action audit summary
J3: FFS status | K3: Male | L3: Female | N3: Loaning start date | O3: Saved from inception | R3: Total | T3: Total # of loans issued during the cycle | U3: Total value of Loans disbursed during the cycle1 (A) | V3: Total monthly Interest earned during cycle 1 (B) | W3: Total value of loans issued during cycle 1 (A+B=D) | X3: Total loan amounts recovered during cycle 1 [E] | Y3: Calculated Total outstanding loan amounts not recovered at end of the cycle [D-E) | Z3: Actual Total outstanding loan amounts not yet recovered | AC3: Male | AD3: Female | AE3: Total | AF3: Interest rate (R) | AG3: # of loans disbursed during the month | AH3: Total value of Loans disbursed during the month (A) | AI3: Total monthly Interest for loans issued during the month (B) | AJ3: Total value of loans issued during the month (A+B=D) | AK3: Total loan amount recovered during the month [E] | AL3: Total outstanding loan amounts carried forward [D-E) | AM3: # of loans disbursed during the month | AN3: Total value of Loans disbursed during the month (A) | AO3: Total monthly Interest for loans issued during the month (B) | AP3: Total value of loans issued during the month (A+B=D) | AQ3: Total loan amount recovered during the month [E] | AR3: Total outstanding loan amounts carried forward [D-E) | AS3: # of loans disbursed during the month | AT3: Total value of Loans disbursed during the month (A) | AU3: Total monthly Interest for loans issued during the month (B) | AV3: Total value of loans issued during the month (A+B=D) | AW3: Total loan amount recovered during the month [E] | AX3: Total outstanding loan amounts carried forward [D-E) | AY3: # of loans disbursed during the month | AZ3: Total value of Loans disbursed during the month (A) | BA3: Total monthly Interest for loans issued during the month (B) | BB3: Total value of loans issued during the month (A+B=D) | BC3: Total loan amount recovered during the month [E] | BD3: Total outstanding loan amounts carried forward [D-E) | BE3: # of loans disbursed during the month | BF3: Total value of Loans disbursed during the month (A) | BG3: Total monthly Interest for loans issued during the month (B) | BH3: Total value of loans issued during the month (A+B=D) | BI3: Total loan amount recovered during the month [E] | BJ3: Total outstanding loan amounts carried forward [D-E) | BK3: # of loans disbursed during the month | BL3: Total value of Loans disbursed during the month (A) | BM3: Total monthly Interest for loans issued during the month (B) | BN3: Total value of loans issued during the month (A+B=D) | BO3: Total loan amount recovered during the month [E] | BP3: Total outstanding loan amounts carried forward [D-E) | BQ3: # of loans disbursed during the month | BR3: Total value of Loans disbursed during the month (A) | BS3: Total monthly Interest for loans issued during the month (B) | BT3: Total value of loans issued during the month (A+B=D) | BU3: Total loan amount recovered during the month [E] | BV3: Total outstanding loan amounts carried forward [D-E) | BW3: # of loans disbursed during the month | BX3: Total value of Loans disbursed during the month (A) | BY3: Total monthly Interest for loans issued during the month (B) | BZ3: Total value of loans issued during the month (A+B=D) | CA3: Total loan amount recovered during the month [E] | CB3: Total outstanding loan amounts carried forward [D-E) | CC3: # of loans disbursed during the month | CD3: Total value of Loans disbursed during the month (A) | CE3: Total monthly Interest for loans issued during the month (B) | CF3: Total value of loans issued during the month (A+B=D) | CG3: Total loan amount recovered during the month [E] | CH3: Total outstanding loan amounts carried forward [D-E) | CI3: # of loans disbursed during the month | CJ3: Total value of Loans disbursed during the month (A) | CK3: Total monthly Interest for loans issued during the month (B) | CL3: Total value of loans issued during the month (A+B=D) | CM3: Total loan amount recovered during the month [E] | CN3: Total outstanding loan amounts carried forward [D-E) | CO3: # of loans disbursed during the month | CP3: Total value of Loans disbursed during the month (A) | CQ3: Total monthly Interest for loans issued during the month (B) | CR3: Total value of loans issued during the month (A+B=D) | CS3: Total loan amount recovered during the month [E] | CT3: Total outstanding loan amounts carried forward [D-E) | CU3: # of loans disbursed during the month | CV3: Total value of Loans disbursed during the month (A) | CW3: Total monthly Interest for loans issued during the month (B) | CX3: Total value of loans issued during the month (A+B=D) | CY3: Total loan amount recovered during the month [E] | CZ3: Total outstanding loan amounts carried forward [D-E) | DA3: Total # of loans issued during the cycle | DB3: Cumulative value of Loans disbursed during the cycle1 (A) | DC3: Cumulative monthly Interest earned during cycle 1 (B) | DD3: Cumulative value of loans issued during cycle 1 (A+B=D) | DE3: Cumulative loan amounts recovered during cycle 1 [E] | DF3: Cumulative value of outstanding loan amounts not recovered at end of the cycle [D-E)
A4: ='Group-Savings'!A4 -> 0 | B4: ='Group-Savings'!B4 -> 0 | C4: ='Group-Savings'!C4 -> 0 | D4: ='Group-Savings'!D4 -> 0 | E4: ='Group-Savings'!E4 -> 0 | F4: ='Group-Savings'!F4 -> 0 | G4: ='Group-Savings'!G4 -> 0 | H4: ='Group-Savings'!H4 -> 0 | ... L4: ='Group-Savings'!L4 -> 0 | M4: =K4+L4 -> 0 | O4: 52 | R4: 24 | S4: 10 | U4: 0 | V4: =S4*U4 -> 0 | W4: 1090900 | X4: 1090900 | Y4: =W4-X4 -> 0 | Z4: 198000 | AI4: =$AF$4*AH4 -> 0 | AJ4: =AH4+AI4 -> 0 | AL4: =AJ4-AK4 -> 0 | AO4: =$AF$4*AN4 -> 0 | AP4: =AN4+AO4 -> 0 | AR4: =(AP4-AQ4)+AL4 -> 0 | AU4: =$AF$4*AT4 -> 0 | AV4: =AT4+AU4 -> 0 | AX4: =(AV4-AW4)+AR4 -> 0 | BA4: =$AF$4*AZ4 -> 0 | BB4: =AZ4+BA4 -> 0 | BD4: =(BB4-BC4)+AX4 -> 0 | BG4: =$AF$4*BF4 -> 0 | BH4: =BF4+BG4 -> 0 | BJ4: =(BH4-BI4)+BD4 -> 0 | BM4: =$AF$4*BL4 -> 0 | BN4: =BL4+BM4 -> 0 | BP4: =(BN4-BO4)+BJ4 -> 0 | BS4: =$AF$4*BR4 -> 0 | BT4: =BR4+BS4 -> 0 | BV4: =(BT4-BU4)+BP4 -> 0 | BY4: =$AF$4*BX4 -> 0 | BZ4: =BX4+BY4 -> 0 | CB4: =(BZ4-CA4)+BV4 -> 0 | CE4: =$AF$4*CD4 -> 0 | CF4: =CD4+CE4 -> 0 | CH4: =(CF4-CG4)+CB4 -> 0 | CK4: =$AF$4*CJ4 -> 0 | CL4: =CJ4+CK4 -> 0 | CN4: =(CL4-CM4)+CH4 -> 0 | CQ4: =$AF$4*CP4 -> 0 | CR4: =CP4+CQ4 -> 0 | CT4: =(CR4-CS4)+CN4 -> 0 | CW4: =$AF$4*CV4 -> 0 | CX4: =CV4+CW4 -> 0 | CZ4: =(CX4-CY4)+CT4 -> 0 | DA4: =SUM(AG4,AM4,AS4,AY4,BE4,BK4,BQ4,BW4,CC4,CI4,CO4,CU4) -> 0 | DB4: =SUM(AH4,AN4,AT4,AZ4,BF4,BL4,BR4,BX4,CD4,CJ4,CP4,CV4) -> 0 | DC4: =SUM(AI4,AO4,AU4,BA4,BG4,BM4,BS4,BY4,CE4,CK4,CQ4,CW4) -> 0 | DD4: =SUM(AJ4,AP4,AV4,BB4,BH4,BN4,BT4,BZ4,CF4,CL4,CR4,CX4) -> 0 | DE4: =SUM(AK4,AQ4,AW4,BC4,BI4,BO4,BU4,CA4,CG4,CM4,CS4,CY4) -> 0 | DF4: =CZ4 -> 0
A5: ='Group-Savings'!A5 -> 0 | B5: ='Group-Savings'!B5 -> 0 | C5: ='Group-Savings'!C5 -> 0 | D5: ='Group-Savings'!D5 -> 0 | E5: ='Group-Savings'!E5 -> 0 | F5: ='Group-Savings'!F5 -> 0 | G5: ='Group-Savings'!G5 -> 0 | H5: ='Group-Savings'!H5 -> 0 | ... L5: ='Group-Savings'!L5 -> 0 | M5: =K5+L5 -> 0 | O5: 31 | R5: 12 | S5: 10 | U5: 0 | V5: =S5*U5 -> 0 | W5: 400000 | X5: 400000 | Y5: =W5-X5 -> 0 | Z5: 92000 | AI5: =$AF$5*AH5 -> 0 | AJ5: =AH5+AI5 -> 0 | AL5: =AJ5-AK5 -> 0 | AO5: =$AF$5*AN5 -> 0 | AP5: =AN5+AO5 -> 0 | AR5: =(AP5-AQ5)+AL5 -> 0 | AU5: =$AF$5*AT5 -> 0 | AV5: =AT5+AU5 -> 0 | AX5: =(AV5-AW5)+AR5 -> 0 | BA5: =$AF$5*AZ5 -> 0 | BB5: =AZ5+BA5 -> 0 | BD5: =(BB5-BC5)+AX5 -> 0 | BG5: =$AF$5*BF5 -> 0 | BH5: =BF5+BG5 -> 0 | BJ5: =(BH5-BI5)+BD5 -> 0 | BM5: =$AF$5*BL5 -> 0 | BN5: =BL5+BM5 -> 0 | BP5: =(BN5-BO5)+BJ5 -> 0 | BS5: =$AF$5*BR5 -> 0 | BT5: =BR5+BS5 -> 0 | BV5: =(BT5-BU5)+BP5 -> 0 | BY5: =$AF$5*BX5 -> 0 | BZ5: =BX5+BY5 -> 0 | CB5: =(BZ5-CA5)+BV5 -> 0 | CE5: =$AF$5*CD5 -> 0 | CF5: =CD5+CE5 -> 0 | CH5: =(CF5-CG5)+CB5 -> 0 | CK5: =$AF$5*CJ5 -> 0 | CL5: =CJ5+CK5 -> 0 | CN5: =(CL5-CM5)+CH5 -> 0 | CQ5: =$AF$5*CP5 -> 0 | CR5: =CP5+CQ5 -> 0 | CT5: =(CR5-CS5)+CN5 -> 0 | CW5: =$AF$5*CV5 -> 0 | CX5: =CV5+CW5 -> 0 | CZ5: =(CX5-CY5)+CT5 -> 0 | DA5: =SUM(AG5,AM5,AS5,AY5,BE5,BK5,BQ5,BW5,CC5,CI5,CO5,CU5) -> 0 | DB5: =SUM(AH5,AN5,AT5,AZ5,BF5,BL5,BR5,BX5,CD5,CJ5,CP5,CV5) -> 0 | DC5: =SUM(AI5,AO5,AU5,BA5,BG5,BM5,BS5,BY5,CE5,CK5,CQ5,CW5) -> 0 | DD5: =SUM(AJ5,AP5,AV5,BB5,BH5,BN5,BT5,BZ5,CF5,CL5,CR5,CX5) -> 0 | DE5: =SUM(AK5,AQ5,AW5,BC5,BI5,BO5,BU5,CA5,CG5,CM5,CS5,CY5) -> 0 | DF5: =CZ5 -> 0
A6: ='Group-Savings'!A6 -> 0 | B6: ='Group-Savings'!B6 -> 0 | C6: ='Group-Savings'!C6 -> 0 | D6: ='Group-Savings'!D6 -> 0 | E6: ='Group-Savings'!E6 -> 0 | F6: ='Group-Savings'!F6 -> 0 | G6: ='Group-Savings'!G6 -> 0 | H6: ='Group-Savings'!H6 -> 0 | ... L6: ='Group-Savings'!L6 -> 0 | M6: =K6+L6 -> 0 | O6: 52 | R6: 22 | S6: 10 | V6: =S6*U6 -> 0 | W6: 1990500 | X6: 650000 | Y6: =W6-X6 -> 1340500 | Z6: 124000 | AI6: =$AF$6*AH6 -> 0 | AJ6: =AH6+AI6 -> 0 | AL6: =AJ6-AK6 -> 0 | AO6: =$AF$6*AN6 -> 0 | AP6: =AN6+AO6 -> 0 | AR6: =(AP6-AQ6)+AL6 -> 0 | AU6: =$AF$6*AT6 -> 0 | AV6: =AT6+AU6 -> 0 | AX6: =(AV6-AW6)+AR6 -> 0 | BA6: =$AF$6*AZ6 -> 0 | BB6: =AZ6+BA6 -> 0 | BD6: =(BB6-BC6)+AX6 -> 0 | BG6: =$AF$6*BF6 -> 0 | BH6: =BF6+BG6 -> 0 | BJ6: =(BH6-BI6)+BD6 -> 0 | BM6: =$AF$6*BL6 -> 0 | BN6: =BL6+BM6 -> 0 | BP6: =(BN6-BO6)+BJ6 -> 0 | BS6: =$AF$6*BR6 -> 0 | BT6: =BR6+BS6 -> 0 | BV6: =(BT6-BU6)+BP6 -> 0 | BY6: =$AF$6*BX6 -> 0 | BZ6: =BX6+BY6 -> 0 | CB6: =(BZ6-CA6)+BV6 -> 0 | CE6: =$AF$6*CD6 -> 0 | CF6: =CD6+CE6 -> 0 | CH6: =(CF6-CG6)+CB6 -> 0 | CK6: =$AF$6*CJ6 -> 0 | CL6: =CJ6+CK6 -> 0 | CN6: =(CL6-CM6)+CH6 -> 0 | CQ6: =$AF$6*CP6 -> 0 | CR6: =CP6+CQ6 -> 0 | CT6: =(CR6-CS6)+CN6 -> 0 | CW6: =$AF$6*CV6 -> 0 | CX6: =CV6+CW6 -> 0 | CZ6: =(CX6-CY6)+CT6 -> 0 | DA6: =SUM(AG6,AM6,AS6,AY6,BE6,BK6,BQ6,BW6,CC6,CI6,CO6,CU6) -> 0 | DB6: =SUM(AH6,AN6,AT6,AZ6,BF6,BL6,BR6,BX6,CD6,CJ6,CP6,CV6) -> 0 | DC6: =SUM(AI6,AO6,AU6,BA6,BG6,BM6,BS6,BY6,CE6,CK6,CQ6,CW6) -> 0 | DD6: =SUM(AJ6,AP6,AV6,BB6,BH6,BN6,BT6,BZ6,CF6,CL6,CR6,CX6) -> 0 | DE6: =SUM(AK6,AQ6,AW6,BC6,BI6,BO6,BU6,CA6,CG6,CM6,CS6,CY6) -> 0 | DF6: =CZ6 -> 0
A7: ='Group-Savings'!A7 -> 0 | B7: ='Group-Savings'!B7 -> 0 | C7: ='Group-Savings'!C7 -> 0 | D7: ='Group-Savings'!D7 -> 0 | E7: ='Group-Savings'!E7 -> 0 | F7: ='Group-Savings'!F7 -> 0 | G7: ='Group-Savings'!G7 -> 0 | H7: ='Group-Savings'!H7 -> 0 | ... L7: ='Group-Savings'!L7 -> 0 | M7: =K7+L7 -> 0 | O7: 17 | R7: 20 | S7: 10 | U7: 0 | V7: =S7*U7 -> 0 | W7: 730000 | X7: 730000 | Y7: =W7-X7 -> 0 | Z7: 80000 | AI7: =$AF$7*AH7 -> 0 | AJ7: =AH7+AI7 -> 0 | AL7: =AJ7-AK7 -> 0 | AO7: =$AF$7*AN7 -> 0 | AP7: =AN7+AO7 -> 0 | AR7: =(AP7-AQ7)+AL7 -> 0 | AU7: =$AF$7*AT7 -> 0 | AV7: =AT7+AU7 -> 0 | AX7: =(AV7-AW7)+AR7 -> 0 | BA7: =$AF$7*AZ7 -> 0 | BB7: =AZ7+BA7 -> 0 | BD7: =(BB7-BC7)+AX7 -> 0 | BG7: =$AF$7*BF7 -> 0 | BH7: =BF7+BG7 -> 0 | BJ7: =(BH7-BI7)+BD7 -> 0 | BM7: =$AF$7*BL7 -> 0 | BN7: =BL7+BM7 -> 0 | BP7: =(BN7-BO7)+BJ7 -> 0 | BS7: =$AF$7*BR7 -> 0 | BT7: =BR7+BS7 -> 0 | BV7: =(BT7-BU7)+BP7 -> 0 | BY7: =$AF$7*BX7 -> 0 | BZ7: =BX7+BY7 -> 0 | CB7: =(BZ7-CA7)+BV7 -> 0 | CE7: =$AF$7*CD7 -> 0 | CF7: =CD7+CE7 -> 0 | CH7: =(CF7-CG7)+CB7 -> 0 | CK7: =$AF$7*CJ7 -> 0 | CL7: =CJ7+CK7 -> 0 | CN7: =(CL7-CM7)+CH7 -> 0 | CQ7: =$AF$7*CP7 -> 0 | CR7: =CP7+CQ7 -> 0 | CT7: =(CR7-CS7)+CN7 -> 0 | CW7: =$AF$7*CV7 -> 0 | CX7: =CV7+CW7 -> 0 | CZ7: =(CX7-CY7)+CT7 -> 0 | DA7: =SUM(AG7,AM7,AS7,AY7,BE7,BK7,BQ7,BW7,CC7,CI7,CO7,CU7) -> 0 | DB7: =SUM(AH7,AN7,AT7,AZ7,BF7,BL7,BR7,BX7,CD7,CJ7,CP7,CV7) -> 0 | DC7: =SUM(AI7,AO7,AU7,BA7,BG7,BM7,BS7,BY7,CE7,CK7,CQ7,CW7) -> 0 | DD7: =SUM(AJ7,AP7,AV7,BB7,BH7,BN7,BT7,BZ7,CF7,CL7,CR7,CX7) -> 0 | DE7: =SUM(AK7,AQ7,AW7,BC7,BI7,BO7,BU7,CA7,CG7,CM7,CS7,CY7) -> 0 | DF7: =CZ7 -> 0
A8: ='Group-Savings'!A8 -> 0 | B8: ='Group-Savings'!B8 -> 0 | C8: ='Group-Savings'!C8 -> 0 | D8: ='Group-Savings'!D8 -> 0 | E8: ='Group-Savings'!E8 -> 0 | F8: ='Group-Savings'!F8 -> 0 | G8: ='Group-Savings'!G8 -> 0 | H8: ='Group-Savings'!H8 -> 0 | ... L8: ='Group-Savings'!L8 -> 0 | M8: =K8+L8 -> 0 | O8: 32 | R8: 18 | S8: 10 | V8: =S8*U8 -> 0 | W8: 3000000 | X8: 150000 | Y8: =W8-X8 -> 2850000 | Z8: 120000 | AI8: =$AF$8*AH8 -> 0 | AJ8: =AH8+AI8 -> 0 | AL8: =AJ8-AK8 -> 0 | AO8: =$AF$8*AN8 -> 0 | AP8: =AN8+AO8 -> 0 | AR8: =(AP8-AQ8)+AL8 -> 0 | AU8: =$AF$8*AT8 -> 0 | AV8: =AT8+AU8 -> 0 | AX8: =(AV8-AW8)+AR8 -> 0 | BA8: =$AF$8*AZ8 -> 0 | BB8: =AZ8+BA8 -> 0 | BD8: =(BB8-BC8)+AX8 -> 0 | BG8: =$AF$8*BF8 -> 0 | BH8: =BF8+BG8 -> 0 | BJ8: =(BH8-BI8)+BD8 -> 0 | BM8: =$AF$8*BL8 -> 0 | BN8: =BL8+BM8 -> 0 | BP8: =(BN8-BO8)+BJ8 -> 0 | BS8: =$AF$8*BR8 -> 0 | BT8: =BR8+BS8 -> 0 | BV8: =(BT8-BU8)+BP8 -> 0 | BY8: =$AF$8*BX8 -> 0 | BZ8: =BX8+BY8 -> 0 | CB8: =(BZ8-CA8)+BV8 -> 0 | CE8: =$AF$8*CD8 -> 0 | CF8: =CD8+CE8 -> 0 | CH8: =(CF8-CG8)+CB8 -> 0 | CK8: =$AF$8*CJ8 -> 0 | CL8: =CJ8+CK8 -> 0 | CN8: =(CL8-CM8)+CH8 -> 0 | CQ8: =$AF$8*CP8 -> 0 | CR8: =CP8+CQ8 -> 0 | CT8: =(CR8-CS8)+CN8 -> 0 | CW8: =$AF$8*CV8 -> 0 | CX8: =CV8+CW8 -> 0 | CZ8: =(CX8-CY8)+CT8 -> 0 | DA8: =SUM(AG8,AM8,AS8,AY8,BE8,BK8,BQ8,BW8,CC8,CI8,CO8,CU8) -> 0 | DB8: =SUM(AH8,AN8,AT8,AZ8,BF8,BL8,BR8,BX8,CD8,CJ8,CP8,CV8) -> 0 | DC8: =SUM(AI8,AO8,AU8,BA8,BG8,BM8,BS8,BY8,CE8,CK8,CQ8,CW8) -> 0 | DD8: =SUM(AJ8,AP8,AV8,BB8,BH8,BN8,BT8,BZ8,CF8,CL8,CR8,CX8) -> 0 | DE8: =SUM(AK8,AQ8,AW8,BC8,BI8,BO8,BU8,CA8,CG8,CM8,CS8,CY8) -> 0 | DF8: =CZ8 -> 0
A9: ='Group-Savings'!A9 -> 0 | B9: ='Group-Savings'!B9 -> 0 | C9: ='Group-Savings'!C9 -> 0 | D9: ='Group-Savings'!D9 -> 0 | E9: ='Group-Savings'!E9 -> 0 | F9: ='Group-Savings'!F9 -> 0 | G9: ='Group-Savings'!G9 -> 0 | H9: ='Group-Savings'!H9 -> 0 | ... L9: ='Group-Savings'!L9 -> 0 | M9: =K9+L9 -> 0 | O9: 24 | R9: 13 | S9: 10 | V9: =S9*U9 -> 0 | W9: 300000 | X9: 300000 | Y9: =W9-X9 -> 0 | Z9: 6000 | AI9: =$AF$9*AH9 -> 0 | AJ9: =AH9+AI9 -> 0 | AL9: =AJ9-AK9 -> 0 | AO9: =$AF$9*AN9 -> 0 | AP9: =AN9+AO9 -> 0 | AR9: =(AP9-AQ9)+AL9 -> 0 | AU9: =$AF$9*AT9 -> 0 | AV9: =AT9+AU9 -> 0 | AX9: =(AV9-AW9)+AR9 -> 0 | BA9: =$AF$9*AZ9 -> 0 | BB9: =AZ9+BA9 -> 0 | BD9: =(BB9-BC9)+AX9 -> 0 | BG9: =$AF$9*BF9 -> 0 | BH9: =BF9+BG9 -> 0 | BJ9: =(BH9-BI9)+BD9 -> 0 | BM9: =$AF$9*BL9 -> 0 | BN9: =BL9+BM9 -> 0 | BP9: =(BN9-BO9)+BJ9 -> 0 | BS9: =$AF$9*BR9 -> 0 | BT9: =BR9+BS9 -> 0 | BV9: =(BT9-BU9)+BP9 -> 0 | BY9: =$AF$9*BX9 -> 0 | BZ9: =BX9+BY9 -> 0 | CB9: =(BZ9-CA9)+BV9 -> 0 | CE9: =$AF$9*CD9 -> 0 | CF9: =CD9+CE9 -> 0 | CH9: =(CF9-CG9)+CB9 -> 0 | CK9: =$AF$9*CJ9 -> 0 | CL9: =CJ9+CK9 -> 0 | CN9: =(CL9-CM9)+CH9 -> 0 | CQ9: =$AF$9*CP9 -> 0 | CR9: =CP9+CQ9 -> 0 | CT9: =(CR9-CS9)+CN9 -> 0 | CW9: =$AF$9*CV9 -> 0 | CX9: =CV9+CW9 -> 0 | CZ9: =(CX9-CY9)+CT9 -> 0 | DA9: =SUM(AG9,AM9,AS9,AY9,BE9,BK9,BQ9,BW9,CC9,CI9,CO9,CU9) -> 0 | DB9: =SUM(AH9,AN9,AT9,AZ9,BF9,BL9,BR9,BX9,CD9,CJ9,CP9,CV9) -> 0 | DC9: =SUM(AI9,AO9,AU9,BA9,BG9,BM9,BS9,BY9,CE9,CK9,CQ9,CW9) -> 0 | DD9: =SUM(AJ9,AP9,AV9,BB9,BH9,BN9,BT9,BZ9,CF9,CL9,CR9,CX9) -> 0 | DE9: =SUM(AK9,AQ9,AW9,BC9,BI9,BO9,BU9,CA9,CG9,CM9,CS9,CY9) -> 0 | DF9: =CZ9 -> 0
A10: ='Group-Savings'!A10 -> 0 | B10: ='Group-Savings'!B10 -> 0 | C10: ='Group-Savings'!C10 -> 0 | D10: ='Group-Savings'!D10 -> 0 | E10: ='Group-Savings'!E10 -> 0 | F10: ='Group-Savings'!F10 -> 0 | G10: ='Group-Savings'!G10 -> 0 | H10: ='Group-Savings'!H10 -> 0 | ... L10: ='Group-Savings'!L10 -> 0 | M10: =K10+L10 -> 0 | O10: 40 | R10: 25 | S10: 10 | V10: =S10*U10 -> 0 | W10: 14170000 | X10: 14170000 | Y10: =W10-X10 -> 0 | Z10: 300000 | AI10: =$AF$10*AH10 -> 0 | AJ10: =AH10+AI10 -> 0 | AL10: =AJ10-AK10 -> 0 | AO10: =$AF$10*AN10 -> 0 | AP10: =AN10+AO10 -> 0 | AR10: =(AP10-AQ10)+AL10 -> 0 | AU10: =$AF$10*AT10 -> 0 | AV10: =AT10+AU10 -> 0 | AX10: =(AV10-AW10)+AR10 -> 0 | BA10: =$AF$10*AZ10 -> 0 | BB10: =AZ10+BA10 -> 0 | BD10: =(BB10-BC10)+AX10 -> 0 | BG10: =$AF$10*BF10 -> 0 | BH10: =BF10+BG10 -> 0 | BJ10: =(BH10-BI10)+BD10 -> 0 | BM10: =$AF$10*BL10 -> 0 | BN10: =BL10+BM10 -> 0 | BP10: =(BN10-BO10)+BJ10 -> 0 | BS10: =$AF$10*BR10 -> 0 | BT10: =BR10+BS10 -> 0 | BV10: =(BT10-BU10)+BP10 -> 0 | BY10: =$AF$10*BX10 -> 0 | BZ10: =BX10+BY10 -> 0 | CB10: =(BZ10-CA10)+BV10 -> 0 | CE10: =$AF$10*CD10 -> 0 | CF10: =CD10+CE10 -> 0 | CH10: =(CF10-CG10)+CB10 -> 0 | CK10: =$AF$10*CJ10 -> 0 | CL10: =CJ10+CK10 -> 0 | CN10: =(CL10-CM10)+CH10 -> 0 | CQ10: =$AF$10*CP10 -> 0 | CR10: =CP10+CQ10 -> 0 | CT10: =(CR10-CS10)+CN10 -> 0 | CW10: =$AF$10*CV10 -> 0 | CX10: =CV10+CW10 -> 0 | CZ10: =(CX10-CY10)+CT10 -> 0 | DA10: =SUM(AG10,AM10,AS10,AY10,BE10,BK10,BQ10,BW10,CC10,CI10,CO10,CU10) -> 0 | DB10: =SUM(AH10,AN10,AT10,AZ10,BF10,BL10,BR10,BX10,CD10,CJ10,CP10,CV10) -> 0 | DC10: =SUM(AI10,AO10,AU10,BA10,BG10,BM10,BS10,BY10,CE10,CK10,CQ10,CW10) -> 0 | DD10: =SUM(AJ10,AP10,AV10,BB10,BH10,BN10,BT10,BZ10,CF10,CL10,CR10,CX10) -> 0 | DE10: =SUM(AK10,AQ10,AW10,BC10,BI10,BO10,BU10,CA10,CG10,CM10,CS10,CY10) -> 0 | DF10: =CZ10 -> 0
A11: ='Group-Savings'!A11 -> 0 | B11: ='Group-Savings'!B11 -> 0 | C11: ='Group-Savings'!C11 -> 0 | D11: ='Group-Savings'!D11 -> 0 | E11: ='Group-Savings'!E11 -> 0 | F11: ='Group-Savings'!F11 -> 0 | G11: ='Group-Savings'!G11 -> 0 | H11: ='Group-Savings'!H11 -> 0 | ... L11: ='Group-Savings'!L11 -> 0 | M11: =K11+L11 -> 0 | O11: 22 | R11: 17 | S11: 10 | V11: =S11*U11 -> 0 | W11: 410000 | X11: 370000 | Y11: =W11-X11 -> 40000 | Z11: 45000 | AI11: =$AF$11*AH11 -> 0 | AJ11: =AH11+AI11 -> 0 | AL11: =AJ11-AK11 -> 0 | AO11: =$AF$11*AN11 -> 0 | AP11: =AN11+AO11 -> 0 | AR11: =(AP11-AQ11)+AL11 -> 0 | AU11: =$AF$11*AT11 -> 0 | AV11: =AT11+AU11 -> 0 | AX11: =(AV11-AW11)+AR11 -> 0 | BA11: =$AF$11*AZ11 -> 0 | BB11: =AZ11+BA11 -> 0 | BD11: =(BB11-BC11)+AX11 -> 0 | BG11: =$AF$11*BF11 -> 0 | BH11: =BF11+BG11 -> 0 | BJ11: =(BH11-BI11)+BD11 -> 0 | BM11: =$AF$11*BL11 -> 0 | BN11: =BL11+BM11 -> 0 | BP11: =(BN11-BO11)+BJ11 -> 0 | BS11: =$AF$11*BR11 -> 0 | BT11: =BR11+BS11 -> 0 | BV11: =(BT11-BU11)+BP11 -> 0 | BY11: =$AF$11*BX11 -> 0 | BZ11: =BX11+BY11 -> 0 | CB11: =(BZ11-CA11)+BV11 -> 0 | CE11: =$AF$11*CD11 -> 0 | CF11: =CD11+CE11 -> 0 | CH11: =(CF11-CG11)+CB11 -> 0 | CK11: =$AF$11*CJ11 -> 0 | CL11: =CJ11+CK11 -> 0 | CN11: =(CL11-CM11)+CH11 -> 0 | CQ11: =$AF$11*CP11 -> 0 | CR11: =CP11+CQ11 -> 0 | CT11: =(CR11-CS11)+CN11 -> 0 | CW11: =$AF$11*CV11 -> 0 | CX11: =CV11+CW11 -> 0 | CZ11: =(CX11-CY11)+CT11 -> 0 | DA11: =SUM(AG11,AM11,AS11,AY11,BE11,BK11,BQ11,BW11,CC11,CI11,CO11,CU11) -> 0 | DB11: =SUM(AH11,AN11,AT11,AZ11,BF11,BL11,BR11,BX11,CD11,CJ11,CP11,CV11) -> 0 | DC11: =SUM(AI11,AO11,AU11,BA11,BG11,BM11,BS11,BY11,CE11,CK11,CQ11,CW11) -> 0 | DD11: =SUM(AJ11,AP11,AV11,BB11,BH11,BN11,BT11,BZ11,CF11,CL11,CR11,CX11) -> 0 | DE11: =SUM(AK11,AQ11,AW11,BC11,BI11,BO11,BU11,CA11,CG11,CM11,CS11,CY11) -> 0 | DF11: =CZ11 -> 0
A12: ='Group-Savings'!A12 -> 0 | B12: ='Group-Savings'!B12 -> 0 | C12: ='Group-Savings'!C12 -> 0 | D12: ='Group-Savings'!D12 -> 0 | E12: ='Group-Savings'!E12 -> 0 | F12: ='Group-Savings'!F12 -> 0 | G12: ='Group-Savings'!G12 -> 0 | H12: ='Group-Savings'!H12 -> 0 | ... L12: ='Group-Savings'!L12 -> 0 | M12: =K12+L12 -> 0 | O12: 48 | R12: 27 | S12: 10 | U12: 0 | V12: =S12*U12 -> 0 | W12: 846100 | X12: 441200 | Y12: =W12-X12 -> 404900 | Z12: 115700 | AI12: =$AF$12*AH12 -> 0 | AJ12: =AH12+AI12 -> 0 | AL12: =AJ12-AK12 -> 0 | AO12: =$AF$12*AN12 -> 0 | AP12: =AN12+AO12 -> 0 | AR12: =(AP12-AQ12)+AL12 -> 0 | AU12: =$AF$12*AT12 -> 0 | AV12: =AT12+AU12 -> 0 | AX12: =(AV12-AW12)+AR12 -> 0 | BA12: =$AF$12*AZ12 -> 0 | BB12: =AZ12+BA12 -> 0 | BD12: =(BB12-BC12)+AX12 -> 0 | BG12: =$AF$12*BF12 -> 0 | BH12: =BF12+BG12 -> 0 | BJ12: =(BH12-BI12)+BD12 -> 0 | BM12: =$AF$12*BL12 -> 0 | BN12: =BL12+BM12 -> 0 | BP12: =(BN12-BO12)+BJ12 -> 0 | BS12: =$AF$12*BR12 -> 0 | BT12: =BR12+BS12 -> 0 | BV12: =(BT12-BU12)+BP12 -> 0 | BY12: =$AF$12*BX12 -> 0 | BZ12: =BX12+BY12 -> 0 | CB12: =(BZ12-CA12)+BV12 -> 0 | CE12: =$AF$12*CD12 -> 0 | CF12: =CD12+CE12 -> 0 | CH12: =(CF12-CG12)+CB12 -> 0 | CK12: =$AF$12*CJ12 -> 0 | CL12: =CJ12+CK12 -> 0 | CN12: =(CL12-CM12)+CH12 -> 0 | CQ12: =$AF$12*CP12 -> 0 | CR12: =CP12+CQ12 -> 0 | CT12: =(CR12-CS12)+CN12 -> 0 | CW12: =$AF$12*CV12 -> 0 | CX12: =CV12+CW12 -> 0 | CZ12: =(CX12-CY12)+CT12 -> 0 | DA12: =SUM(AG12,AM12,AS12,AY12,BE12,BK12,BQ12,BW12,CC12,CI12,CO12,CU12) -> 0 | DB12: =SUM(AH12,AN12,AT12,AZ12,BF12,BL12,BR12,BX12,CD12,CJ12,CP12,CV12) -> 0 | DC12: =SUM(AI12,AO12,AU12,BA12,BG12,BM12,BS12,BY12,CE12,CK12,CQ12,CW12) -> 0 | DD12: =SUM(AJ12,AP12,AV12,BB12,BH12,BN12,BT12,BZ12,CF12,CL12,CR12,CX12) -> 0 | DE12: =SUM(AK12,AQ12,AW12,BC12,BI12,BO12,BU12,CA12,CG12,CM12,CS12,CY12) -> 0 | DF12: =CZ12 -> 0
A13: ='Group-Savings'!A13 -> 0 | B13: ='Group-Savings'!B13 -> 0 | C13: ='Group-Savings'!C13 -> 0 | D13: ='Group-Savings'!D13 -> 0 | E13: ='Group-Savings'!E13 -> 0 | F13: ='Group-Savings'!F13 -> 0 | G13: ='Group-Savings'!G13 -> 0 | H13: ='Group-Savings'!H13 -> 0 | ... L13: ='Group-Savings'!L13 -> 0 | M13: =K13+L13 -> 0 | O13: 24 | R13: 25 | S13: 10 | V13: =S13*U13 -> 0 | W13: 566100 | X13: 63900 | Y13: =W13-X13 -> 502200 | Z13: 51000 | AI13: =$AF$13*AH13 -> 0 | AJ13: =AH13+AI13 -> 0 | AL13: =AJ13-AK13 -> 0 | AO13: =$AF$13*AN13 -> 0 | AP13: =AN13+AO13 -> 0 | AR13: =(AP13-AQ13)+AL13 -> 0 | AU13: =$AF$13*AT13 -> 0 | AV13: =AT13+AU13 -> 0 | AX13: =(AV13-AW13)+AR13 -> 0 | BA13: =$AF$13*AZ13 -> 0 | BB13: =AZ13+BA13 -> 0 | BD13: =(BB13-BC13)+AX13 -> 0 | BG13: =$AF$13*BF13 -> 0 | BH13: =BF13+BG13 -> 0 | BJ13: =(BH13-BI13)+BD13 -> 0 | BM13: =$AF$13*BL13 -> 0 | BN13: =BL13+BM13 -> 0 | BP13: =(BN13-BO13)+BJ13 -> 0 | BS13: =$AF$13*BR13 -> 0 | BT13: =BR13+BS13 -> 0 | BV13: =(BT13-BU13)+BP13 -> 0 | BY13: =$AF$13*BX13 -> 0 | BZ13: =BX13+BY13 -> 0 | CB13: =(BZ13-CA13)+BV13 -> 0 | CE13: =$AF$13*CD13 -> 0 | CF13: =CD13+CE13 -> 0 | CH13: =(CF13-CG13)+CB13 -> 0 | CK13: =$AF$13*CJ13 -> 0 | CL13: =CJ13+CK13 -> 0 | CN13: =(CL13-CM13)+CH13 -> 0 | CQ13: =$AF$13*CP13 -> 0 | CR13: =CP13+CQ13 -> 0 | CT13: =(CR13-CS13)+CN13 -> 0 | CW13: =$AF$13*CV13 -> 0 | CX13: =CV13+CW13 -> 0 | CZ13: =(CX13-CY13)+CT13 -> 0 | DA13: =SUM(AG13,AM13,AS13,AY13,BE13,BK13,BQ13,BW13,CC13,CI13,CO13,CU13) -> 0 | DB13: =SUM(AH13,AN13,AT13,AZ13,BF13,BL13,BR13,BX13,CD13,CJ13,CP13,CV13) -> 0 | DC13: =SUM(AI13,AO13,AU13,BA13,BG13,BM13,BS13,BY13,CE13,CK13,CQ13,CW13) -> 0 | DD13: =SUM(AJ13,AP13,AV13,BB13,BH13,BN13,BT13,BZ13,CF13,CL13,CR13,CX13) -> 0 | DE13: =SUM(AK13,AQ13,AW13,BC13,BI13,BO13,BU13,CA13,CG13,CM13,CS13,CY13) -> 0 | DF13: =CZ13 -> 0
A14: ='Group-Savings'!A14 -> 0 | B14: ='Group-Savings'!B14 -> 0 | C14: ='Group-Savings'!C14 -> 0 | D14: ='Group-Savings'!D14 -> 0 | E14: ='Group-Savings'!E14 -> 0 | F14: ='Group-Savings'!F14 -> 0 | G14: ='Group-Savings'!G14 -> 0 | H14: ='Group-Savings'!H14 -> 0 | ... L14: ='Group-Savings'!L14 -> 0 | M14: =K14+L14 -> 0 | O14: 32 | R14: 31 | S14: 10 | U14: 0 | V14: =S14*U14 -> 0 | W14: 822000 | X14: 213800 | Y14: =W14-X14 -> 608200 | Z14: 210000 | AI14: =$AF$14*AH14 -> 0 | AJ14: =AH14+AI14 -> 0 | AL14: =AJ14-AK14 -> 0 | AO14: =$AF$14*AN14 -> 0 | AP14: =AN14+AO14 -> 0 | AR14: =(AP14-AQ14)+AL14 -> 0 | AU14: =$AF$14*AT14 -> 0 | AV14: =AT14+AU14 -> 0 | AX14: =(AV14-AW14)+AR14 -> 0 | BA14: =$AF$14*AZ14 -> 0 | BB14: =AZ14+BA14 -> 0 | BD14: =(BB14-BC14)+AX14 -> 0 | BG14: =$AF$14*BF14 -> 0 | BH14: =BF14+BG14 -> 0 | BJ14: =(BH14-BI14)+BD14 -> 0 | BM14: =$AF$14*BL14 -> 0 | BN14: =BL14+BM14 -> 0 | BP14: =(BN14-BO14)+BJ14 -> 0 | BS14: =$AF$14*BR14 -> 0 | BT14: =BR14+BS14 -> 0 | BV14: =(BT14-BU14)+BP14 -> 0 | BY14: =$AF$14*BX14 -> 0 | BZ14: =BX14+BY14 -> 0 | CB14: =(BZ14-CA14)+BV14 -> 0 | CE14: =$AF$14*CD14 -> 0 | CF14: =CD14+CE14 -> 0 | CH14: =(CF14-CG14)+CB14 -> 0 | CK14: =$AF$14*CJ14 -> 0 | CL14: =CJ14+CK14 -> 0 | CN14: =(CL14-CM14)+CH14 -> 0 | CQ14: =$AF$14*CP14 -> 0 | CR14: =CP14+CQ14 -> 0 | CT14: =(CR14-CS14)+CN14 -> 0 | CW14: =$AF$14*CV14 -> 0 | CX14: =CV14+CW14 -> 0 | CZ14: =(CX14-CY14)+CT14 -> 0 | DA14: =SUM(AG14,AM14,AS14,AY14,BE14,BK14,BQ14,BW14,CC14,CI14,CO14,CU14) -> 0 | DB14: =SUM(AH14,AN14,AT14,AZ14,BF14,BL14,BR14,BX14,CD14,CJ14,CP14,CV14) -> 0 | DC14: =SUM(AI14,AO14,AU14,BA14,BG14,BM14,BS14,BY14,CE14,CK14,CQ14,CW14) -> 0 | DD14: =SUM(AJ14,AP14,AV14,BB14,BH14,BN14,BT14,BZ14,CF14,CL14,CR14,CX14) -> 0 | DE14: =SUM(AK14,AQ14,AW14,BC14,BI14,BO14,BU14,CA14,CG14,CM14,CS14,CY14) -> 0 | DF14: =CZ14 -> 0
A15: ='Group-Savings'!A15 -> 0 | B15: ='Group-Savings'!B15 -> 0 | C15: ='Group-Savings'!C15 -> 0 | D15: ='Group-Savings'!D15 -> 0 | E15: ='Group-Savings'!E15 -> 0 | F15: ='Group-Savings'!F15 -> 0 | G15: ='Group-Savings'!G15 -> 0 | H15: ='Group-Savings'!H15 -> 0 | ... L15: ='Group-Savings'!L15 -> 0 | M15: =K15+L15 -> 0 | O15: 49 | R15: 27 | S15: 10 | U15: 0 | V15: =S15*U15 -> 0 | W15: 955000 | X15: 955000 | Y15: =W15-X15 -> 0 | Z15: 343000 | AI15: =$AF$15*AH15 -> 0 | AJ15: =AH15+AI15 -> 0 | AL15: =AJ15-AK15 -> 0 | AO15: =$AF$15*AN15 -> 0 | AP15: =AN15+AO15 -> 0 | AR15: =(AP15-AQ15)+AL15 -> 0 | AU15: =$AF$15*AT15 -> 0 | AV15: =AT15+AU15 -> 0 | AX15: =(AV15-AW15)+AR15 -> 0 | BA15: =$AF$15*AZ15 -> 0 | BB15: =AZ15+BA15 -> 0 | BD15: =(BB15-BC15)+AX15 -> 0 | BG15: =$AF$15*BF15 -> 0 | BH15: =BF15+BG15 -> 0 | BJ15: =(BH15-BI15)+BD15 -> 0 | BM15: =$AF$15*BL15 -> 0 | BN15: =BL15+BM15 -> 0 | BP15: =(BN15-BO15)+BJ15 -> 0 | BS15: =$AF$15*BR15 -> 0 | BT15: =BR15+BS15 -> 0 | BV15: =(BT15-BU15)+BP15 -> 0 | BY15: =$AF$15*BX15 -> 0 | BZ15: =BX15+BY15 -> 0 | CB15: =(BZ15-CA15)+BV15 -> 0 | CE15: =$AF$15*CD15 -> 0 | CF15: =CD15+CE15 -> 0 | CH15: =(CF15-CG15)+CB15 -> 0 | CK15: =$AF$15*CJ15 -> 0 | CL15: =CJ15+CK15 -> 0 | CN15: =(CL15-CM15)+CH15 -> 0 | CQ15: =$AF$15*CP15 -> 0 | CR15: =CP15+CQ15 -> 0 | CT15: =(CR15-CS15)+CN15 -> 0 | CW15: =$AF$15*CV15 -> 0 | CX15: =CV15+CW15 -> 0 | CZ15: =(CX15-CY15)+CT15 -> 0 | DA15: =SUM(AG15,AM15,AS15,AY15,BE15,BK15,BQ15,BW15,CC15,CI15,CO15,CU15) -> 0 | DB15: =SUM(AH15,AN15,AT15,AZ15,BF15,BL15,BR15,BX15,CD15,CJ15,CP15,CV15) -> 0 | DC15: =SUM(AI15,AO15,AU15,BA15,BG15,BM15,BS15,BY15,CE15,CK15,CQ15,CW15) -> 0 | DD15: =SUM(AJ15,AP15,AV15,BB15,BH15,BN15,BT15,BZ15,CF15,CL15,CR15,CX15) -> 0 | DE15: =SUM(AK15,AQ15,AW15,BC15,BI15,BO15,BU15,CA15,CG15,CM15,CS15,CY15) -> 0 | DF15: =CZ15 -> 0
A16: ='Group-Savings'!A16 -> 0 | B16: ='Group-Savings'!B16 -> 0 | C16: ='Group-Savings'!C16 -> 0 | D16: ='Group-Savings'!D16 -> 0 | E16: ='Group-Savings'!E16 -> 0 | F16: ='Group-Savings'!F16 -> 0 | G16: ='Group-Savings'!G16 -> 0 | H16: ='Group-Savings'!H16 -> 0 | ... L16: ='Group-Savings'!L16 -> 0 | M16: =K16+L16 -> 0 | O16: 31 | R16: 26 | S16: 10 | U16: 0 | V16: =S16*U16 -> 0 | W16: 1190000 | X16: 1110000 | Y16: =W16-X16 -> 80000 | Z16: 230000 | AI16: =$AF$16*AH16 -> 0 | AJ16: =AH16+AI16 -> 0 | AL16: =AJ16-AK16 -> 0 | AO16: =$AF$16*AN16 -> 0 | AP16: =AN16+AO16 -> 0 | AR16: =(AP16-AQ16)+AL16 -> 0 | AU16: =$AF$16*AT16 -> 0 | AV16: =AT16+AU16 -> 0 | AX16: =(AV16-AW16)+AR16 -> 0 | BA16: =$AF$16*AZ16 -> 0 | BB16: =AZ16+BA16 -> 0 | BD16: =(BB16-BC16)+AX16 -> 0 | BG16: =$AF$16*BF16 -> 0 | BH16: =BF16+BG16 -> 0 | BJ16: =(BH16-BI16)+BD16 -> 0 | BM16: =$AF$16*BL16 -> 0 | BN16: =BL16+BM16 -> 0 | BP16: =(BN16-BO16)+BJ16 -> 0 | BS16: =$AF$16*BR16 -> 0 | BT16: =BR16+BS16 -> 0 | BV16: =(BT16-BU16)+BP16 -> 0 | BY16: =$AF$16*BX16 -> 0 | BZ16: =BX16+BY16 -> 0 | CB16: =(BZ16-CA16)+BV16 -> 0 | CE16: =$AF$16*CD16 -> 0 | CF16: =CD16+CE16 -> 0 | CH16: =(CF16-CG16)+CB16 -> 0 | CK16: =$AF$16*CJ16 -> 0 | CL16: =CJ16+CK16 -> 0 | CN16: =(CL16-CM16)+CH16 -> 0 | CQ16: =$AF$16*CP16 -> 0 | CR16: =CP16+CQ16 -> 0 | CT16: =(CR16-CS16)+CN16 -> 0 | CW16: =$AF$16*CV16 -> 0 | CX16: =CV16+CW16 -> 0 | CZ16: =(CX16-CY16)+CT16 -> 0 | DA16: =SUM(AG16,AM16,AS16,AY16,BE16,BK16,BQ16,BW16,CC16,CI16,CO16,CU16) -> 0 | DB16: =SUM(AH16,AN16,AT16,AZ16,BF16,BL16,BR16,BX16,CD16,CJ16,CP16,CV16) -> 0 | DC16: =SUM(AI16,AO16,AU16,BA16,BG16,BM16,BS16,BY16,CE16,CK16,CQ16,CW16) -> 0 | DD16: =SUM(AJ16,AP16,AV16,BB16,BH16,BN16,BT16,BZ16,CF16,CL16,CR16,CX16) -> 0 | DE16: =SUM(AK16,AQ16,AW16,BC16,BI16,BO16,BU16,CA16,CG16,CM16,CS16,CY16) -> 0 | DF16: =CZ16 -> 0
A17: ='Group-Savings'!A17 -> 0 | B17: ='Group-Savings'!B17 -> 0 | C17: ='Group-Savings'!C17 -> 0 | D17: ='Group-Savings'!D17 -> 0 | E17: ='Group-Savings'!E17 -> 0 | F17: ='Group-Savings'!F17 -> 0 | G17: ='Group-Savings'!G17 -> 0 | H17: ='Group-Savings'!H17 -> 0 | ... L17: ='Group-Savings'!L17 -> 0 | M17: =K17+L17 -> 0 | O17: 31 | R17: 21 | S17: 10 | V17: =S17*U17 -> 0 | W17: 331000 | X17: 331000 | Y17: =W17-X17 -> 0 | Z17: 95000 | AI17: =$AF$17*AH17 -> 0 | AJ17: =AH17+AI17 -> 0 | AL17: =AJ17-AK17 -> 0 | AO17: =$AF$17*AN17 -> 0 | AP17: =AN17+AO17 -> 0 | AR17: =(AP17-AQ17)+AL17 -> 0 | AU17: =$AF$17*AT17 -> 0 | AV17: =AT17+AU17 -> 0 | AX17: =(AV17-AW17)+AR17 -> 0 | BA17: =$AF$17*AZ17 -> 0 | BB17: =AZ17+BA17 -> 0 | BD17: =(BB17-BC17)+AX17 -> 0 | BG17: =$AF$17*BF17 -> 0 | BH17: =BF17+BG17 -> 0 | BJ17: =(BH17-BI17)+BD17 -> 0 | BM17: =$AF$17*BL17 -> 0 | BN17: =BL17+BM17 -> 0 | BP17: =(BN17-BO17)+BJ17 -> 0 | BS17: =$AF$17*BR17 -> 0 | BT17: =BR17+BS17 -> 0 | BV17: =(BT17-BU17)+BP17 -> 0 | BY17: =$AF$17*BX17 -> 0 | BZ17: =BX17+BY17 -> 0 | CB17: =(BZ17-CA17)+BV17 -> 0 | CE17: =$AF$17*CD17 -> 0 | CF17: =CD17+CE17 -> 0 | CH17: =(CF17-CG17)+CB17 -> 0 | CK17: =$AF$17*CJ17 -> 0 | CL17: =CJ17+CK17 -> 0 | CN17: =(CL17-CM17)+CH17 -> 0 | CQ17: =$AF$17*CP17 -> 0 | CR17: =CP17+CQ17 -> 0 | CT17: =(CR17-CS17)+CN17 -> 0 | CW17: =$AF$17*CV17 -> 0 | CX17: =CV17+CW17 -> 0 | CZ17: =(CX17-CY17)+CT17 -> 0 | DA17: =SUM(AG17,AM17,AS17,AY17,BE17,BK17,BQ17,BW17,CC17,CI17,CO17,CU17) -> 0 | DB17: =SUM(AH17,AN17,AT17,AZ17,BF17,BL17,BR17,BX17,CD17,CJ17,CP17,CV17) -> 0 | DC17: =SUM(AI17,AO17,AU17,BA17,BG17,BM17,BS17,BY17,CE17,CK17,CQ17,CW17) -> 0 | DD17: =SUM(AJ17,AP17,AV17,BB17,BH17,BN17,BT17,BZ17,CF17,CL17,CR17,CX17) -> 0 | DE17: =SUM(AK17,AQ17,AW17,BC17,BI17,BO17,BU17,CA17,CG17,CM17,CS17,CY17) -> 0 | DF17: =CZ17 -> 0
A18: ='Group-Savings'!A18 -> 0 | B18: ='Group-Savings'!B18 -> 0 | C18: ='Group-Savings'!C18 -> 0 | D18: ='Group-Savings'!D18 -> 0 | E18: ='Group-Savings'!E18 -> 0 | F18: ='Group-Savings'!F18 -> 0 | G18: ='Group-Savings'!G18 -> 0 | H18: ='Group-Savings'!H18 -> 0 | ... L18: ='Group-Savings'!L18 -> 0 | M18: =K18+L18 -> 0 | O18: 28 | R18: 19 | S18: 10 | V18: =S18*U18 -> 0 | W18: 425000 | X18: 440000 | Y18: =W18-X18 -> -15000 | Z18: 98000 | AI18: =$AF$18*AH18 -> 0 | AJ18: =AH18+AI18 -> 0 | AL18: =AJ18-AK18 -> 0 | AO18: =$AF$18*AN18 -> 0 | AP18: =AN18+AO18 -> 0 | AR18: =(AP18-AQ18)+AL18 -> 0 | AU18: =$AF$18*AT18 -> 0 | AV18: =AT18+AU18 -> 0 | AX18: =(AV18-AW18)+AR18 -> 0 | BA18: =$AF$18*AZ18 -> 0 | BB18: =AZ18+BA18 -> 0 | BD18: =(BB18-BC18)+AX18 -> 0 | BG18: =$AF$18*BF18 -> 0 | BH18: =BF18+BG18 -> 0 | BJ18: =(BH18-BI18)+BD18 -> 0 | BM18: =$AF$18*BL18 -> 0 | BN18: =BL18+BM18 -> 0 | BP18: =(BN18-BO18)+BJ18 -> 0 | BS18: =$AF$18*BR18 -> 0 | BT18: =BR18+BS18 -> 0 | BV18: =(BT18-BU18)+BP18 -> 0 | BY18: =$AF$18*BX18 -> 0 | BZ18: =BX18+BY18 -> 0 | CB18: =(BZ18-CA18)+BV18 -> 0 | CE18: =$AF$18*CD18 -> 0 | CF18: =CD18+CE18 -> 0 | CH18: =(CF18-CG18)+CB18 -> 0 | CK18: =$AF$18*CJ18 -> 0 | CL18: =CJ18+CK18 -> 0 | CN18: =(CL18-CM18)+CH18 -> 0 | CQ18: =$AF$18*CP18 -> 0 | CR18: =CP18+CQ18 -> 0 | CT18: =(CR18-CS18)+CN18 -> 0 | CW18: =$AF$18*CV18 -> 0 | CX18: =CV18+CW18 -> 0 | CZ18: =(CX18-CY18)+CT18 -> 0 | DA18: =SUM(AG18,AM18,AS18,AY18,BE18,BK18,BQ18,BW18,CC18,CI18,CO18,CU18) -> 0 | DB18: =SUM(AH18,AN18,AT18,AZ18,BF18,BL18,BR18,BX18,CD18,CJ18,CP18,CV18) -> 0 | DC18: =SUM(AI18,AO18,AU18,BA18,BG18,BM18,BS18,BY18,CE18,CK18,CQ18,CW18) -> 0 | DD18: =SUM(AJ18,AP18,AV18,BB18,BH18,BN18,BT18,BZ18,CF18,CL18,CR18,CX18) -> 0 | DE18: =SUM(AK18,AQ18,AW18,BC18,BI18,BO18,BU18,CA18,CG18,CM18,CS18,CY18) -> 0 | DF18: =CZ18 -> 0
A19: ='Group-Savings'!A19 -> 0 | B19: ='Group-Savings'!B19 -> 0 | C19: ='Group-Savings'!C19 -> 0 | D19: ='Group-Savings'!D19 -> 0 | E19: ='Group-Savings'!E19 -> 0 | F19: ='Group-Savings'!F19 -> 0 | G19: ='Group-Savings'!G19 -> 0 | H19: ='Group-Savings'!H19 -> 0 | ... L19: ='Group-Savings'!L19 -> 0 | M19: =K19+L19 -> 0 | O19: 52 | R19: 32 | S19: 10 | V19: =S19*U19 -> 0 | W19: 2483900 | X19: 2483900 | Y19: =W19-X19 -> 0 | Z19: 189800 | AI19: =$AF$19*AH19 -> 0 | AJ19: =AH19+AI19 -> 0 | AL19: =AJ19-AK19 -> 0 | AO19: =$AF$19*AN19 -> 0 | AP19: =AN19+AO19 -> 0 | AR19: =(AP19-AQ19)+AL19 -> 0 | AU19: =$AF$19*AT19 -> 0 | AV19: =AT19+AU19 -> 0 | AX19: =(AV19-AW19)+AR19 -> 0 | BA19: =$AF$19*AZ19 -> 0 | BB19: =AZ19+BA19 -> 0 | BD19: =(BB19-BC19)+AX19 -> 0 | BG19: =$AF$19*BF19 -> 0 | BH19: =BF19+BG19 -> 0 | BJ19: =(BH19-BI19)+BD19 -> 0 | BM19: =$AF$19*BL19 -> 0 | BN19: =BL19+BM19 -> 0 | BP19: =(BN19-BO19)+BJ19 -> 0 | BS19: =$AF$19*BR19 -> 0 | BT19: =BR19+BS19 -> 0 | BV19: =(BT19-BU19)+BP19 -> 0 | BY19: =$AF$19*BX19 -> 0 | BZ19: =BX19+BY19 -> 0 | CB19: =(BZ19-CA19)+BV19 -> 0 | CE19: =$AF$19*CD19 -> 0 | CF19: =CD19+CE19 -> 0 | CH19: =(CF19-CG19)+CB19 -> 0 | CK19: =$AF$19*CJ19 -> 0 | CL19: =CJ19+CK19 -> 0 | CN19: =(CL19-CM19)+CH19 -> 0 | CQ19: =$AF$19*CP19 -> 0 | CR19: =CP19+CQ19 -> 0 | CT19: =(CR19-CS19)+CN19 -> 0 | CW19: =$AF$19*CV19 -> 0 | CX19: =CV19+CW19 -> 0 | CZ19: =(CX19-CY19)+CT19 -> 0 | DA19: =SUM(AG19,AM19,AS19,AY19,BE19,BK19,BQ19,BW19,CC19,CI19,CO19,CU19) -> 0 | DB19: =SUM(AH19,AN19,AT19,AZ19,BF19,BL19,BR19,BX19,CD19,CJ19,CP19,CV19) -> 0 | DC19: =SUM(AI19,AO19,AU19,BA19,BG19,BM19,BS19,BY19,CE19,CK19,CQ19,CW19) -> 0 | DD19: =SUM(AJ19,AP19,AV19,BB19,BH19,BN19,BT19,BZ19,CF19,CL19,CR19,CX19) -> 0 | DE19: =SUM(AK19,AQ19,AW19,BC19,BI19,BO19,BU19,CA19,CG19,CM19,CS19,CY19) -> 0 | DF19: =CZ19 -> 0
A20: ='Group-Savings'!A20 -> 0 | B20: ='Group-Savings'!B20 -> 0 | C20: ='Group-Savings'!C20 -> 0 | D20: ='Group-Savings'!D20 -> 0 | E20: ='Group-Savings'!E20 -> 0 | F20: ='Group-Savings'!F20 -> 0 | G20: ='Group-Savings'!G20 -> 0 | H20: ='Group-Savings'!H20 -> 0 | ... L20: ='Group-Savings'!L20 -> 0 | M20: =K20+L20 -> 0 | O20: 28 | R20: 26 | S20: 10 | V20: =S20*U20 -> 0 | W20: 4775000 | X20: 4775000 | Y20: =W20-X20 -> 0 | Z20: 280000 | AI20: =$AF$20*AH20 -> 0 | AJ20: =AH20+AI20 -> 0 | AL20: =AJ20-AK20 -> 0 | AO20: =$AF$20*AN20 -> 0 | AP20: =AN20+AO20 -> 0 | AR20: =(AP20-AQ20)+AL20 -> 0 | AU20: =$AF$20*AT20 -> 0 | AV20: =AT20+AU20 -> 0 | AX20: =(AV20-AW20)+AR20 -> 0 | BA20: =$AF$20*AZ20 -> 0 | BB20: =AZ20+BA20 -> 0 | BD20: =(BB20-BC20)+AX20 -> 0 | BG20: =$AF$20*BF20 -> 0 | BH20: =BF20+BG20 -> 0 | BJ20: =(BH20-BI20)+BD20 -> 0 | BM20: =$AF$20*BL20 -> 0 | BN20: =BL20+BM20 -> 0 | BP20: =(BN20-BO20)+BJ20 -> 0 | BS20: =$AF$20*BR20 -> 0 | BT20: =BR20+BS20 -> 0 | BV20: =(BT20-BU20)+BP20 -> 0 | BY20: =$AF$20*BX20 -> 0 | BZ20: =BX20+BY20 -> 0 | CB20: =(BZ20-CA20)+BV20 -> 0 | CE20: =$AF$20*CD20 -> 0 | CF20: =CD20+CE20 -> 0 | CH20: =(CF20-CG20)+CB20 -> 0 | CK20: =$AF$20*CJ20 -> 0 | CL20: =CJ20+CK20 -> 0 | CN20: =(CL20-CM20)+CH20 -> 0 | CQ20: =$AF$20*CP20 -> 0 | CR20: =CP20+CQ20 -> 0 | CT20: =(CR20-CS20)+CN20 -> 0 | CW20: =$AF$20*CV20 -> 0 | CX20: =CV20+CW20 -> 0 | CZ20: =(CX20-CY20)+CT20 -> 0 | DA20: =SUM(AG20,AM20,AS20,AY20,BE20,BK20,BQ20,BW20,CC20,CI20,CO20,CU20) -> 0 | DB20: =SUM(AH20,AN20,AT20,AZ20,BF20,BL20,BR20,BX20,CD20,CJ20,CP20,CV20) -> 0 | DC20: =SUM(AI20,AO20,AU20,BA20,BG20,BM20,BS20,BY20,CE20,CK20,CQ20,CW20) -> 0 | DD20: =SUM(AJ20,AP20,AV20,BB20,BH20,BN20,BT20,BZ20,CF20,CL20,CR20,CX20) -> 0 | DE20: =SUM(AK20,AQ20,AW20,BC20,BI20,BO20,BU20,CA20,CG20,CM20,CS20,CY20) -> 0 | DF20: =CZ20 -> 0
A21: ='Group-Savings'!A21 -> 0 | B21: ='Group-Savings'!B21 -> 0 | C21: ='Group-Savings'!C21 -> 0 | D21: ='Group-Savings'!D21 -> 0 | E21: ='Group-Savings'!E21 -> 0 | F21: ='Group-Savings'!F21 -> 0 | G21: ='Group-Savings'!G21 -> 0 | H21: ='Group-Savings'!H21 -> 0 | ... L21: ='Group-Savings'!L21 -> 0 | M21: =K21+L21 -> 0 | O21: 10 | R21: 19 | S21: 10 | U21: 0 | V21: =S21*U21 -> 0 | W21: 6001000 | X21: 5001000 | Y21: =W21-X21 -> 1000000 | Z21: 65000 | AI21: =$AF$21*AH21 -> 0 | AJ21: =AH21+AI21 -> 0 | AL21: =AJ21-AK21 -> 0 | AO21: =$AF$21*AN21 -> 0 | AP21: =AN21+AO21 -> 0 | AR21: =(AP21-AQ21)+AL21 -> 0 | AU21: =$AF$21*AT21 -> 0 | AV21: =AT21+AU21 -> 0 | AX21: =(AV21-AW21)+AR21 -> 0 | BA21: =$AF$21*AZ21 -> 0 | BB21: =AZ21+BA21 -> 0 | BD21: =(BB21-BC21)+AX21 -> 0 | BG21: =$AF$21*BF21 -> 0 | BH21: =BF21+BG21 -> 0 | BJ21: =(BH21-BI21)+BD21 -> 0 | BM21: =$AF$21*BL21 -> 0 | BN21: =BL21+BM21 -> 0 | BP21: =(BN21-BO21)+BJ21 -> 0 | BS21: =$AF$21*BR21 -> 0 | BT21: =BR21+BS21 -> 0 | BV21: =(BT21-BU21)+BP21 -> 0 | BY21: =$AF$21*BX21 -> 0 | BZ21: =BX21+BY21 -> 0 | CB21: =(BZ21-CA21)+BV21 -> 0 | CE21: =$AF$21*CD21 -> 0 | CF21: =CD21+CE21 -> 0 | CH21: =(CF21-CG21)+CB21 -> 0 | CK21: =$AF$21*CJ21 -> 0 | CL21: =CJ21+CK21 -> 0 | CN21: =(CL21-CM21)+CH21 -> 0 | CQ21: =$AF$21*CP21 -> 0 | CR21: =CP21+CQ21 -> 0 | CT21: =(CR21-CS21)+CN21 -> 0 | CW21: =$AF$21*CV21 -> 0 | CX21: =CV21+CW21 -> 0 | CZ21: =(CX21-CY21)+CT21 -> 0 | DA21: =SUM(AG21,AM21,AS21,AY21,BE21,BK21,BQ21,BW21,CC21,CI21,CO21,CU21) -> 0 | DB21: =SUM(AH21,AN21,AT21,AZ21,BF21,BL21,BR21,BX21,CD21,CJ21,CP21,CV21) -> 0 | DC21: =SUM(AI21,AO21,AU21,BA21,BG21,BM21,BS21,BY21,CE21,CK21,CQ21,CW21) -> 0 | DD21: =SUM(AJ21,AP21,AV21,BB21,BH21,BN21,BT21,BZ21,CF21,CL21,CR21,CX21) -> 0 | DE21: =SUM(AK21,AQ21,AW21,BC21,BI21,BO21,BU21,CA21,CG21,CM21,CS21,CY21) -> 0 | DF21: =CZ21 -> 0
A22: ='Group-Savings'!A22 -> 0 | B22: ='Group-Savings'!B22 -> 0 | C22: ='Group-Savings'!C22 -> 0 | D22: ='Group-Savings'!D22 -> 0 | E22: ='Group-Savings'!E22 -> 0 | F22: ='Group-Savings'!F22 -> 0 | G22: ='Group-Savings'!G22 -> 0 | H22: ='Group-Savings'!H22 -> 0 | ... L22: ='Group-Savings'!L22 -> 0 | M22: =K22+L22 -> 0 | O22: 26 | R22: 12 | S22: 10 | V22: =S22*U22 -> 0 | W22: 275000 | X22: 275000 | Y22: =W22-X22 -> 0 | Z22: 130000 | AI22: =$AF$22*AH22 -> 0 | AJ22: =AH22+AI22 -> 0 | AL22: =AJ22-AK22 -> 0 | AO22: =$AF$22*AN22 -> 0 | AP22: =AN22+AO22 -> 0 | AR22: =(AP22-AQ22)+AL22 -> 0 | AU22: =$AF$22*AT22 -> 0 | AV22: =AT22+AU22 -> 0 | AX22: =(AV22-AW22)+AR22 -> 0 | BA22: =$AF$22*AZ22 -> 0 | BB22: =AZ22+BA22 -> 0 | BD22: =(BB22-BC22)+AX22 -> 0 | BG22: =$AF$22*BF22 -> 0 | BH22: =BF22+BG22 -> 0 | BJ22: =(BH22-BI22)+BD22 -> 0 | BM22: =$AF$22*BL22 -> 0 | BN22: =BL22+BM22 -> 0 | BP22: =(BN22-BO22)+BJ22 -> 0 | BS22: =$AF$22*BR22 -> 0 | BT22: =BR22+BS22 -> 0 | BV22: =(BT22-BU22)+BP22 -> 0 | BY22: =$AF$22*BX22 -> 0 | BZ22: =BX22+BY22 -> 0 | CB22: =(BZ22-CA22)+BV22 -> 0 | CE22: =$AF$22*CD22 -> 0 | CF22: =CD22+CE22 -> 0 | CH22: =(CF22-CG22)+CB22 -> 0 | CK22: =$AF$22*CJ22 -> 0 | CL22: =CJ22+CK22 -> 0 | CN22: =(CL22-CM22)+CH22 -> 0 | CQ22: =$AF$22*CP22 -> 0 | CR22: =CP22+CQ22 -> 0 | CT22: =(CR22-CS22)+CN22 -> 0 | CW22: =$AF$22*CV22 -> 0 | CX22: =CV22+CW22 -> 0 | CZ22: =(CX22-CY22)+CT22 -> 0 | DA22: =SUM(AG22,AM22,AS22,AY22,BE22,BK22,BQ22,BW22,CC22,CI22,CO22,CU22) -> 0 | DB22: =SUM(AH22,AN22,AT22,AZ22,BF22,BL22,BR22,BX22,CD22,CJ22,CP22,CV22) -> 0 | DC22: =SUM(AI22,AO22,AU22,BA22,BG22,BM22,BS22,BY22,CE22,CK22,CQ22,CW22) -> 0 | DD22: =SUM(AJ22,AP22,AV22,BB22,BH22,BN22,BT22,BZ22,CF22,CL22,CR22,CX22) -> 0 | DE22: =SUM(AK22,AQ22,AW22,BC22,BI22,BO22,BU22,CA22,CG22,CM22,CS22,CY22) -> 0 | DF22: =CZ22 -> 0
A23: ='Group-Savings'!A23 -> 0 | B23: ='Group-Savings'!B23 -> 0 | C23: ='Group-Savings'!C23 -> 0 | D23: ='Group-Savings'!D23 -> 0 | E23: ='Group-Savings'!E23 -> 0 | F23: ='Group-Savings'!F23 -> 0 | G23: ='Group-Savings'!G23 -> 0 | H23: ='Group-Savings'!H23 -> 0 | ... L23: ='Group-Savings'!L23 -> 0 | M23: =K23+L23 -> 0 | O23: 41 | R23: 28 | S23: 10 | V23: =S23*U23 -> 0 | W23: 1306000 | X23: 457000 | Y23: =W23-X23 -> 849000 | Z23: 490000 | AI23: =$AF$23*AH23 -> 0 | AJ23: =AH23+AI23 -> 0 | AL23: =AJ23-AK23 -> 0 | AO23: =$AF$23*AN23 -> 0 | AP23: =AN23+AO23 -> 0 | AR23: =(AP23-AQ23)+AL23 -> 0 | AU23: =$AF$23*AT23 -> 0 | AV23: =AT23+AU23 -> 0 | AX23: =(AV23-AW23)+AR23 -> 0 | BA23: =$AF$23*AZ23 -> 0 | BB23: =AZ23+BA23 -> 0 | BD23: =(BB23-BC23)+AX23 -> 0 | BG23: =$AF$23*BF23 -> 0 | BH23: =BF23+BG23 -> 0 | BJ23: =(BH23-BI23)+BD23 -> 0 | BM23: =$AF$23*BL23 -> 0 | BN23: =BL23+BM23 -> 0 | BP23: =(BN23-BO23)+BJ23 -> 0 | BS23: =$AF$23*BR23 -> 0 | BT23: =BR23+BS23 -> 0 | BV23: =(BT23-BU23)+BP23 -> 0 | BY23: =$AF$23*BX23 -> 0 | BZ23: =BX23+BY23 -> 0 | CB23: =(BZ23-CA23)+BV23 -> 0 | CE23: =$AF$23*CD23 -> 0 | CF23: =CD23+CE23 -> 0 | CH23: =(CF23-CG23)+CB23 -> 0 | CK23: =$AF$23*CJ23 -> 0 | CL23: =CJ23+CK23 -> 0 | CN23: =(CL23-CM23)+CH23 -> 0 | CQ23: =$AF$23*CP23 -> 0 | CR23: =CP23+CQ23 -> 0 | CT23: =(CR23-CS23)+CN23 -> 0 | CW23: =$AF$23*CV23 -> 0 | CX23: =CV23+CW23 -> 0 | CZ23: =(CX23-CY23)+CT23 -> 0 | DA23: =SUM(AG23,AM23,AS23,AY23,BE23,BK23,BQ23,BW23,CC23,CI23,CO23,CU23) -> 0 | DB23: =SUM(AH23,AN23,AT23,AZ23,BF23,BL23,BR23,BX23,CD23,CJ23,CP23,CV23) -> 0 | DC23: =SUM(AI23,AO23,AU23,BA23,BG23,BM23,BS23,BY23,CE23,CK23,CQ23,CW23) -> 0 | DD23: =SUM(AJ23,AP23,AV23,BB23,BH23,BN23,BT23,BZ23,CF23,CL23,CR23,CX23) -> 0 | DE23: =SUM(AK23,AQ23,AW23,BC23,BI23,BO23,BU23,CA23,CG23,CM23,CS23,CY23) -> 0 | DF23: =CZ23 -> 0
A24: ='Group-Savings'!A24 -> 0 | B24: ='Group-Savings'!B24 -> 0 | C24: ='Group-Savings'!C24 -> 0 | D24: ='Group-Savings'!D24 -> 0 | E24: ='Group-Savings'!E24 -> 0 | F24: ='Group-Savings'!F24 -> 0 | G24: ='Group-Savings'!G24 -> 0 | H24: ='Group-Savings'!H24 -> 0 | ... L24: ='Group-Savings'!L24 -> 0 | M24: =K24+L24 -> 0 | O24: 9 | R24: 7 | S24: 10 | U24: 0 | V24: =S24*U24 -> 0 | W24: 247400 | X24: 247000 | Y24: =W24-X24 -> 400 | Z24: 45000 | AI24: =$AF$24*AH24 -> 0 | AJ24: =AH24+AI24 -> 0 | AL24: =AJ24-AK24 -> 0 | AO24: =$AF$24*AN24 -> 0 | AP24: =AN24+AO24 -> 0 | AR24: =(AP24-AQ24)+AL24 -> 0 | AU24: =$AF$24*AT24 -> 0 | AV24: =AT24+AU24 -> 0 | AX24: =(AV24-AW24)+AR24 -> 0 | BA24: =$AF$24*AZ24 -> 0 | BB24: =AZ24+BA24 -> 0 | BD24: =(BB24-BC24)+AX24 -> 0 | BG24: =$AF$24*BF24 -> 0 | BH24: =BF24+BG24 -> 0 | BJ24: =(BH24-BI24)+BD24 -> 0 | BM24: =$AF$24*BL24 -> 0 | BN24: =BL24+BM24 -> 0 | BP24: =(BN24-BO24)+BJ24 -> 0 | BS24: =$AF$24*BR24 -> 0 | BT24: =BR24+BS24 -> 0 | BV24: =(BT24-BU24)+BP24 -> 0 | BY24: =$AF$24*BX24 -> 0 | BZ24: =BX24+BY24 -> 0 | CB24: =(BZ24-CA24)+BV24 -> 0 | CE24: =$AF$24*CD24 -> 0 | CF24: =CD24+CE24 -> 0 | CH24: =(CF24-CG24)+CB24 -> 0 | CK24: =$AF$24*CJ24 -> 0 | CL24: =CJ24+CK24 -> 0 | CN24: =(CL24-CM24)+CH24 -> 0 | CQ24: =$AF$24*CP24 -> 0 | CR24: =CP24+CQ24 -> 0 | CT24: =(CR24-CS24)+CN24 -> 0 | CW24: =$AF$24*CV24 -> 0 | CX24: =CV24+CW24 -> 0 | CZ24: =(CX24-CY24)+CT24 -> 0 | DA24: =SUM(AG24,AM24,AS24,AY24,BE24,BK24,BQ24,BW24,CC24,CI24,CO24,CU24) -> 0 | DB24: =SUM(AH24,AN24,AT24,AZ24,BF24,BL24,BR24,BX24,CD24,CJ24,CP24,CV24) -> 0 | DC24: =SUM(AI24,AO24,AU24,BA24,BG24,BM24,BS24,BY24,CE24,CK24,CQ24,CW24) -> 0 | DD24: =SUM(AJ24,AP24,AV24,BB24,BH24,BN24,BT24,BZ24,CF24,CL24,CR24,CX24) -> 0 | DE24: =SUM(AK24,AQ24,AW24,BC24,BI24,BO24,BU24,CA24,CG24,CM24,CS24,CY24) -> 0 | DF24: =CZ24 -> 0
A25: ='Group-Savings'!A25 -> 0 | B25: ='Group-Savings'!B25 -> 0 | C25: ='Group-Savings'!C25 -> 0 | D25: ='Group-Savings'!D25 -> 0 | E25: ='Group-Savings'!E25 -> 0 | F25: ='Group-Savings'!F25 -> 0 | G25: ='Group-Savings'!G25 -> 0 | H25: ='Group-Savings'!H25 -> 0 | ... L25: ='Group-Savings'!L25 -> 0 | M25: =K25+L25 -> 0 | O25: 47 | R25: 24 | S25: 10 | V25: =S25*U25 -> 0 | W25: 6083000 | X25: 6083000 | Y25: =W25-X25 -> 0 | Z25: 282000 | AI25: =$AF$25*AH25 -> 0 | AJ25: =AH25+AI25 -> 0 | AL25: =AJ25-AK25 -> 0 | AO25: =$AF$25*AN25 -> 0 | AP25: =AN25+AO25 -> 0 | AR25: =(AP25-AQ25)+AL25 -> 0 | AU25: =$AF$25*AT25 -> 0 | AV25: =AT25+AU25 -> 0 | AX25: =(AV25-AW25)+AR25 -> 0 | BA25: =$AF$25*AZ25 -> 0 | BB25: =AZ25+BA25 -> 0 | BD25: =(BB25-BC25)+AX25 -> 0 | BG25: =$AF$25*BF25 -> 0 | BH25: =BF25+BG25 -> 0 | BJ25: =(BH25-BI25)+BD25 -> 0 | BM25: =$AF$25*BL25 -> 0 | BN25: =BL25+BM25 -> 0 | BP25: =(BN25-BO25)+BJ25 -> 0 | BS25: =$AF$25*BR25 -> 0 | BT25: =BR25+BS25 -> 0 | BV25: =(BT25-BU25)+BP25 -> 0 | BY25: =$AF$25*BX25 -> 0 | BZ25: =BX25+BY25 -> 0 | CB25: =(BZ25-CA25)+BV25 -> 0 | CE25: =$AF$25*CD25 -> 0 | CF25: =CD25+CE25 -> 0 | CH25: =(CF25-CG25)+CB25 -> 0 | CK25: =$AF$25*CJ25 -> 0 | CL25: =CJ25+CK25 -> 0 | CN25: =(CL25-CM25)+CH25 -> 0 | CQ25: =$AF$25*CP25 -> 0 | CR25: =CP25+CQ25 -> 0 | CT25: =(CR25-CS25)+CN25 -> 0 | CW25: =$AF$25*CV25 -> 0 | CX25: =CV25+CW25 -> 0 | CZ25: =(CX25-CY25)+CT25 -> 0 | DA25: =SUM(AG25,AM25,AS25,AY25,BE25,BK25,BQ25,BW25,CC25,CI25,CO25,CU25) -> 0 | DB25: =SUM(AH25,AN25,AT25,AZ25,BF25,BL25,BR25,BX25,CD25,CJ25,CP25,CV25) -> 0 | DC25: =SUM(AI25,AO25,AU25,BA25,BG25,BM25,BS25,BY25,CE25,CK25,CQ25,CW25) -> 0 | DD25: =SUM(AJ25,AP25,AV25,BB25,BH25,BN25,BT25,BZ25,CF25,CL25,CR25,CX25) -> 0 | DE25: =SUM(AK25,AQ25,AW25,BC25,BI25,BO25,BU25,CA25,CG25,CM25,CS25,CY25) -> 0 | DF25: =CZ25 -> 0
A26: ='Group-Savings'!A26 -> 0 | B26: ='Group-Savings'!B26 -> 0 | C26: ='Group-Savings'!C26 -> 0 | D26: ='Group-Savings'!D26 -> 0 | E26: ='Group-Savings'!E26 -> 0 | F26: ='Group-Savings'!F26 -> 0 | G26: ='Group-Savings'!G26 -> 0 | H26: ='Group-Savings'!H26 -> 0 | ... L26: ='Group-Savings'!L26 -> 0 | M26: =K26+L26 -> 0 | O26: 31 | R26: 12 | S26: 10 | V26: =S26*U26 -> 0 | W26: 400000 | X26: 400000 | Y26: =W26-X26 -> 0 | Z26: 92000 | AI26: =$AF$26*AH26 -> 0 | AJ26: =AH26+AI26 -> 0 | AL26: =AJ26-AK26 -> 0 | AO26: =$AF$26*AN26 -> 0 | AP26: =AN26+AO26 -> 0 | AR26: =(AP26-AQ26)+AL26 -> 0 | AU26: =$AF$26*AT26 -> 0 | AV26: =AT26+AU26 -> 0 | AX26: =(AV26-AW26)+AR26 -> 0 | BA26: =$AF$26*AZ26 -> 0 | BB26: =AZ26+BA26 -> 0 | BD26: =(BB26-BC26)+AX26 -> 0 | BG26: =$AF$26*BF26 -> 0 | BH26: =BF26+BG26 -> 0 | BJ26: =(BH26-BI26)+BD26 -> 0 | BM26: =$AF$26*BL26 -> 0 | BN26: =BL26+BM26 -> 0 | BP26: =(BN26-BO26)+BJ26 -> 0 | BS26: =$AF$26*BR26 -> 0 | BT26: =BR26+BS26 -> 0 | BV26: =(BT26-BU26)+BP26 -> 0 | BY26: =$AF$26*BX26 -> 0 | BZ26: =BX26+BY26 -> 0 | CB26: =(BZ26-CA26)+BV26 -> 0 | CE26: =$AF$26*CD26 -> 0 | CF26: =CD26+CE26 -> 0 | CH26: =(CF26-CG26)+CB26 -> 0 | CK26: =$AF$26*CJ26 -> 0 | CL26: =CJ26+CK26 -> 0 | CN26: =(CL26-CM26)+CH26 -> 0 | CQ26: =$AF$26*CP26 -> 0 | CR26: =CP26+CQ26 -> 0 | CT26: =(CR26-CS26)+CN26 -> 0 | CW26: =$AF$26*CV26 -> 0 | CX26: =CV26+CW26 -> 0 | CZ26: =(CX26-CY26)+CT26 -> 0 | DA26: =SUM(AG26,AM26,AS26,AY26,BE26,BK26,BQ26,BW26,CC26,CI26,CO26,CU26) -> 0 | DB26: =SUM(AH26,AN26,AT26,AZ26,BF26,BL26,BR26,BX26,CD26,CJ26,CP26,CV26) -> 0 | DC26: =SUM(AI26,AO26,AU26,BA26,BG26,BM26,BS26,BY26,CE26,CK26,CQ26,CW26) -> 0 | DD26: =SUM(AJ26,AP26,AV26,BB26,BH26,BN26,BT26,BZ26,CF26,CL26,CR26,CX26) -> 0 | DE26: =SUM(AK26,AQ26,AW26,BC26,BI26,BO26,BU26,CA26,CG26,CM26,CS26,CY26) -> 0 | DF26: =CZ26 -> 0
A27: ='Group-Savings'!A27 -> 0 | B27: ='Group-Savings'!B27 -> 0 | C27: ='Group-Savings'!C27 -> 0 | D27: ='Group-Savings'!D27 -> 0 | E27: ='Group-Savings'!E27 -> 0 | F27: ='Group-Savings'!F27 -> 0 | G27: ='Group-Savings'!G27 -> 0 | H27: ='Group-Savings'!H27 -> 0 | ... L27: ='Group-Savings'!L27 -> 0 | M27: =K27+L27 -> 0 | O27: 24 | R27: 20 | S27: 10 | V27: =S27*U27 -> 0 | W27: 130000 | X27: 130000 | Y27: =W27-X27 -> 0 | Z27: 39000 | AI27: =$AF$27*AH27 -> 0 | AJ27: =AH27+AI27 -> 0 | AL27: =AJ27-AK27 -> 0 | AO27: =$AF$27*AN27 -> 0 | AP27: =AN27+AO27 -> 0 | AR27: =(AP27-AQ27)+AL27 -> 0 | AU27: =$AF$27*AT27 -> 0 | AV27: =AT27+AU27 -> 0 | AX27: =(AV27-AW27)+AR27 -> 0 | BA27: =$AF$27*AZ27 -> 0 | BB27: =AZ27+BA27 -> 0 | BD27: =(BB27-BC27)+AX27 -> 0 | BG27: =$AF$27*BF27 -> 0 | BH27: =BF27+BG27 -> 0 | BJ27: =(BH27-BI27)+BD27 -> 0 | BM27: =$AF$27*BL27 -> 0 | BN27: =BL27+BM27 -> 0 | BP27: =(BN27-BO27)+BJ27 -> 0 | BS27: =$AF$27*BR27 -> 0 | BT27: =BR27+BS27 -> 0 | BV27: =(BT27-BU27)+BP27 -> 0 | BY27: =$AF$27*BX27 -> 0 | BZ27: =BX27+BY27 -> 0 | CB27: =(BZ27-CA27)+BV27 -> 0 | CE27: =$AF$27*CD27 -> 0 | CF27: =CD27+CE27 -> 0 | CH27: =(CF27-CG27)+CB27 -> 0 | CK27: =$AF$27*CJ27 -> 0 | CL27: =CJ27+CK27 -> 0 | CN27: =(CL27-CM27)+CH27 -> 0 | CQ27: =$AF$27*CP27 -> 0 | CR27: =CP27+CQ27 -> 0 | CT27: =(CR27-CS27)+CN27 -> 0 | CW27: =$AF$27*CV27 -> 0 | CX27: =CV27+CW27 -> 0 | CZ27: =(CX27-CY27)+CT27 -> 0 | DA27: =SUM(AG27,AM27,AS27,AY27,BE27,BK27,BQ27,BW27,CC27,CI27,CO27,CU27) -> 0 | DB27: =SUM(AH27,AN27,AT27,AZ27,BF27,BL27,BR27,BX27,CD27,CJ27,CP27,CV27) -> 0 | DC27: =SUM(AI27,AO27,AU27,BA27,BG27,BM27,BS27,BY27,CE27,CK27,CQ27,CW27) -> 0 | DD27: =SUM(AJ27,AP27,AV27,BB27,BH27,BN27,BT27,BZ27,CF27,CL27,CR27,CX27) -> 0 | DE27: =SUM(AK27,AQ27,AW27,BC27,BI27,BO27,BU27,CA27,CG27,CM27,CS27,CY27) -> 0 | DF27: =CZ27 -> 0
A28: ='Group-Savings'!A28 -> 0 | B28: ='Group-Savings'!B28 -> 0 | C28: ='Group-Savings'!C28 -> 0 | D28: ='Group-Savings'!D28 -> 0 | E28: ='Group-Savings'!E28 -> 0 | F28: ='Group-Savings'!F28 -> 0 | G28: ='Group-Savings'!G28 -> 0 | H28: ='Group-Savings'!H28 -> 0 | ... L28: ='Group-Savings'!L28 -> 0 | M28: =K28+L28 -> 0 | O28: 46 | R28: 30 | S28: 10 | V28: =S28*U28 -> 0 | W28: 5960000 | X28: 5960000 | Y28: =W28-X28 -> 0 | Z28: 186000 | AI28: =$AF$28*AH28 -> 0 | AJ28: =AH28+AI28 -> 0 | AL28: =AJ28-AK28 -> 0 | AO28: =$AF$28*AN28 -> 0 | AP28: =AN28+AO28 -> 0 | AR28: =(AP28-AQ28)+AL28 -> 0 | AU28: =$AF$28*AT28 -> 0 | AV28: =AT28+AU28 -> 0 | AX28: =(AV28-AW28)+AR28 -> 0 | BA28: =$AF$28*AZ28 -> 0 | BB28: =AZ28+BA28 -> 0 | BD28: =(BB28-BC28)+AX28 -> 0 | BG28: =$AF$28*BF28 -> 0 | BH28: =BF28+BG28 -> 0 | BJ28: =(BH28-BI28)+BD28 -> 0 | BM28: =$AF$28*BL28 -> 0 | BN28: =BL28+BM28 -> 0 | BP28: =(BN28-BO28)+BJ28 -> 0 | BS28: =$AF$28*BR28 -> 0 | BT28: =BR28+BS28 -> 0 | BV28: =(BT28-BU28)+BP28 -> 0 | BY28: =$AF$28*BX28 -> 0 | BZ28: =BX28+BY28 -> 0 | CB28: =(BZ28-CA28)+BV28 -> 0 | CE28: =$AF$28*CD28 -> 0 | CF28: =CD28+CE28 -> 0 | CH28: =(CF28-CG28)+CB28 -> 0 | CK28: =$AF$28*CJ28 -> 0 | CL28: =CJ28+CK28 -> 0 | CN28: =(CL28-CM28)+CH28 -> 0 | CQ28: =$AF$28*CP28 -> 0 | CR28: =CP28+CQ28 -> 0 | CT28: =(CR28-CS28)+CN28 -> 0 | CW28: =$AF$28*CV28 -> 0 | CX28: =CV28+CW28 -> 0 | CZ28: =(CX28-CY28)+CT28 -> 0 | DA28: =SUM(AG28,AM28,AS28,AY28,BE28,BK28,BQ28,BW28,CC28,CI28,CO28,CU28) -> 0 | DB28: =SUM(AH28,AN28,AT28,AZ28,BF28,BL28,BR28,BX28,CD28,CJ28,CP28,CV28) -> 0 | DC28: =SUM(AI28,AO28,AU28,BA28,BG28,BM28,BS28,BY28,CE28,CK28,CQ28,CW28) -> 0 | DD28: =SUM(AJ28,AP28,AV28,BB28,BH28,BN28,BT28,BZ28,CF28,CL28,CR28,CX28) -> 0 | DE28: =SUM(AK28,AQ28,AW28,BC28,BI28,BO28,BU28,CA28,CG28,CM28,CS28,CY28) -> 0 | DF28: =CZ28 -> 0
A29: ='Group-Savings'!A29 -> 0 | B29: ='Group-Savings'!B29 -> 0 | C29: ='Group-Savings'!C29 -> 0 | D29: ='Group-Savings'!D29 -> 0 | E29: ='Group-Savings'!E29 -> 0 | F29: ='Group-Savings'!F29 -> 0 | G29: ='Group-Savings'!G29 -> 0 | H29: ='Group-Savings'!H29 -> 0 | ... L29: ='Group-Savings'!L29 -> 0 | M29: =K29+L29 -> 0 | O29: 31 | R29: 19 | S29: 10 | V29: =S29*U29 -> 0 | W29: 800000 | X29: 480000 | Y29: =W29-X29 -> 320000 | Z29: 120000 | AI29: =$AF$29*AH29 -> 0 | AJ29: =AH29+AI29 -> 0 | AL29: =AJ29-AK29 -> 0 | AO29: =$AF$29*AN29 -> 0 | AP29: =AN29+AO29 -> 0 | AR29: =(AP29-AQ29)+AL29 -> 0 | AU29: =$AF$29*AT29 -> 0 | AV29: =AT29+AU29 -> 0 | AX29: =(AV29-AW29)+AR29 -> 0 | BA29: =$AF$29*AZ29 -> 0 | BB29: =AZ29+BA29 -> 0 | BD29: =(BB29-BC29)+AX29 -> 0 | BG29: =$AF$29*BF29 -> 0 | BH29: =BF29+BG29 -> 0 | BJ29: =(BH29-BI29)+BD29 -> 0 | BM29: =$AF$29*BL29 -> 0 | BN29: =BL29+BM29 -> 0 | BP29: =(BN29-BO29)+BJ29 -> 0 | BS29: =$AF$29*BR29 -> 0 | BT29: =BR29+BS29 -> 0 | BV29: =(BT29-BU29)+BP29 -> 0 | BY29: =$AF$29*BX29 -> 0 | BZ29: =BX29+BY29 -> 0 | CB29: =(BZ29-CA29)+BV29 -> 0 | CE29: =$AF$29*CD29 -> 0 | CF29: =CD29+CE29 -> 0 | CH29: =(CF29-CG29)+CB29 -> 0 | CK29: =$AF$29*CJ29 -> 0 | CL29: =CJ29+CK29 -> 0 | CN29: =(CL29-CM29)+CH29 -> 0 | CQ29: =$AF$29*CP29 -> 0 | CR29: =CP29+CQ29 -> 0 | CT29: =(CR29-CS29)+CN29 -> 0 | CW29: =$AF$29*CV29 -> 0 | CX29: =CV29+CW29 -> 0 | CZ29: =(CX29-CY29)+CT29 -> 0 | DA29: =SUM(AG29,AM29,AS29,AY29,BE29,BK29,BQ29,BW29,CC29,CI29,CO29,CU29) -> 0 | DB29: =SUM(AH29,AN29,AT29,AZ29,BF29,BL29,BR29,BX29,CD29,CJ29,CP29,CV29) -> 0 | DC29: =SUM(AI29,AO29,AU29,BA29,BG29,BM29,BS29,BY29,CE29,CK29,CQ29,CW29) -> 0 | DD29: =SUM(AJ29,AP29,AV29,BB29,BH29,BN29,BT29,BZ29,CF29,CL29,CR29,CX29) -> 0 | DE29: =SUM(AK29,AQ29,AW29,BC29,BI29,BO29,BU29,CA29,CG29,CM29,CS29,CY29) -> 0 | DF29: =CZ29 -> 0
A30: ='Group-Savings'!A30 -> 0 | B30: ='Group-Savings'!B30 -> 0 | C30: ='Group-Savings'!C30 -> 0 | D30: ='Group-Savings'!D30 -> 0 | E30: ='Group-Savings'!E30 -> 0 | F30: ='Group-Savings'!F30 -> 0 | G30: ='Group-Savings'!G30 -> 0 | H30: ='Group-Savings'!H30 -> 0 | ... L30: ='Group-Savings'!L30 -> 0 | M30: =K30+L30 -> 0 | O30: 32 | R30: 11 | S30: 10 | V30: =S30*U30 -> 0 | W30: 698000 | X30: 534000 | Y30: =W30-X30 -> 164000 | Z30: 160000 | AI30: =$AF$30*AH30 -> 0 | AJ30: =AH30+AI30 -> 0 | AL30: =AJ30-AK30 -> 0 | AO30: =$AF$30*AN30 -> 0 | AP30: =AN30+AO30 -> 0 | AR30: =(AP30-AQ30)+AL30 -> 0 | AU30: =$AF$30*AT30 -> 0 | AV30: =AT30+AU30 -> 0 | AX30: =(AV30-AW30)+AR30 -> 0 | BA30: =$AF$30*AZ30 -> 0 | BB30: =AZ30+BA30 -> 0 | BD30: =(BB30-BC30)+AX30 -> 0 | BG30: =$AF$30*BF30 -> 0 | BH30: =BF30+BG30 -> 0 | BJ30: =(BH30-BI30)+BD30 -> 0 | BM30: =$AF$30*BL30 -> 0 | BN30: =BL30+BM30 -> 0 | BP30: =(BN30-BO30)+BJ30 -> 0 | BS30: =$AF$30*BR30 -> 0 | BT30: =BR30+BS30 -> 0 | BV30: =(BT30-BU30)+BP30 -> 0 | BY30: =$AF$30*BX30 -> 0 | BZ30: =BX30+BY30 -> 0 | CB30: =(BZ30-CA30)+BV30 -> 0 | CE30: =$AF$30*CD30 -> 0 | CF30: =CD30+CE30 -> 0 | CH30: =(CF30-CG30)+CB30 -> 0 | CK30: =$AF$30*CJ30 -> 0 | CL30: =CJ30+CK30 -> 0 | CN30: =(CL30-CM30)+CH30 -> 0 | CQ30: =$AF$30*CP30 -> 0 | CR30: =CP30+CQ30 -> 0 | CT30: =(CR30-CS30)+CN30 -> 0 | CW30: =$AF$30*CV30 -> 0 | CX30: =CV30+CW30 -> 0 | CZ30: =(CX30-CY30)+CT30 -> 0 | DA30: =SUM(AG30,AM30,AS30,AY30,BE30,BK30,BQ30,BW30,CC30,CI30,CO30,CU30) -> 0 | DB30: =SUM(AH30,AN30,AT30,AZ30,BF30,BL30,BR30,BX30,CD30,CJ30,CP30,CV30) -> 0 | DC30: =SUM(AI30,AO30,AU30,BA30,BG30,BM30,BS30,BY30,CE30,CK30,CQ30,CW30) -> 0 | DD30: =SUM(AJ30,AP30,AV30,BB30,BH30,BN30,BT30,BZ30,CF30,CL30,CR30,CX30) -> 0 | DE30: =SUM(AK30,AQ30,AW30,BC30,BI30,BO30,BU30,CA30,CG30,CM30,CS30,CY30) -> 0 | DF30: =CZ30 -> 0
A31: ='Group-Savings'!A31 -> 0 | B31: ='Group-Savings'!B31 -> 0 | C31: ='Group-Savings'!C31 -> 0 | D31: ='Group-Savings'!D31 -> 0 | E31: ='Group-Savings'!E31 -> 0 | F31: ='Group-Savings'!F31 -> 0 | G31: ='Group-Savings'!G31 -> 0 | H31: ='Group-Savings'!H31 -> 0 | ... L31: ='Group-Savings'!L31 -> 0 | M31: =K31+L31 -> 0 | O31: 28 | R31: 25 | S31: 10 | V31: =S31*U31 -> 0 | W31: 3945000 | X31: 3945000 | Y31: =W31-X31 -> 0 | Z31: 280000 | AI31: =$AF$31*AH31 -> 0 | AJ31: =AH31+AI31 -> 0 | AL31: =AJ31-AK31 -> 0 | AO31: =$AF$31*AN31 -> 0 | AP31: =AN31+AO31 -> 0 | AR31: =(AP31-AQ31)+AL31 -> 0 | AU31: =$AF$31*AT31 -> 0 | AV31: =AT31+AU31 -> 0 | AX31: =(AV31-AW31)+AR31 -> 0 | BA31: =$AF$31*AZ31 -> 0 | BB31: =AZ31+BA31 -> 0 | BD31: =(BB31-BC31)+AX31 -> 0 | BG31: =$AF$31*BF31 -> 0 | BH31: =BF31+BG31 -> 0 | BJ31: =(BH31-BI31)+BD31 -> 0 | BM31: =$AF$31*BL31 -> 0 | BN31: =BL31+BM31 -> 0 | BP31: =(BN31-BO31)+BJ31 -> 0 | BS31: =$AF$31*BR31 -> 0 | BT31: =BR31+BS31 -> 0 | BV31: =(BT31-BU31)+BP31 -> 0 | BY31: =$AF$31*BX31 -> 0 | BZ31: =BX31+BY31 -> 0 | CB31: =(BZ31-CA31)+BV31 -> 0 | CE31: =$AF$31*CD31 -> 0 | CF31: =CD31+CE31 -> 0 | CH31: =(CF31-CG31)+CB31 -> 0 | CK31: =$AF$31*CJ31 -> 0 | CL31: =CJ31+CK31 -> 0 | CN31: =(CL31-CM31)+CH31 -> 0 | CQ31: =$AF$31*CP31 -> 0 | CR31: =CP31+CQ31 -> 0 | CT31: =(CR31-CS31)+CN31 -> 0 | CW31: =$AF$31*CV31 -> 0 | CX31: =CV31+CW31 -> 0 | CZ31: =(CX31-CY31)+CT31 -> 0 | DA31: =SUM(AG31,AM31,AS31,AY31,BE31,BK31,BQ31,BW31,CC31,CI31,CO31,CU31) -> 0 | DB31: =SUM(AH31,AN31,AT31,AZ31,BF31,BL31,BR31,BX31,CD31,CJ31,CP31,CV31) -> 0 | DC31: =SUM(AI31,AO31,AU31,BA31,BG31,BM31,BS31,BY31,CE31,CK31,CQ31,CW31) -> 0 | DD31: =SUM(AJ31,AP31,AV31,BB31,BH31,BN31,BT31,BZ31,CF31,CL31,CR31,CX31) -> 0 | DE31: =SUM(AK31,AQ31,AW31,BC31,BI31,BO31,BU31,CA31,CG31,CM31,CS31,CY31) -> 0 | DF31: =CZ31 -> 0
A32: ='Group-Savings'!A32 -> 0 | B32: ='Group-Savings'!B32 -> 0 | C32: ='Group-Savings'!C32 -> 0 | D32: ='Group-Savings'!D32 -> 0 | E32: ='Group-Savings'!E32 -> 0 | F32: ='Group-Savings'!F32 -> 0 | G32: ='Group-Savings'!G32 -> 0 | H32: ='Group-Savings'!H32 -> 0 | ... L32: ='Group-Savings'!L32 -> 0 | M32: =K32+L32 -> 0 | O32: 34 | R32: 25 | S32: 10 | V32: =S32*U32 -> 0 | W32: 9550000 | X32: 8270000 | Y32: =W32-X32 -> 1280000 | Z32: 510000 | AI32: =$AF$32*AH32 -> 0 | AJ32: =AH32+AI32 -> 0 | AL32: =AJ32-AK32 -> 0 | AO32: =$AF$32*AN32 -> 0 | AP32: =AN32+AO32 -> 0 | AR32: =(AP32-AQ32)+AL32 -> 0 | AU32: =$AF$32*AT32 -> 0 | AV32: =AT32+AU32 -> 0 | AX32: =(AV32-AW32)+AR32 -> 0 | BA32: =$AF$32*AZ32 -> 0 | BB32: =AZ32+BA32 -> 0 | BD32: =(BB32-BC32)+AX32 -> 0 | BG32: =$AF$32*BF32 -> 0 | BH32: =BF32+BG32 -> 0 | BJ32: =(BH32-BI32)+BD32 -> 0 | BM32: =$AF$32*BL32 -> 0 | BN32: =BL32+BM32 -> 0 | BP32: =(BN32-BO32)+BJ32 -> 0 | BS32: =$AF$32*BR32 -> 0 | BT32: =BR32+BS32 -> 0 | BV32: =(BT32-BU32)+BP32 -> 0 | BY32: =$AF$32*BX32 -> 0 | BZ32: =BX32+BY32 -> 0 | CB32: =(BZ32-CA32)+BV32 -> 0 | CE32: =$AF$32*CD32 -> 0 | CF32: =CD32+CE32 -> 0 | CH32: =(CF32-CG32)+CB32 -> 0 | CK32: =$AF$32*CJ32 -> 0 | CL32: =CJ32+CK32 -> 0 | CN32: =(CL32-CM32)+CH32 -> 0 | CQ32: =$AF$32*CP32 -> 0 | CR32: =CP32+CQ32 -> 0 | CT32: =(CR32-CS32)+CN32 -> 0 | CW32: =$AF$32*CV32 -> 0 | CX32: =CV32+CW32 -> 0 | CZ32: =(CX32-CY32)+CT32 -> 0 | DA32: =SUM(AG32,AM32,AS32,AY32,BE32,BK32,BQ32,BW32,CC32,CI32,CO32,CU32) -> 0 | DB32: =SUM(AH32,AN32,AT32,AZ32,BF32,BL32,BR32,BX32,CD32,CJ32,CP32,CV32) -> 0 | DC32: =SUM(AI32,AO32,AU32,BA32,BG32,BM32,BS32,BY32,CE32,CK32,CQ32,CW32) -> 0 | DD32: =SUM(AJ32,AP32,AV32,BB32,BH32,BN32,BT32,BZ32,CF32,CL32,CR32,CX32) -> 0 | DE32: =SUM(AK32,AQ32,AW32,BC32,BI32,BO32,BU32,CA32,CG32,CM32,CS32,CY32) -> 0 | DF32: =CZ32 -> 0
A33: ='Group-Savings'!A33 -> 0 | B33: ='Group-Savings'!B33 -> 0 | C33: ='Group-Savings'!C33 -> 0 | D33: ='Group-Savings'!D33 -> 0 | E33: ='Group-Savings'!E33 -> 0 | F33: ='Group-Savings'!F33 -> 0 | G33: ='Group-Savings'!G33 -> 0 | H33: ='Group-Savings'!H33 -> 0 | ... L33: ='Group-Savings'!L33 -> 0 | M33: =K33+L33 -> 0 | O33: 28 | R33: 21 | S33: 10 | V33: =S33*U33 -> 0 | W33: 408000 | X33: 206300 | Y33: =W33-X33 -> 201700 | Z33: 165600 | AI33: =$AF$33*AH33 -> 0 | AJ33: =AH33+AI33 -> 0 | AL33: =AJ33-AK33 -> 0 | AO33: =$AF$33*AN33 -> 0 | AP33: =AN33+AO33 -> 0 | AR33: =(AP33-AQ33)+AL33 -> 0 | AU33: =$AF$33*AT33 -> 0 | AV33: =AT33+AU33 -> 0 | AX33: =(AV33-AW33)+AR33 -> 0 | BA33: =$AF$33*AZ33 -> 0 | BB33: =AZ33+BA33 -> 0 | BD33: =(BB33-BC33)+AX33 -> 0 | BG33: =$AF$33*BF33 -> 0 | BH33: =BF33+BG33 -> 0 | BJ33: =(BH33-BI33)+BD33 -> 0 | BM33: =$AF$33*BL33 -> 0 | BN33: =BL33+BM33 -> 0 | BP33: =(BN33-BO33)+BJ33 -> 0 | BS33: =$AF$33*BR33 -> 0 | BT33: =BR33+BS33 -> 0 | BV33: =(BT33-BU33)+BP33 -> 0 | BY33: =$AF$33*BX33 -> 0 | BZ33: =BX33+BY33 -> 0 | CB33: =(BZ33-CA33)+BV33 -> 0 | CE33: =$AF$33*CD33 -> 0 | CF33: =CD33+CE33 -> 0 | CH33: =(CF33-CG33)+CB33 -> 0 | CK33: =$AF$33*CJ33 -> 0 | CL33: =CJ33+CK33 -> 0 | CN33: =(CL33-CM33)+CH33 -> 0 | CQ33: =$AF$33*CP33 -> 0 | CR33: =CP33+CQ33 -> 0 | CT33: =(CR33-CS33)+CN33 -> 0 | CW33: =$AF$33*CV33 -> 0 | CX33: =CV33+CW33 -> 0 | CZ33: =(CX33-CY33)+CT33 -> 0 | DA33: =SUM(AG33,AM33,AS33,AY33,BE33,BK33,BQ33,BW33,CC33,CI33,CO33,CU33) -> 0 | DB33: =SUM(AH33,AN33,AT33,AZ33,BF33,BL33,BR33,BX33,CD33,CJ33,CP33,CV33) -> 0 | DC33: =SUM(AI33,AO33,AU33,BA33,BG33,BM33,BS33,BY33,CE33,CK33,CQ33,CW33) -> 0 | DD33: =SUM(AJ33,AP33,AV33,BB33,BH33,BN33,BT33,BZ33,CF33,CL33,CR33,CX33) -> 0 | DE33: =SUM(AK33,AQ33,AW33,BC33,BI33,BO33,BU33,CA33,CG33,CM33,CS33,CY33) -> 0 | DF33: =CZ33 -> 0
A34: ='Group-Savings'!A34 -> 0 | B34: ='Group-Savings'!B34 -> 0 | C34: ='Group-Savings'!C34 -> 0 | D34: ='Group-Savings'!D34 -> 0 | E34: ='Group-Savings'!E34 -> 0 | F34: ='Group-Savings'!F34 -> 0 | G34: ='Group-Savings'!G34 -> 0 | H34: ='Group-Savings'!H34 -> 0 | ... L34: ='Group-Savings'!L34 -> 0 | M34: =K34+L34 -> 0 | O34: 40 | R34: 27 | S34: 10 | V34: =S34*U34 -> 0 | W34: 1026000 | X34: 1026000 | Y34: =W34-X34 -> 0 | Z34: 600000 | AI34: =$AF$34*AH34 -> 0 | AJ34: =AH34+AI34 -> 0 | AL34: =AJ34-AK34 -> 0 | AO34: =$AF$34*AN34 -> 0 | AP34: =AN34+AO34 -> 0 | AR34: =(AP34-AQ34)+AL34 -> 0 | AU34: =$AF$34*AT34 -> 0 | AV34: =AT34+AU34 -> 0 | AX34: =(AV34-AW34)+AR34 -> 0 | BA34: =$AF$34*AZ34 -> 0 | BB34: =AZ34+BA34 -> 0 | BD34: =(BB34-BC34)+AX34 -> 0 | BG34: =$AF$34*BF34 -> 0 | BH34: =BF34+BG34 -> 0 | BJ34: =(BH34-BI34)+BD34 -> 0 | BM34: =$AF$34*BL34 -> 0 | BN34: =BL34+BM34 -> 0 | BP34: =(BN34-BO34)+BJ34 -> 0 | BS34: =$AF$34*BR34 -> 0 | BT34: =BR34+BS34 -> 0 | BV34: =(BT34-BU34)+BP34 -> 0 | BY34: =$AF$34*BX34 -> 0 | BZ34: =BX34+BY34 -> 0 | CB34: =(BZ34-CA34)+BV34 -> 0 | CE34: =$AF$34*CD34 -> 0 | CF34: =CD34+CE34 -> 0 | CH34: =(CF34-CG34)+CB34 -> 0 | CK34: =$AF$34*CJ34 -> 0 | CL34: =CJ34+CK34 -> 0 | CN34: =(CL34-CM34)+CH34 -> 0 | CQ34: =$AF$34*CP34 -> 0 | CR34: =CP34+CQ34 -> 0 | CT34: =(CR34-CS34)+CN34 -> 0 | CW34: =$AF$34*CV34 -> 0 | CX34: =CV34+CW34 -> 0 | CZ34: =(CX34-CY34)+CT34 -> 0 | DA34: =SUM(AG34,AM34,AS34,AY34,BE34,BK34,BQ34,BW34,CC34,CI34,CO34,CU34) -> 0 | DB34: =SUM(AH34,AN34,AT34,AZ34,BF34,BL34,BR34,BX34,CD34,CJ34,CP34,CV34) -> 0 | DC34: =SUM(AI34,AO34,AU34,BA34,BG34,BM34,BS34,BY34,CE34,CK34,CQ34,CW34) -> 0 | DD34: =SUM(AJ34,AP34,AV34,BB34,BH34,BN34,BT34,BZ34,CF34,CL34,CR34,CX34) -> 0 | DE34: =SUM(AK34,AQ34,AW34,BC34,BI34,BO34,BU34,CA34,CG34,CM34,CS34,CY34) -> 0 | DF34: =CZ34 -> 0
A35: ='Group-Savings'!A35 -> 0 | B35: ='Group-Savings'!B35 -> 0 | C35: ='Group-Savings'!C35 -> 0 | D35: ='Group-Savings'!D35 -> 0 | E35: ='Group-Savings'!E35 -> 0 | F35: ='Group-Savings'!F35 -> 0 | G35: ='Group-Savings'!G35 -> 0 | H35: ='Group-Savings'!H35 -> 0 | ... L35: ='Group-Savings'!L35 -> 0 | M35: =K35+L35 -> 0 | O35: 32 | R35: 30 | S35: 10 | U35: 500000 | V35: =S35*U35 -> 5000000 | W35: 7500000 | X35: 2540000 | Y35: =W35-X35 -> 4960000 | Z35: 720000 | AI35: =$AF$35*AH35 -> 0 | AJ35: =AH35+AI35 -> 0 | AL35: =AJ35-AK35 -> 0 | AO35: =$AF$35*AN35 -> 0 | AP35: =AN35+AO35 -> 0 | AR35: =(AP35-AQ35)+AL35 -> 0 | AU35: =$AF$35*AT35 -> 0 | AV35: =AT35+AU35 -> 0 | AX35: =(AV35-AW35)+AR35 -> 0 | BA35: =$AF$35*AZ35 -> 0 | BB35: =AZ35+BA35 -> 0 | BD35: =(BB35-BC35)+AX35 -> 0 | BG35: =$AF$35*BF35 -> 0 | BH35: =BF35+BG35 -> 0 | BJ35: =(BH35-BI35)+BD35 -> 0 | BM35: =$AF$35*BL35 -> 0 | BN35: =BL35+BM35 -> 0 | BP35: =(BN35-BO35)+BJ35 -> 0 | BS35: =$AF$35*BR35 -> 0 | BT35: =BR35+BS35 -> 0 | BV35: =(BT35-BU35)+BP35 -> 0 | BY35: =$AF$35*BX35 -> 0 | BZ35: =BX35+BY35 -> 0 | CB35: =(BZ35-CA35)+BV35 -> 0 | CE35: =$AF$35*CD35 -> 0 | CF35: =CD35+CE35 -> 0 | CH35: =(CF35-CG35)+CB35 -> 0 | CK35: =$AF$35*CJ35 -> 0 | CL35: =CJ35+CK35 -> 0 | CN35: =(CL35-CM35)+CH35 -> 0 | CQ35: =$AF$35*CP35 -> 0 | CR35: =CP35+CQ35 -> 0 | CT35: =(CR35-CS35)+CN35 -> 0 | CW35: =$AF$35*CV35 -> 0 | CX35: =CV35+CW35 -> 0 | CZ35: =(CX35-CY35)+CT35 -> 0 | DA35: =SUM(AG35,AM35,AS35,AY35,BE35,BK35,BQ35,BW35,CC35,CI35,CO35,CU35) -> 0 | DB35: =SUM(AH35,AN35,AT35,AZ35,BF35,BL35,BR35,BX35,CD35,CJ35,CP35,CV35) -> 0 | DC35: =SUM(AI35,AO35,AU35,BA35,BG35,BM35,BS35,BY35,CE35,CK35,CQ35,CW35) -> 0 | DD35: =SUM(AJ35,AP35,AV35,BB35,BH35,BN35,BT35,BZ35,CF35,CL35,CR35,CX35) -> 0 | DE35: =SUM(AK35,AQ35,AW35,BC35,BI35,BO35,BU35,CA35,CG35,CM35,CS35,CY35) -> 0 | DF35: =CZ35 -> 0
A36: ='Group-Savings'!A36 -> 0 | B36: ='Group-Savings'!B36 -> 0 | C36: ='Group-Savings'!C36 -> 0 | D36: ='Group-Savings'!D36 -> 0 | E36: ='Group-Savings'!E36 -> 0 | F36: ='Group-Savings'!F36 -> 0 | G36: ='Group-Savings'!G36 -> 0 | H36: ='Group-Savings'!H36 -> 0 | ... L36: ='Group-Savings'!L36 -> 0 | M36: =K36+L36 -> 0 | O36: 48 | R36: 27 | S36: 10 | U36: 0 | V36: =S36*U36 -> 0 | W36: 846100 | X36: 441200 | Y36: =W36-X36 -> 404900 | Z36: 115700 | AI36: =$AF$36*AH36 -> 0 | AJ36: =AH36+AI36 -> 0 | AL36: =AJ36-AK36 -> 0 | AO36: =$AF$36*AN36 -> 0 | AP36: =AN36+AO36 -> 0 | AR36: =(AP36-AQ36)+AL36 -> 0 | AU36: =$AF$36*AT36 -> 0 | AV36: =AT36+AU36 -> 0 | AX36: =(AV36-AW36)+AR36 -> 0 | BA36: =$AF$36*AZ36 -> 0 | BB36: =AZ36+BA36 -> 0 | BD36: =(BB36-BC36)+AX36 -> 0 | BG36: =$AF$36*BF36 -> 0 | BH36: =BF36+BG36 -> 0 | BJ36: =(BH36-BI36)+BD36 -> 0 | BM36: =$AF$36*BL36 -> 0 | BN36: =BL36+BM36 -> 0 | BP36: =(BN36-BO36)+BJ36 -> 0 | BS36: =$AF$36*BR36 -> 0 | BT36: =BR36+BS36 -> 0 | BV36: =(BT36-BU36)+BP36 -> 0 | BY36: =$AF$36*BX36 -> 0 | BZ36: =BX36+BY36 -> 0 | CB36: =(BZ36-CA36)+BV36 -> 0 | CE36: =$AF$36*CD36 -> 0 | CF36: =CD36+CE36 -> 0 | CH36: =(CF36-CG36)+CB36 -> 0 | CK36: =$AF$36*CJ36 -> 0 | CL36: =CJ36+CK36 -> 0 | CN36: =(CL36-CM36)+CH36 -> 0 | CQ36: =$AF$36*CP36 -> 0 | CR36: =CP36+CQ36 -> 0 | CT36: =(CR36-CS36)+CN36 -> 0 | CW36: =$AF$36*CV36 -> 0 | CX36: =CV36+CW36 -> 0 | CZ36: =(CX36-CY36)+CT36 -> 0 | DA36: =SUM(AG36,AM36,AS36,AY36,BE36,BK36,BQ36,BW36,CC36,CI36,CO36,CU36) -> 0 | DB36: =SUM(AH36,AN36,AT36,AZ36,BF36,BL36,BR36,BX36,CD36,CJ36,CP36,CV36) -> 0 | DC36: =SUM(AI36,AO36,AU36,BA36,BG36,BM36,BS36,BY36,CE36,CK36,CQ36,CW36) -> 0 | DD36: =SUM(AJ36,AP36,AV36,BB36,BH36,BN36,BT36,BZ36,CF36,CL36,CR36,CX36) -> 0 | DE36: =SUM(AK36,AQ36,AW36,BC36,BI36,BO36,BU36,CA36,CG36,CM36,CS36,CY36) -> 0 | DF36: =CZ36 -> 0
A37: ='Group-Savings'!A37 -> 0 | B37: ='Group-Savings'!B37 -> 0 | C37: ='Group-Savings'!C37 -> 0 | D37: ='Group-Savings'!D37 -> 0 | E37: ='Group-Savings'!E37 -> 0 | F37: ='Group-Savings'!F37 -> 0 | G37: ='Group-Savings'!G37 -> 0 | H37: ='Group-Savings'!H37 -> 0 | ... L37: ='Group-Savings'!L37 -> 0 | M37: =K37+L37 -> 0 | O37: 32 | R37: 14 | S37: 10 | U37: 0 | V37: =S37*U37 -> 0 | W37: 430000 | X37: 286000 | Y37: =W37-X37 -> 144000 | Z37: 192000 | AI37: =$AF$37*AH37 -> 0 | AJ37: =AH37+AI37 -> 0 | AL37: =AJ37-AK37 -> 0 | AO37: =$AF$37*AN37 -> 0 | AP37: =AN37+AO37 -> 0 | AR37: =(AP37-AQ37)+AL37 -> 0 | AU37: =$AF$37*AT37 -> 0 | AV37: =AT37+AU37 -> 0 | AX37: =(AV37-AW37)+AR37 -> 0 | BA37: =$AF$37*AZ37 -> 0 | BB37: =AZ37+BA37 -> 0 | BD37: =(BB37-BC37)+AX37 -> 0 | BG37: =$AF$37*BF37 -> 0 | BH37: =BF37+BG37 -> 0 | BJ37: =(BH37-BI37)+BD37 -> 0 | BM37: =$AF$37*BL37 -> 0 | BN37: =BL37+BM37 -> 0 | BP37: =(BN37-BO37)+BJ37 -> 0 | BS37: =$AF$37*BR37 -> 0 | BT37: =BR37+BS37 -> 0 | BV37: =(BT37-BU37)+BP37 -> 0 | BY37: =$AF$37*BX37 -> 0 | BZ37: =BX37+BY37 -> 0 | CB37: =(BZ37-CA37)+BV37 -> 0 | CE37: =$AF$37*CD37 -> 0 | CF37: =CD37+CE37 -> 0 | CH37: =(CF37-CG37)+CB37 -> 0 | CK37: =$AF$37*CJ37 -> 0 | CL37: =CJ37+CK37 -> 0 | CN37: =(CL37-CM37)+CH37 -> 0 | CQ37: =$AF$37*CP37 -> 0 | CR37: =CP37+CQ37 -> 0 | CT37: =(CR37-CS37)+CN37 -> 0 | CW37: =$AF$37*CV37 -> 0 | CX37: =CV37+CW37 -> 0 | CZ37: =(CX37-CY37)+CT37 -> 0 | DA37: =SUM(AG37,AM37,AS37,AY37,BE37,BK37,BQ37,BW37,CC37,CI37,CO37,CU37) -> 0 | DB37: =SUM(AH37,AN37,AT37,AZ37,BF37,BL37,BR37,BX37,CD37,CJ37,CP37,CV37) -> 0 | DC37: =SUM(AI37,AO37,AU37,BA37,BG37,BM37,BS37,BY37,CE37,CK37,CQ37,CW37) -> 0 | DD37: =SUM(AJ37,AP37,AV37,BB37,BH37,BN37,BT37,BZ37,CF37,CL37,CR37,CX37) -> 0 | DE37: =SUM(AK37,AQ37,AW37,BC37,BI37,BO37,BU37,CA37,CG37,CM37,CS37,CY37) -> 0 | DF37: =CZ37 -> 0
A38: ='Group-Savings'!A38 -> 0 | B38: ='Group-Savings'!B38 -> 0 | C38: ='Group-Savings'!C38 -> 0 | D38: ='Group-Savings'!D38 -> 0 | E38: ='Group-Savings'!E38 -> 0 | F38: ='Group-Savings'!F38 -> 0 | G38: ='Group-Savings'!G38 -> 0 | H38: ='Group-Savings'!H38 -> 0 | ... L38: ='Group-Savings'!L38 -> 0 | M38: =K38+L38 -> 0 | O38: 17 | R38: 22 | S38: 10 | U38: 0 | V38: =S38*U38 -> 0 | W38: 853000 | X38: 853000 | Y38: =W38-X38 -> 0 | Z38: 98000 | AI38: =$AF$38*AH38 -> 0 | AJ38: =AH38+AI38 -> 0 | AL38: =AJ38-AK38 -> 0 | AO38: =$AF$38*AN38 -> 0 | AP38: =AN38+AO38 -> 0 | AR38: =(AP38-AQ38)+AL38 -> 0 | AU38: =$AF$38*AT38 -> 0 | AV38: =AT38+AU38 -> 0 | AX38: =(AV38-AW38)+AR38 -> 0 | BA38: =$AF$38*AZ38 -> 0 | BB38: =AZ38+BA38 -> 0 | BD38: =(BB38-BC38)+AX38 -> 0 | BG38: =$AF$38*BF38 -> 0 | BH38: =BF38+BG38 -> 0 | BJ38: =(BH38-BI38)+BD38 -> 0 | BM38: =$AF$38*BL38 -> 0 | BN38: =BL38+BM38 -> 0 | BP38: =(BN38-BO38)+BJ38 -> 0 | BS38: =$AF$38*BR38 -> 0 | BT38: =BR38+BS38 -> 0 | BV38: =(BT38-BU38)+BP38 -> 0 | BY38: =$AF$38*BX38 -> 0 | BZ38: =BX38+BY38 -> 0 | CB38: =(BZ38-CA38)+BV38 -> 0 | CE38: =$AF$38*CD38 -> 0 | CF38: =CD38+CE38 -> 0 | CH38: =(CF38-CG38)+CB38 -> 0 | CK38: =$AF$38*CJ38 -> 0 | CL38: =CJ38+CK38 -> 0 | CN38: =(CL38-CM38)+CH38 -> 0 | CQ38: =$AF$38*CP38 -> 0 | CR38: =CP38+CQ38 -> 0 | CT38: =(CR38-CS38)+CN38 -> 0 | CW38: =$AF$38*CV38 -> 0 | CX38: =CV38+CW38 -> 0 | CZ38: =(CX38-CY38)+CT38 -> 0 | DA38: =SUM(AG38,AM38,AS38,AY38,BE38,BK38,BQ38,BW38,CC38,CI38,CO38,CU38) -> 0 | DB38: =SUM(AH38,AN38,AT38,AZ38,BF38,BL38,BR38,BX38,CD38,CJ38,CP38,CV38) -> 0 | DC38: =SUM(AI38,AO38,AU38,BA38,BG38,BM38,BS38,BY38,CE38,CK38,CQ38,CW38) -> 0 | DD38: =SUM(AJ38,AP38,AV38,BB38,BH38,BN38,BT38,BZ38,CF38,CL38,CR38,CX38) -> 0 | DE38: =SUM(AK38,AQ38,AW38,BC38,BI38,BO38,BU38,CA38,CG38,CM38,CS38,CY38) -> 0 | DF38: =CZ38 -> 0
A39: ='Group-Savings'!A39 -> 0 | B39: ='Group-Savings'!B39 -> 0 | C39: ='Group-Savings'!C39 -> 0 | D39: ='Group-Savings'!D39 -> 0 | E39: ='Group-Savings'!E39 -> 0 | F39: ='Group-Savings'!F39 -> 0 | G39: ='Group-Savings'!G39 -> 0 | H39: ='Group-Savings'!H39 -> 0 | ... L39: ='Group-Savings'!L39 -> 0 | M39: =K39+L39 -> 0 | O39: 28 | R39: 33 | S39: 10 | U39: 0 | V39: =S39*U39 -> 0 | W39: 992000 | X39: 710000 | Y39: =W39-X39 -> 282000 | Z39: 216000 | AI39: =$AF$39*AH39 -> 0 | AJ39: =AH39+AI39 -> 0 | AL39: =AJ39-AK39 -> 0 | AO39: =$AF$39*AN39 -> 0 | AP39: =AN39+AO39 -> 0 | AR39: =(AP39-AQ39)+AL39 -> 0 | AU39: =$AF$39*AT39 -> 0 | AV39: =AT39+AU39 -> 0 | AX39: =(AV39-AW39)+AR39 -> 0 | BA39: =$AF$39*AZ39 -> 0 | BB39: =AZ39+BA39 -> 0 | BD39: =(BB39-BC39)+AX39 -> 0 | BG39: =$AF$39*BF39 -> 0 | BH39: =BF39+BG39 -> 0 | BJ39: =(BH39-BI39)+BD39 -> 0 | BM39: =$AF$39*BL39 -> 0 | BN39: =BL39+BM39 -> 0 | BP39: =(BN39-BO39)+BJ39 -> 0 | BS39: =$AF$39*BR39 -> 0 | BT39: =BR39+BS39 -> 0 | BV39: =(BT39-BU39)+BP39 -> 0 | BY39: =$AF$39*BX39 -> 0 | BZ39: =BX39+BY39 -> 0 | CB39: =(BZ39-CA39)+BV39 -> 0 | CE39: =$AF$39*CD39 -> 0 | CF39: =CD39+CE39 -> 0 | CH39: =(CF39-CG39)+CB39 -> 0 | CK39: =$AF$39*CJ39 -> 0 | CL39: =CJ39+CK39 -> 0 | CN39: =(CL39-CM39)+CH39 -> 0 | CQ39: =$AF$39*CP39 -> 0 | CR39: =CP39+CQ39 -> 0 | CT39: =(CR39-CS39)+CN39 -> 0 | CW39: =$AF$39*CV39 -> 0 | CX39: =CV39+CW39 -> 0 | CZ39: =(CX39-CY39)+CT39 -> 0 | DA39: =SUM(AG39,AM39,AS39,AY39,BE39,BK39,BQ39,BW39,CC39,CI39,CO39,CU39) -> 0 | DB39: =SUM(AH39,AN39,AT39,AZ39,BF39,BL39,BR39,BX39,CD39,CJ39,CP39,CV39) -> 0 | DC39: =SUM(AI39,AO39,AU39,BA39,BG39,BM39,BS39,BY39,CE39,CK39,CQ39,CW39) -> 0 | DD39: =SUM(AJ39,AP39,AV39,BB39,BH39,BN39,BT39,BZ39,CF39,CL39,CR39,CX39) -> 0 | DE39: =SUM(AK39,AQ39,AW39,BC39,BI39,BO39,BU39,CA39,CG39,CM39,CS39,CY39) -> 0 | DF39: =CZ39 -> 0
A40: ='Group-Savings'!A40 -> 0 | B40: ='Group-Savings'!B40 -> 0 | C40: ='Group-Savings'!C40 -> 0 | D40: ='Group-Savings'!D40 -> 0 | E40: ='Group-Savings'!E40 -> 0 | F40: ='Group-Savings'!F40 -> 0 | G40: ='Group-Savings'!G40 -> 0 | H40: ='Group-Savings'!H40 -> 0 | ... L40: ='Group-Savings'!L40 -> 0 | M40: =K40+L40 -> 0 | O40: 28 | R40: 21 | S40: 10 | U40: 0 | V40: =S40*U40 -> 0 | W40: 408000 | X40: 206300 | Y40: =W40-X40 -> 201700 | Z40: 165600 | AI40: =$AF$40*AH40 -> 0 | AJ40: =AH40+AI40 -> 0 | AL40: =AJ40-AK40 -> 0 | AO40: =$AF$40*AN40 -> 0 | AP40: =AN40+AO40 -> 0 | AR40: =(AP40-AQ40)+AL40 -> 0 | AU40: =$AF$40*AT40 -> 0 | AV40: =AT40+AU40 -> 0 | AX40: =(AV40-AW40)+AR40 -> 0 | BA40: =$AF$40*AZ40 -> 0 | BB40: =AZ40+BA40 -> 0 | BD40: =(BB40-BC40)+AX40 -> 0 | BG40: =$AF$40*BF40 -> 0 | BH40: =BF40+BG40 -> 0 | BJ40: =(BH40-BI40)+BD40 -> 0 | BM40: =$AF$40*BL40 -> 0 | BN40: =BL40+BM40 -> 0 | BP40: =(BN40-BO40)+BJ40 -> 0 | BS40: =$AF$40*BR40 -> 0 | BT40: =BR40+BS40 -> 0 | BV40: =(BT40-BU40)+BP40 -> 0 | BY40: =$AF$40*BX40 -> 0 | BZ40: =BX40+BY40 -> 0 | CB40: =(BZ40-CA40)+BV40 -> 0 | CE40: =$AF$40*CD40 -> 0 | CF40: =CD40+CE40 -> 0 | CH40: =(CF40-CG40)+CB40 -> 0 | CK40: =$AF$40*CJ40 -> 0 | CL40: =CJ40+CK40 -> 0 | CN40: =(CL40-CM40)+CH40 -> 0 | CQ40: =$AF$40*CP40 -> 0 | CR40: =CP40+CQ40 -> 0 | CT40: =(CR40-CS40)+CN40 -> 0 | CW40: =$AF$40*CV40 -> 0 | CX40: =CV40+CW40 -> 0 | CZ40: =(CX40-CY40)+CT40 -> 0 | DA40: =SUM(AG40,AM40,AS40,AY40,BE40,BK40,BQ40,BW40,CC40,CI40,CO40,CU40) -> 0 | DB40: =SUM(AH40,AN40,AT40,AZ40,BF40,BL40,BR40,BX40,CD40,CJ40,CP40,CV40) -> 0 | DC40: =SUM(AI40,AO40,AU40,BA40,BG40,BM40,BS40,BY40,CE40,CK40,CQ40,CW40) -> 0 | DD40: =SUM(AJ40,AP40,AV40,BB40,BH40,BN40,BT40,BZ40,CF40,CL40,CR40,CX40) -> 0 | DE40: =SUM(AK40,AQ40,AW40,BC40,BI40,BO40,BU40,CA40,CG40,CM40,CS40,CY40) -> 0 | DF40: =CZ40 -> 0
A41: ='Group-Savings'!A41 -> 0 | B41: ='Group-Savings'!B41 -> 0 | C41: ='Group-Savings'!C41 -> 0 | D41: ='Group-Savings'!D41 -> 0 | E41: ='Group-Savings'!E41 -> 0 | F41: ='Group-Savings'!F41 -> 0 | G41: ='Group-Savings'!G41 -> 0 | H41: ='Group-Savings'!H41 -> 0 | ... L41: ='Group-Savings'!L41 -> 0 | M41: =K41+L41 -> 0 | O41: 28 | R41: 19 | S41: 10 | U41: 0 | V41: =S41*U41 -> 0 | W41: 425000 | X41: 440000 | Y41: =W41-X41 -> -15000 | Z41: 98000 | AI41: =$AF$41*AH41 -> 0 | AJ41: =AH41+AI41 -> 0 | AL41: =AJ41-AK41 -> 0 | AO41: =$AF$41*AN41 -> 0 | AP41: =AN41+AO41 -> 0 | AR41: =(AP41-AQ41)+AL41 -> 0 | AU41: =$AF$41*AT41 -> 0 | AV41: =AT41+AU41 -> 0 | AX41: =(AV41-AW41)+AR41 -> 0 | BA41: =$AF$41*AZ41 -> 0 | BB41: =AZ41+BA41 -> 0 | BD41: =(BB41-BC41)+AX41 -> 0 | BG41: =$AF$41*BF41 -> 0 | BH41: =BF41+BG41 -> 0 | BJ41: =(BH41-BI41)+BD41 -> 0 | BM41: =$AF$41*BL41 -> 0 | BN41: =BL41+BM41 -> 0 | BP41: =(BN41-BO41)+BJ41 -> 0 | BS41: =$AF$41*BR41 -> 0 | BT41: =BR41+BS41 -> 0 | BV41: =(BT41-BU41)+BP41 -> 0 | BY41: =$AF$41*BX41 -> 0 | BZ41: =BX41+BY41 -> 0 | CB41: =(BZ41-CA41)+BV41 -> 0 | CE41: =$AF$41*CD41 -> 0 | CF41: =CD41+CE41 -> 0 | CH41: =(CF41-CG41)+CB41 -> 0 | CK41: =$AF$41*CJ41 -> 0 | CL41: =CJ41+CK41 -> 0 | CN41: =(CL41-CM41)+CH41 -> 0 | CQ41: =$AF$41*CP41 -> 0 | CR41: =CP41+CQ41 -> 0 | CT41: =(CR41-CS41)+CN41 -> 0 | CW41: =$AF$41*CV41 -> 0 | CX41: =CV41+CW41 -> 0 | CZ41: =(CX41-CY41)+CT41 -> 0 | DA41: =SUM(AG41,AM41,AS41,AY41,BE41,BK41,BQ41,BW41,CC41,CI41,CO41,CU41) -> 0 | DB41: =SUM(AH41,AN41,AT41,AZ41,BF41,BL41,BR41,BX41,CD41,CJ41,CP41,CV41) -> 0 | DC41: =SUM(AI41,AO41,AU41,BA41,BG41,BM41,BS41,BY41,CE41,CK41,CQ41,CW41) -> 0 | DD41: =SUM(AJ41,AP41,AV41,BB41,BH41,BN41,BT41,BZ41,CF41,CL41,CR41,CX41) -> 0 | DE41: =SUM(AK41,AQ41,AW41,BC41,BI41,BO41,BU41,CA41,CG41,CM41,CS41,CY41) -> 0 | DF41: =CZ41 -> 0
A42: ='Group-Savings'!A42 -> 0 | B42: ='Group-Savings'!B42 -> 0 | C42: ='Group-Savings'!C42 -> 0 | D42: ='Group-Savings'!D42 -> 0 | E42: ='Group-Savings'!E42 -> 0 | F42: ='Group-Savings'!F42 -> 0 | G42: ='Group-Savings'!G42 -> 0 | H42: ='Group-Savings'!H42 -> 0 | ... L42: ='Group-Savings'!L42 -> 0 | M42: =K42+L42 -> 0 | O42: 32 | R42: 14 | S42: 10 | U42: 0 | V42: =S42*U42 -> 0 | W42: 1810000 | X42: 726000 | Y42: =W42-X42 -> 1084000 | Z42: 102000 | AI42: =$AF$42*AH42 -> 0 | AJ42: =AH42+AI42 -> 0 | AL42: =AJ42-AK42 -> 0 | AO42: =$AF$42*AN42 -> 0 | AP42: =AN42+AO42 -> 0 | AR42: =(AP42-AQ42)+AL42 -> 0 | AU42: =$AF$42*AT42 -> 0 | AV42: =AT42+AU42 -> 0 | AX42: =(AV42-AW42)+AR42 -> 0 | BA42: =$AF$42*AZ42 -> 0 | BB42: =AZ42+BA42 -> 0 | BD42: =(BB42-BC42)+AX42 -> 0 | BG42: =$AF$42*BF42 -> 0 | BH42: =BF42+BG42 -> 0 | BJ42: =(BH42-BI42)+BD42 -> 0 | BM42: =$AF$42*BL42 -> 0 | BN42: =BL42+BM42 -> 0 | BP42: =(BN42-BO42)+BJ42 -> 0 | BS42: =$AF$42*BR42 -> 0 | BT42: =BR42+BS42 -> 0 | BV42: =(BT42-BU42)+BP42 -> 0 | BY42: =$AF$42*BX42 -> 0 | BZ42: =BX42+BY42 -> 0 | CB42: =(BZ42-CA42)+BV42 -> 0 | CE42: =$AF$42*CD42 -> 0 | CF42: =CD42+CE42 -> 0 | CH42: =(CF42-CG42)+CB42 -> 0 | CK42: =$AF$42*CJ42 -> 0 | CL42: =CJ42+CK42 -> 0 | CN42: =(CL42-CM42)+CH42 -> 0 | CQ42: =$AF$42*CP42 -> 0 | CR42: =CP42+CQ42 -> 0 | CT42: =(CR42-CS42)+CN42 -> 0 | CW42: =$AF$42*CV42 -> 0 | CX42: =CV42+CW42 -> 0 | CZ42: =(CX42-CY42)+CT42 -> 0 | DA42: =SUM(AG42,AM42,AS42,AY42,BE42,BK42,BQ42,BW42,CC42,CI42,CO42,CU42) -> 0 | DB42: =SUM(AH42,AN42,AT42,AZ42,BF42,BL42,BR42,BX42,CD42,CJ42,CP42,CV42) -> 0 | DC42: =SUM(AI42,AO42,AU42,BA42,BG42,BM42,BS42,BY42,CE42,CK42,CQ42,CW42) -> 0 | DD42: =SUM(AJ42,AP42,AV42,BB42,BH42,BN42,BT42,BZ42,CF42,CL42,CR42,CX42) -> 0 | DE42: =SUM(AK42,AQ42,AW42,BC42,BI42,BO42,BU42,CA42,CG42,CM42,CS42,CY42) -> 0 | DF42: =CZ42 -> 0
A43: ='Group-Savings'!A43 -> 0 | B43: ='Group-Savings'!B43 -> 0 | C43: ='Group-Savings'!C43 -> 0 | D43: ='Group-Savings'!D43 -> 0 | E43: ='Group-Savings'!E43 -> 0 | F43: ='Group-Savings'!F43 -> 0 | G43: ='Group-Savings'!G43 -> 0 | H43: ='Group-Savings'!H43 -> 0 | ... L43: ='Group-Savings'!L43 -> 0 | M43: =K43+L43 -> 0 | O43: 32 | R43: 30 | S43: 10 | U43: 0 | V43: =S43*U43 -> 0 | W43: 671000 | X43: 671000 | Y43: =W43-X43 -> 0 | Z43: 192000 | AI43: =$AF$43*AH43 -> 0 | AJ43: =AH43+AI43 -> 0 | AL43: =AJ43-AK43 -> 0 | AO43: =$AF$43*AN43 -> 0 | AP43: =AN43+AO43 -> 0 | AR43: =(AP43-AQ43)+AL43 -> 0 | AU43: =$AF$43*AT43 -> 0 | AV43: =AT43+AU43 -> 0 | AX43: =(AV43-AW43)+AR43 -> 0 | BA43: =$AF$43*AZ43 -> 0 | BB43: =AZ43+BA43 -> 0 | BD43: =(BB43-BC43)+AX43 -> 0 | BG43: =$AF$43*BF43 -> 0 | BH43: =BF43+BG43 -> 0 | BJ43: =(BH43-BI43)+BD43 -> 0 | BM43: =$AF$43*BL43 -> 0 | BN43: =BL43+BM43 -> 0 | BP43: =(BN43-BO43)+BJ43 -> 0 | BS43: =$AF$43*BR43 -> 0 | BT43: =BR43+BS43 -> 0 | BV43: =(BT43-BU43)+BP43 -> 0 | BY43: =$AF$43*BX43 -> 0 | BZ43: =BX43+BY43 -> 0 | CB43: =(BZ43-CA43)+BV43 -> 0 | CE43: =$AF$43*CD43 -> 0 | CF43: =CD43+CE43 -> 0 | CH43: =(CF43-CG43)+CB43 -> 0 | CK43: =$AF$43*CJ43 -> 0 | CL43: =CJ43+CK43 -> 0 | CN43: =(CL43-CM43)+CH43 -> 0 | CQ43: =$AF$43*CP43 -> 0 | CR43: =CP43+CQ43 -> 0 | CT43: =(CR43-CS43)+CN43 -> 0 | CW43: =$AF$43*CV43 -> 0 | CX43: =CV43+CW43 -> 0 | CZ43: =(CX43-CY43)+CT43 -> 0 | DA43: =SUM(AG43,AM43,AS43,AY43,BE43,BK43,BQ43,BW43,CC43,CI43,CO43,CU43) -> 0 | DB43: =SUM(AH43,AN43,AT43,AZ43,BF43,BL43,BR43,BX43,CD43,CJ43,CP43,CV43) -> 0 | DC43: =SUM(AI43,AO43,AU43,BA43,BG43,BM43,BS43,BY43,CE43,CK43,CQ43,CW43) -> 0 | DD43: =SUM(AJ43,AP43,AV43,BB43,BH43,BN43,BT43,BZ43,CF43,CL43,CR43,CX43) -> 0 | DE43: =SUM(AK43,AQ43,AW43,BC43,BI43,BO43,BU43,CA43,CG43,CM43,CS43,CY43) -> 0 | DF43: =CZ43 -> 0
A44: ='Group-Savings'!A44 -> 0 | B44: ='Group-Savings'!B44 -> 0 | C44: ='Group-Savings'!C44 -> 0 | D44: ='Group-Savings'!D44 -> 0 | E44: ='Group-Savings'!E44 -> 0 | F44: ='Group-Savings'!F44 -> 0 | G44: ='Group-Savings'!G44 -> 0 | H44: ='Group-Savings'!H44 -> 0 | ... L44: ='Group-Savings'!L44 -> 0 | M44: =K44+L44 -> 0 | O44: 32 | R44: 11 | S44: 10 | U44: 0 | V44: =S44*U44 -> 0 | W44: 300000 | X44: 150000 | Y44: =W44-X44 -> 150000 | Z44: 192000 | AI44: =$AF$44*AH44 -> 0 | AJ44: =AH44+AI44 -> 0 | AL44: =AJ44-AK44 -> 0 | AO44: =$AF$44*AN44 -> 0 | AP44: =AN44+AO44 -> 0 | AR44: =(AP44-AQ44)+AL44 -> 0 | AU44: =$AF$44*AT44 -> 0 | AV44: =AT44+AU44 -> 0 | AX44: =(AV44-AW44)+AR44 -> 0 | BA44: =$AF$44*AZ44 -> 0 | BB44: =AZ44+BA44 -> 0 | BD44: =(BB44-BC44)+AX44 -> 0 | BG44: =$AF$44*BF44 -> 0 | BH44: =BF44+BG44 -> 0 | BJ44: =(BH44-BI44)+BD44 -> 0 | BM44: =$AF$44*BL44 -> 0 | BN44: =BL44+BM44 -> 0 | BP44: =(BN44-BO44)+BJ44 -> 0 | BS44: =$AF$44*BR44 -> 0 | BT44: =BR44+BS44 -> 0 | BV44: =(BT44-BU44)+BP44 -> 0 | BY44: =$AF$44*BX44 -> 0 | BZ44: =BX44+BY44 -> 0 | CB44: =(BZ44-CA44)+BV44 -> 0 | CE44: =$AF$44*CD44 -> 0 | CF44: =CD44+CE44 -> 0 | CH44: =(CF44-CG44)+CB44 -> 0 | CK44: =$AF$44*CJ44 -> 0 | CL44: =CJ44+CK44 -> 0 | CN44: =(CL44-CM44)+CH44 -> 0 | CQ44: =$AF$44*CP44 -> 0 | CR44: =CP44+CQ44 -> 0 | CT44: =(CR44-CS44)+CN44 -> 0 | CW44: =$AF$44*CV44 -> 0 | CX44: =CV44+CW44 -> 0 | CZ44: =(CX44-CY44)+CT44 -> 0 | DA44: =SUM(AG44,AM44,AS44,AY44,BE44,BK44,BQ44,BW44,CC44,CI44,CO44,CU44) -> 0 | DB44: =SUM(AH44,AN44,AT44,AZ44,BF44,BL44,BR44,BX44,CD44,CJ44,CP44,CV44) -> 0 | DC44: =SUM(AI44,AO44,AU44,BA44,BG44,BM44,BS44,BY44,CE44,CK44,CQ44,CW44) -> 0 | DD44: =SUM(AJ44,AP44,AV44,BB44,BH44,BN44,BT44,BZ44,CF44,CL44,CR44,CX44) -> 0 | DE44: =SUM(AK44,AQ44,AW44,BC44,BI44,BO44,BU44,CA44,CG44,CM44,CS44,CY44) -> 0 | DF44: =CZ44 -> 0
A45: ='Group-Savings'!A45 -> 0 | B45: ='Group-Savings'!B45 -> 0 | C45: ='Group-Savings'!C45 -> 0 | D45: ='Group-Savings'!D45 -> 0 | E45: ='Group-Savings'!E45 -> 0 | F45: ='Group-Savings'!F45 -> 0 | G45: ='Group-Savings'!G45 -> 0 | H45: ='Group-Savings'!H45 -> 0 | ... L45: ='Group-Savings'!L45 -> 0 | M45: =K45+L45 -> 0 | O45: 28 | R45: 12 | S45: 10 | V45: =S45*U45 -> 0 | W45: 545000 | X45: 438000 | Y45: =W45-X45 -> 107000 | Z45: 110000 | AI45: =$AF$45*AH45 -> 0 | AJ45: =AH45+AI45 -> 0 | AL45: =AJ45-AK45 -> 0 | AO45: =$AF$45*AN45 -> 0 | AP45: =AN45+AO45 -> 0 | AR45: =(AP45-AQ45)+AL45 -> 0 | AU45: =$AF$45*AT45 -> 0 | AV45: =AT45+AU45 -> 0 | AX45: =(AV45-AW45)+AR45 -> 0 | BA45: =$AF$45*AZ45 -> 0 | BB45: =AZ45+BA45 -> 0 | BD45: =(BB45-BC45)+AX45 -> 0 | BG45: =$AF$45*BF45 -> 0 | BH45: =BF45+BG45 -> 0 | BJ45: =(BH45-BI45)+BD45 -> 0 | BM45: =$AF$45*BL45 -> 0 | BN45: =BL45+BM45 -> 0 | BP45: =(BN45-BO45)+BJ45 -> 0 | BS45: =$AF$45*BR45 -> 0 | BT45: =BR45+BS45 -> 0 | BV45: =(BT45-BU45)+BP45 -> 0 | BY45: =$AF$45*BX45 -> 0 | BZ45: =BX45+BY45 -> 0 | CB45: =(BZ45-CA45)+BV45 -> 0 | CE45: =$AF$45*CD45 -> 0 | CF45: =CD45+CE45 -> 0 | CH45: =(CF45-CG45)+CB45 -> 0 | CK45: =$AF$45*CJ45 -> 0 | CL45: =CJ45+CK45 -> 0 | CN45: =(CL45-CM45)+CH45 -> 0 | CQ45: =$AF$45*CP45 -> 0 | CR45: =CP45+CQ45 -> 0 | CT45: =(CR45-CS45)+CN45 -> 0 | CW45: =$AF$45*CV45 -> 0 | CX45: =CV45+CW45 -> 0 | CZ45: =(CX45-CY45)+CT45 -> 0 | DA45: =SUM(AG45,AM45,AS45,AY45,BE45,BK45,BQ45,BW45,CC45,CI45,CO45,CU45) -> 0 | DB45: =SUM(AH45,AN45,AT45,AZ45,BF45,BL45,BR45,BX45,CD45,CJ45,CP45,CV45) -> 0 | DC45: =SUM(AI45,AO45,AU45,BA45,BG45,BM45,BS45,BY45,CE45,CK45,CQ45,CW45) -> 0 | DD45: =SUM(AJ45,AP45,AV45,BB45,BH45,BN45,BT45,BZ45,CF45,CL45,CR45,CX45) -> 0 | DE45: =SUM(AK45,AQ45,AW45,BC45,BI45,BO45,BU45,CA45,CG45,CM45,CS45,CY45) -> 0 | DF45: =CZ45 -> 0
A46: ='Group-Savings'!A46 -> 0 | B46: ='Group-Savings'!B46 -> 0 | C46: ='Group-Savings'!C46 -> 0 | D46: ='Group-Savings'!D46 -> 0 | E46: ='Group-Savings'!E46 -> 0 | F46: ='Group-Savings'!F46 -> 0 | G46: ='Group-Savings'!G46 -> 0 | H46: ='Group-Savings'!H46 -> 0 | ... L46: ='Group-Savings'!L46 -> 0 | M46: =K46+L46 -> 0 | O46: 46 | R46: 30 | S46: 10 | U46: 0 | V46: =S46*U46 -> 0 | W46: 5982100 | X46: 5100000 | Y46: =W46-X46 -> 882100 | Z46: 186000 | AI46: =$AF$46*AH46 -> 0 | AJ46: =AH46+AI46 -> 0 | AL46: =AJ46-AK46 -> 0 | AO46: =$AF$46*AN46 -> 0 | AP46: =AN46+AO46 -> 0 | AR46: =(AP46-AQ46)+AL46 -> 0 | AU46: =$AF$46*AT46 -> 0 | AV46: =AT46+AU46 -> 0 | AX46: =(AV46-AW46)+AR46 -> 0 | BA46: =$AF$46*AZ46 -> 0 | BB46: =AZ46+BA46 -> 0 | BD46: =(BB46-BC46)+AX46 -> 0 | BG46: =$AF$46*BF46 -> 0 | BH46: =BF46+BG46 -> 0 | BJ46: =(BH46-BI46)+BD46 -> 0 | BM46: =$AF$46*BL46 -> 0 | BN46: =BL46+BM46 -> 0 | BP46: =(BN46-BO46)+BJ46 -> 0 | BS46: =$AF$46*BR46 -> 0 | BT46: =BR46+BS46 -> 0 | BV46: =(BT46-BU46)+BP46 -> 0 | BY46: =$AF$46*BX46 -> 0 | BZ46: =BX46+BY46 -> 0 | CB46: =(BZ46-CA46)+BV46 -> 0 | CE46: =$AF$46*CD46 -> 0 | CF46: =CD46+CE46 -> 0 | CH46: =(CF46-CG46)+CB46 -> 0 | CK46: =$AF$46*CJ46 -> 0 | CL46: =CJ46+CK46 -> 0 | CN46: =(CL46-CM46)+CH46 -> 0 | CQ46: =$AF$46*CP46 -> 0 | CR46: =CP46+CQ46 -> 0 | CT46: =(CR46-CS46)+CN46 -> 0 | CW46: =$AF$46*CV46 -> 0 | CX46: =CV46+CW46 -> 0 | CZ46: =(CX46-CY46)+CT46 -> 0 | DA46: =SUM(AG46,AM46,AS46,AY46,BE46,BK46,BQ46,BW46,CC46,CI46,CO46,CU46) -> 0 | DB46: =SUM(AH46,AN46,AT46,AZ46,BF46,BL46,BR46,BX46,CD46,CJ46,CP46,CV46) -> 0 | DC46: =SUM(AI46,AO46,AU46,BA46,BG46,BM46,BS46,BY46,CE46,CK46,CQ46,CW46) -> 0 | DD46: =SUM(AJ46,AP46,AV46,BB46,BH46,BN46,BT46,BZ46,CF46,CL46,CR46,CX46) -> 0 | DE46: =SUM(AK46,AQ46,AW46,BC46,BI46,BO46,BU46,CA46,CG46,CM46,CS46,CY46) -> 0 | DF46: =CZ46 -> 0
A47: ='Group-Savings'!A47 -> 0 | B47: ='Group-Savings'!B47 -> 0 | C47: ='Group-Savings'!C47 -> 0 | D47: ='Group-Savings'!D47 -> 0 | E47: ='Group-Savings'!E47 -> 0 | F47: ='Group-Savings'!F47 -> 0 | G47: ='Group-Savings'!G47 -> 0 | H47: ='Group-Savings'!H47 -> 0 | ... L47: ='Group-Savings'!L47 -> 0 | M47: =K47+L47 -> 0 | O47: 32 | R47: 14 | S47: 10 | U47: 0 | V47: =S47*U47 -> 0 | W47: 1710000 | X47: 726000 | Y47: =W47-X47 -> 984000 | Z47: 192000 | AI47: =$AF$47*AH47 -> 0 | AJ47: =AH47+AI47 -> 0 | AL47: =AJ47-AK47 -> 0 | AO47: =$AF$47*AN47 -> 0 | AP47: =AN47+AO47 -> 0 | AR47: =(AP47-AQ47)+AL47 -> 0 | AU47: =$AF$47*AT47 -> 0 | AV47: =AT47+AU47 -> 0 | AX47: =(AV47-AW47)+AR47 -> 0 | BA47: =$AF$47*AZ47 -> 0 | BB47: =AZ47+BA47 -> 0 | BD47: =(BB47-BC47)+AX47 -> 0 | BG47: =$AF$47*BF47 -> 0 | BH47: =BF47+BG47 -> 0 | BJ47: =(BH47-BI47)+BD47 -> 0 | BM47: =$AF$47*BL47 -> 0 | BN47: =BL47+BM47 -> 0 | BP47: =(BN47-BO47)+BJ47 -> 0 | BS47: =$AF$47*BR47 -> 0 | BT47: =BR47+BS47 -> 0 | BV47: =(BT47-BU47)+BP47 -> 0 | BY47: =$AF$47*BX47 -> 0 | BZ47: =BX47+BY47 -> 0 | CB47: =(BZ47-CA47)+BV47 -> 0 | CE47: =$AF$47*CD47 -> 0 | CF47: =CD47+CE47 -> 0 | CH47: =(CF47-CG47)+CB47 -> 0 | CK47: =$AF$47*CJ47 -> 0 | CL47: =CJ47+CK47 -> 0 | CN47: =(CL47-CM47)+CH47 -> 0 | CQ47: =$AF$47*CP47 -> 0 | CR47: =CP47+CQ47 -> 0 | CT47: =(CR47-CS47)+CN47 -> 0 | CW47: =$AF$47*CV47 -> 0 | CX47: =CV47+CW47 -> 0 | CZ47: =(CX47-CY47)+CT47 -> 0 | DA47: =SUM(AG47,AM47,AS47,AY47,BE47,BK47,BQ47,BW47,CC47,CI47,CO47,CU47) -> 0 | DB47: =SUM(AH47,AN47,AT47,AZ47,BF47,BL47,BR47,BX47,CD47,CJ47,CP47,CV47) -> 0 | DC47: =SUM(AI47,AO47,AU47,BA47,BG47,BM47,BS47,BY47,CE47,CK47,CQ47,CW47) -> 0 | DD47: =SUM(AJ47,AP47,AV47,BB47,BH47,BN47,BT47,BZ47,CF47,CL47,CR47,CX47) -> 0 | DE47: =SUM(AK47,AQ47,AW47,BC47,BI47,BO47,BU47,CA47,CG47,CM47,CS47,CY47) -> 0 | DF47: =CZ47 -> 0
A48: ='Group-Savings'!A48 -> 0 | B48: ='Group-Savings'!B48 -> 0 | C48: ='Group-Savings'!C48 -> 0 | D48: ='Group-Savings'!D48 -> 0 | E48: ='Group-Savings'!E48 -> 0 | F48: ='Group-Savings'!F48 -> 0 | G48: ='Group-Savings'!G48 -> 0 | H48: ='Group-Savings'!H48 -> 0 | ... L48: ='Group-Savings'!L48 -> 0 | M48: =K48+L48 -> 0 | O48: 24 | R48: 10 | S48: 10 | U48: 0 | V48: =S48*U48 -> 0 | W48: 638000 | X48: 750000 | Y48: =W48-X48 -> -112000 | Z48: 192000 | AI48: =$AF$48*AH48 -> 0 | AJ48: =AH48+AI48 -> 0 | AL48: =AJ48-AK48 -> 0 | AO48: =$AF$48*AN48 -> 0 | AP48: =AN48+AO48 -> 0 | AR48: =(AP48-AQ48)+AL48 -> 0 | AU48: =$AF$48*AT48 -> 0 | AV48: =AT48+AU48 -> 0 | AX48: =(AV48-AW48)+AR48 -> 0 | BA48: =$AF$48*AZ48 -> 0 | BB48: =AZ48+BA48 -> 0 | BD48: =(BB48-BC48)+AX48 -> 0 | BG48: =$AF$48*BF48 -> 0 | BH48: =BF48+BG48 -> 0 | BJ48: =(BH48-BI48)+BD48 -> 0 | BM48: =$AF$48*BL48 -> 0 | BN48: =BL48+BM48 -> 0 | BP48: =(BN48-BO48)+BJ48 -> 0 | BS48: =$AF$48*BR48 -> 0 | BT48: =BR48+BS48 -> 0 | BV48: =(BT48-BU48)+BP48 -> 0 | BY48: =$AF$48*BX48 -> 0 | BZ48: =BX48+BY48 -> 0 | CB48: =(BZ48-CA48)+BV48 -> 0 | CE48: =$AF$48*CD48 -> 0 | CF48: =CD48+CE48 -> 0 | CH48: =(CF48-CG48)+CB48 -> 0 | CK48: =$AF$48*CJ48 -> 0 | CL48: =CJ48+CK48 -> 0 | CN48: =(CL48-CM48)+CH48 -> 0 | CQ48: =$AF$48*CP48 -> 0 | CR48: =CP48+CQ48 -> 0 | CT48: =(CR48-CS48)+CN48 -> 0 | CW48: =$AF$48*CV48 -> 0 | CX48: =CV48+CW48 -> 0 | CZ48: =(CX48-CY48)+CT48 -> 0 | DA48: =SUM(AG48,AM48,AS48,AY48,BE48,BK48,BQ48,BW48,CC48,CI48,CO48,CU48) -> 0 | DB48: =SUM(AH48,AN48,AT48,AZ48,BF48,BL48,BR48,BX48,CD48,CJ48,CP48,CV48) -> 0 | DC48: =SUM(AI48,AO48,AU48,BA48,BG48,BM48,BS48,BY48,CE48,CK48,CQ48,CW48) -> 0 | DD48: =SUM(AJ48,AP48,AV48,BB48,BH48,BN48,BT48,BZ48,CF48,CL48,CR48,CX48) -> 0 | DE48: =SUM(AK48,AQ48,AW48,BC48,BI48,BO48,BU48,CA48,CG48,CM48,CS48,CY48) -> 0 | DF48: =CZ48 -> 0
A49: ='Group-Savings'!A49 -> 0 | B49: ='Group-Savings'!B49 -> 0 | C49: ='Group-Savings'!C49 -> 0 | D49: ='Group-Savings'!D49 -> 0 | E49: ='Group-Savings'!E49 -> 0 | F49: ='Group-Savings'!F49 -> 0 | G49: ='Group-Savings'!G49 -> 0 | H49: ='Group-Savings'!H49 -> 0 | ... L49: ='Group-Savings'!L49 -> 0 | M49: =K49+L49 -> 0 | O49: 10 | R49: 25 | S49: 10 | U49: 0 | V49: =S49*U49 -> 0 | W49: 1045000 | X49: 1045000 | Y49: =W49-X49 -> 0 | Z49: 132500 | AI49: =$AF$49*AH49 -> 0 | AJ49: =AH49+AI49 -> 0 | AL49: =AJ49-AK49 -> 0 | AO49: =$AF$49*AN49 -> 0 | AP49: =AN49+AO49 -> 0 | AR49: =(AP49-AQ49)+AL49 -> 0 | AU49: =$AF$49*AT49 -> 0 | AV49: =AT49+AU49 -> 0 | AX49: =(AV49-AW49)+AR49 -> 0 | BA49: =$AF$49*AZ49 -> 0 | BB49: =AZ49+BA49 -> 0 | BD49: =(BB49-BC49)+AX49 -> 0 | BG49: =$AF$49*BF49 -> 0 | BH49: =BF49+BG49 -> 0 | BJ49: =(BH49-BI49)+BD49 -> 0 | BM49: =$AF$49*BL49 -> 0 | BN49: =BL49+BM49 -> 0 | BP49: =(BN49-BO49)+BJ49 -> 0 | BS49: =$AF$49*BR49 -> 0 | BT49: =BR49+BS49 -> 0 | BV49: =(BT49-BU49)+BP49 -> 0 | BY49: =$AF$49*BX49 -> 0 | BZ49: =BX49+BY49 -> 0 | CB49: =(BZ49-CA49)+BV49 -> 0 | CE49: =$AF$49*CD49 -> 0 | CF49: =CD49+CE49 -> 0 | CH49: =(CF49-CG49)+CB49 -> 0 | CK49: =$AF$49*CJ49 -> 0 | CL49: =CJ49+CK49 -> 0 | CN49: =(CL49-CM49)+CH49 -> 0 | CQ49: =$AF$49*CP49 -> 0 | CR49: =CP49+CQ49 -> 0 | CT49: =(CR49-CS49)+CN49 -> 0 | CW49: =$AF$49*CV49 -> 0 | CX49: =CV49+CW49 -> 0 | CZ49: =(CX49-CY49)+CT49 -> 0 | DA49: =SUM(AG49,AM49,AS49,AY49,BE49,BK49,BQ49,BW49,CC49,CI49,CO49,CU49) -> 0 | DB49: =SUM(AH49,AN49,AT49,AZ49,BF49,BL49,BR49,BX49,CD49,CJ49,CP49,CV49) -> 0 | DC49: =SUM(AI49,AO49,AU49,BA49,BG49,BM49,BS49,BY49,CE49,CK49,CQ49,CW49) -> 0 | DD49: =SUM(AJ49,AP49,AV49,BB49,BH49,BN49,BT49,BZ49,CF49,CL49,CR49,CX49) -> 0 | DE49: =SUM(AK49,AQ49,AW49,BC49,BI49,BO49,BU49,CA49,CG49,CM49,CS49,CY49) -> 0 | DF49: =CZ49 -> 0
A50: ='Group-Savings'!A50 -> 0 | B50: ='Group-Savings'!B50 -> 0 | C50: ='Group-Savings'!C50 -> 0 | D50: ='Group-Savings'!D50 -> 0 | E50: ='Group-Savings'!E50 -> 0 | F50: ='Group-Savings'!F50 -> 0 | G50: ='Group-Savings'!G50 -> 0 | H50: ='Group-Savings'!H50 -> 0 | ... L50: ='Group-Savings'!L50 -> 0 | M50: =K50+L50 -> 0 | O50: 40 | R50: 30 | S50: 10 | U50: 0 | V50: =S50*U50 -> 0 | W50: 20235000 | X50: 13635000 | Y50: =W50-X50 -> 6600000 | Z50: 400000 | AI50: =$AF$50*AH50 -> 0 | AJ50: =AH50+AI50 -> 0 | AL50: =AJ50-AK50 -> 0 | AO50: =$AF$50*AN50 -> 0 | AP50: =AN50+AO50 -> 0 | AR50: =(AP50-AQ50)+AL50 -> 0 | AU50: =$AF$50*AT50 -> 0 | AV50: =AT50+AU50 -> 0 | AX50: =(AV50-AW50)+AR50 -> 0 | BA50: =$AF$50*AZ50 -> 0 | BB50: =AZ50+BA50 -> 0 | BD50: =(BB50-BC50)+AX50 -> 0 | BG50: =$AF$50*BF50 -> 0 | BH50: =BF50+BG50 -> 0 | BJ50: =(BH50-BI50)+BD50 -> 0 | BM50: =$AF$50*BL50 -> 0 | BN50: =BL50+BM50 -> 0 | BP50: =(BN50-BO50)+BJ50 -> 0 | BS50: =$AF$50*BR50 -> 0 | BT50: =BR50+BS50 -> 0 | BV50: =(BT50-BU50)+BP50 -> 0 | BY50: =$AF$50*BX50 -> 0 | BZ50: =BX50+BY50 -> 0 | CB50: =(BZ50-CA50)+BV50 -> 0 | CE50: =$AF$50*CD50 -> 0 | CF50: =CD50+CE50 -> 0 | CH50: =(CF50-CG50)+CB50 -> 0 | CK50: =$AF$50*CJ50 -> 0 | CL50: =CJ50+CK50 -> 0 | CN50: =(CL50-CM50)+CH50 -> 0 | CQ50: =$AF$50*CP50 -> 0 | CR50: =CP50+CQ50 -> 0 | CT50: =(CR50-CS50)+CN50 -> 0 | CW50: =$AF$50*CV50 -> 0 | CX50: =CV50+CW50 -> 0 | CZ50: =(CX50-CY50)+CT50 -> 0 | DA50: =SUM(AG50,AM50,AS50,AY50,BE50,BK50,BQ50,BW50,CC50,CI50,CO50,CU50) -> 0 | DB50: =SUM(AH50,AN50,AT50,AZ50,BF50,BL50,BR50,BX50,CD50,CJ50,CP50,CV50) -> 0 | DC50: =SUM(AI50,AO50,AU50,BA50,BG50,BM50,BS50,BY50,CE50,CK50,CQ50,CW50) -> 0 | DD50: =SUM(AJ50,AP50,AV50,BB50,BH50,BN50,BT50,BZ50,CF50,CL50,CR50,CX50) -> 0 | DE50: =SUM(AK50,AQ50,AW50,BC50,BI50,BO50,BU50,CA50,CG50,CM50,CS50,CY50) -> 0 | DF50: =CZ50 -> 0
A51: ='Group-Savings'!A51 -> 0 | B51: ='Group-Savings'!B51 -> 0 | C51: ='Group-Savings'!C51 -> 0 | D51: ='Group-Savings'!D51 -> 0 | E51: ='Group-Savings'!E51 -> 0 | F51: ='Group-Savings'!F51 -> 0 | G51: ='Group-Savings'!G51 -> 0 | H51: ='Group-Savings'!H51 -> 0 | ... L51: ='Group-Savings'!L51 -> 0 | M51: =K51+L51 -> 0 | O51: 32 | R51: 10 | S51: 10 | U51: 0 | V51: =S51*U51 -> 0 | W51: 650000 | X51: 300000 | Y51: =W51-X51 -> 350000 | Z51: 216000 | AI51: =$AF$51*AH51 -> 0 | AJ51: =AH51+AI51 -> 0 | AL51: =AJ51-AK51 -> 0 | AO51: =$AF$51*AN51 -> 0 | AP51: =AN51+AO51 -> 0 | AR51: =(AP51-AQ51)+AL51 -> 0 | AU51: =$AF$51*AT51 -> 0 | AV51: =AT51+AU51 -> 0 | AX51: =(AV51-AW51)+AR51 -> 0 | BA51: =$AF$51*AZ51 -> 0 | BB51: =AZ51+BA51 -> 0 | BD51: =(BB51-BC51)+AX51 -> 0 | BG51: =$AF$51*BF51 -> 0 | BH51: =BF51+BG51 -> 0 | BJ51: =(BH51-BI51)+BD51 -> 0 | BM51: =$AF$51*BL51 -> 0 | BN51: =BL51+BM51 -> 0 | BP51: =(BN51-BO51)+BJ51 -> 0 | BS51: =$AF$51*BR51 -> 0 | BT51: =BR51+BS51 -> 0 | BV51: =(BT51-BU51)+BP51 -> 0 | BY51: =$AF$51*BX51 -> 0 | BZ51: =BX51+BY51 -> 0 | CB51: =(BZ51-CA51)+BV51 -> 0 | CE51: =$AF$51*CD51 -> 0 | CF51: =CD51+CE51 -> 0 | CH51: =(CF51-CG51)+CB51 -> 0 | CK51: =$AF$51*CJ51 -> 0 | CL51: =CJ51+CK51 -> 0 | CN51: =(CL51-CM51)+CH51 -> 0 | CQ51: =$AF$51*CP51 -> 0 | CR51: =CP51+CQ51 -> 0 | CT51: =(CR51-CS51)+CN51 -> 0 | CW51: =$AF$51*CV51 -> 0 | CX51: =CV51+CW51 -> 0 | CZ51: =(CX51-CY51)+CT51 -> 0 | DA51: =SUM(AG51,AM51,AS51,AY51,BE51,BK51,BQ51,BW51,CC51,CI51,CO51,CU51) -> 0 | DB51: =SUM(AH51,AN51,AT51,AZ51,BF51,BL51,BR51,BX51,CD51,CJ51,CP51,CV51) -> 0 | DC51: =SUM(AI51,AO51,AU51,BA51,BG51,BM51,BS51,BY51,CE51,CK51,CQ51,CW51) -> 0 | DD51: =SUM(AJ51,AP51,AV51,BB51,BH51,BN51,BT51,BZ51,CF51,CL51,CR51,CX51) -> 0 | DE51: =SUM(AK51,AQ51,AW51,BC51,BI51,BO51,BU51,CA51,CG51,CM51,CS51,CY51) -> 0 | DF51: =CZ51 -> 0
A52: ='Group-Savings'!A52 -> 0 | B52: ='Group-Savings'!B52 -> 0 | C52: ='Group-Savings'!C52 -> 0 | D52: ='Group-Savings'!D52 -> 0 | E52: ='Group-Savings'!E52 -> 0 | F52: ='Group-Savings'!F52 -> 0 | G52: ='Group-Savings'!G52 -> 0 | H52: ='Group-Savings'!H52 -> 0 | ... L52: ='Group-Savings'!L52 -> 0 | M52: =K52+L52 -> 0 | O52: 32 | R52: 28 | S52: 10 | U52: 0 | V52: =S52*U52 -> 0 | W52: 1306000 | X52: 457000 | Y52: =W52-X52 -> 849000 | Z52: 490000 | AI52: =$AF$52*AH52 -> 0 | AJ52: =AH52+AI52 -> 0 | AL52: =AJ52-AK52 -> 0 | AO52: =$AF$52*AN52 -> 0 | AP52: =AN52+AO52 -> 0 | AR52: =(AP52-AQ52)+AL52 -> 0 | AU52: =$AF$52*AT52 -> 0 | AV52: =AT52+AU52 -> 0 | AX52: =(AV52-AW52)+AR52 -> 0 | BA52: =$AF$52*AZ52 -> 0 | BB52: =AZ52+BA52 -> 0 | BD52: =(BB52-BC52)+AX52 -> 0 | BG52: =$AF$52*BF52 -> 0 | BH52: =BF52+BG52 -> 0 | BJ52: =(BH52-BI52)+BD52 -> 0 | BM52: =$AF$52*BL52 -> 0 | BN52: =BL52+BM52 -> 0 | BP52: =(BN52-BO52)+BJ52 -> 0 | BS52: =$AF$52*BR52 -> 0 | BT52: =BR52+BS52 -> 0 | BV52: =(BT52-BU52)+BP52 -> 0 | BY52: =$AF$52*BX52 -> 0 | BZ52: =BX52+BY52 -> 0 | CB52: =(BZ52-CA52)+BV52 -> 0 | CE52: =$AF$52*CD52 -> 0 | CF52: =CD52+CE52 -> 0 | CH52: =(CF52-CG52)+CB52 -> 0 | CK52: =$AF$52*CJ52 -> 0 | CL52: =CJ52+CK52 -> 0 | CN52: =(CL52-CM52)+CH52 -> 0 | CQ52: =$AF$52*CP52 -> 0 | CR52: =CP52+CQ52 -> 0 | CT52: =(CR52-CS52)+CN52 -> 0 | CW52: =$AF$52*CV52 -> 0 | CX52: =CV52+CW52 -> 0 | CZ52: =(CX52-CY52)+CT52 -> 0 | DA52: =SUM(AG52,AM52,AS52,AY52,BE52,BK52,BQ52,BW52,CC52,CI52,CO52,CU52) -> 0 | DB52: =SUM(AH52,AN52,AT52,AZ52,BF52,BL52,BR52,BX52,CD52,CJ52,CP52,CV52) -> 0 | DC52: =SUM(AI52,AO52,AU52,BA52,BG52,BM52,BS52,BY52,CE52,CK52,CQ52,CW52) -> 0 | DD52: =SUM(AJ52,AP52,AV52,BB52,BH52,BN52,BT52,BZ52,CF52,CL52,CR52,CX52) -> 0 | DE52: =SUM(AK52,AQ52,AW52,BC52,BI52,BO52,BU52,CA52,CG52,CM52,CS52,CY52) -> 0 | DF52: =CZ52 -> 0
A53: ='Group-Savings'!A53 -> 0 | B53: ='Group-Savings'!B53 -> 0 | C53: ='Group-Savings'!C53 -> 0 | D53: ='Group-Savings'!D53 -> 0 | E53: ='Group-Savings'!E53 -> 0 | F53: ='Group-Savings'!F53 -> 0 | G53: ='Group-Savings'!G53 -> 0 | H53: ='Group-Savings'!H53 -> 0 | ... L53: ='Group-Savings'!L53 -> 0 | M53: =K53+L53 -> 0 | O53: 32 | R53: 14 | S53: 10 | U53: 0 | V53: =S53*U53 -> 0 | W53: 430000 | X53: 286000 | Y53: =W53-X53 -> 144000 | Z53: 192000 | AI53: =$AF$53*AH53 -> 0 | AJ53: =AH53+AI53 -> 0 | AL53: =AJ53-AK53 -> 0 | AO53: =$AF$53*AN53 -> 0 | AP53: =AN53+AO53 -> 0 | AR53: =(AP53-AQ53)+AL53 -> 0 | AU53: =$AF$53*AT53 -> 0 | AV53: =AT53+AU53 -> 0 | AX53: =(AV53-AW53)+AR53 -> 0 | BA53: =$AF$53*AZ53 -> 0 | BB53: =AZ53+BA53 -> 0 | BD53: =(BB53-BC53)+AX53 -> 0 | BG53: =$AF$53*BF53 -> 0 | BH53: =BF53+BG53 -> 0 | BJ53: =(BH53-BI53)+BD53 -> 0 | BM53: =$AF$53*BL53 -> 0 | BN53: =BL53+BM53 -> 0 | BP53: =(BN53-BO53)+BJ53 -> 0 | BS53: =$AF$53*BR53 -> 0 | BT53: =BR53+BS53 -> 0 | BV53: =(BT53-BU53)+BP53 -> 0 | BY53: =$AF$53*BX53 -> 0 | BZ53: =BX53+BY53 -> 0 | CB53: =(BZ53-CA53)+BV53 -> 0 | CE53: =$AF$53*CD53 -> 0 | CF53: =CD53+CE53 -> 0 | CH53: =(CF53-CG53)+CB53 -> 0 | CK53: =$AF$53*CJ53 -> 0 | CL53: =CJ53+CK53 -> 0 | CN53: =(CL53-CM53)+CH53 -> 0 | CQ53: =$AF$53*CP53 -> 0 | CR53: =CP53+CQ53 -> 0 | CT53: =(CR53-CS53)+CN53 -> 0 | CW53: =$AF$53*CV53 -> 0 | CX53: =CV53+CW53 -> 0 | CZ53: =(CX53-CY53)+CT53 -> 0 | DA53: =SUM(AG53,AM53,AS53,AY53,BE53,BK53,BQ53,BW53,CC53,CI53,CO53,CU53) -> 0 | DB53: =SUM(AH53,AN53,AT53,AZ53,BF53,BL53,BR53,BX53,CD53,CJ53,CP53,CV53) -> 0 | DC53: =SUM(AI53,AO53,AU53,BA53,BG53,BM53,BS53,BY53,CE53,CK53,CQ53,CW53) -> 0 | DD53: =SUM(AJ53,AP53,AV53,BB53,BH53,BN53,BT53,BZ53,CF53,CL53,CR53,CX53) -> 0 | DE53: =SUM(AK53,AQ53,AW53,BC53,BI53,BO53,BU53,CA53,CG53,CM53,CS53,CY53) -> 0 | DF53: =CZ53 -> 0
A54: ='Group-Savings'!A54 -> 0 | B54: ='Group-Savings'!B54 -> 0 | C54: ='Group-Savings'!C54 -> 0 | D54: ='Group-Savings'!D54 -> 0 | E54: ='Group-Savings'!E54 -> 0 | F54: ='Group-Savings'!F54 -> 0 | G54: ='Group-Savings'!G54 -> 0 | H54: ='Group-Savings'!H54 -> 0 | ... L54: ='Group-Savings'!L54 -> 0 | M54: =K54+L54 -> 0 | O54: 28 | R54: 5 | S54: 10 | U54: 0 | V54: =S54*U54 -> 0 | W54: 200000 | X54: 55000 | Y54: =W54-X54 -> 145000 | Z54: 168000 | AI54: =$AF$54*AH54 -> 0 | AJ54: =AH54+AI54 -> 0 | AL54: =AJ54-AK54 -> 0 | AO54: =$AF$54*AN54 -> 0 | AP54: =AN54+AO54 -> 0 | AR54: =(AP54-AQ54)+AL54 -> 0 | AU54: =$AF$54*AT54 -> 0 | AV54: =AT54+AU54 -> 0 | AX54: =(AV54-AW54)+AR54 -> 0 | BA54: =$AF$54*AZ54 -> 0 | BB54: =AZ54+BA54 -> 0 | BD54: =(BB54-BC54)+AX54 -> 0 | BG54: =$AF$54*BF54 -> 0 | BH54: =BF54+BG54 -> 0 | BJ54: =(BH54-BI54)+BD54 -> 0 | BM54: =$AF$54*BL54 -> 0 | BN54: =BL54+BM54 -> 0 | BP54: =(BN54-BO54)+BJ54 -> 0 | BS54: =$AF$54*BR54 -> 0 | BT54: =BR54+BS54 -> 0 | BV54: =(BT54-BU54)+BP54 -> 0 | BY54: =$AF$54*BX54 -> 0 | BZ54: =BX54+BY54 -> 0 | CB54: =(BZ54-CA54)+BV54 -> 0 | CE54: =$AF$54*CD54 -> 0 | CF54: =CD54+CE54 -> 0 | CH54: =(CF54-CG54)+CB54 -> 0 | CK54: =$AF$54*CJ54 -> 0 | CL54: =CJ54+CK54 -> 0 | CN54: =(CL54-CM54)+CH54 -> 0 | CQ54: =$AF$54*CP54 -> 0 | CR54: =CP54+CQ54 -> 0 | CT54: =(CR54-CS54)+CN54 -> 0 | CW54: =$AF$54*CV54 -> 0 | CX54: =CV54+CW54 -> 0 | CZ54: =(CX54-CY54)+CT54 -> 0 | DA54: =SUM(AG54,AM54,AS54,AY54,BE54,BK54,BQ54,BW54,CC54,CI54,CO54,CU54) -> 0 | DB54: =SUM(AH54,AN54,AT54,AZ54,BF54,BL54,BR54,BX54,CD54,CJ54,CP54,CV54) -> 0 | DC54: =SUM(AI54,AO54,AU54,BA54,BG54,BM54,BS54,BY54,CE54,CK54,CQ54,CW54) -> 0 | DD54: =SUM(AJ54,AP54,AV54,BB54,BH54,BN54,BT54,BZ54,CF54,CL54,CR54,CX54) -> 0 | DE54: =SUM(AK54,AQ54,AW54,BC54,BI54,BO54,BU54,CA54,CG54,CM54,CS54,CY54) -> 0 | DF54: =CZ54 -> 0
A55: ='Group-Savings'!A55 -> 0 | B55: ='Group-Savings'!B55 -> 0 | C55: ='Group-Savings'!C55 -> 0 | D55: ='Group-Savings'!D55 -> 0 | E55: ='Group-Savings'!E55 -> 0 | F55: ='Group-Savings'!F55 -> 0 | G55: ='Group-Savings'!G55 -> 0 | H55: ='Group-Savings'!H55 -> 0 | ... L55: ='Group-Savings'!L55 -> 0 | M55: =K55+L55 -> 0 | O55: 32 | R55: 30 | S55: 10 | U55: 0 | V55: =S55*U55 -> 0 | W55: 610000 | X55: 413500 | Y55: =W55-X55 -> 196500 | Z55: 40700 | AI55: =$AF$55*AH55 -> 0 | AJ55: =AH55+AI55 -> 0 | AL55: =AJ55-AK55 -> 0 | AO55: =$AF$55*AN55 -> 0 | AP55: =AN55+AO55 -> 0 | AR55: =(AP55-AQ55)+AL55 -> 0 | AU55: =$AF$55*AT55 -> 0 | AV55: =AT55+AU55 -> 0 | AX55: =(AV55-AW55)+AR55 -> 0 | BA55: =$AF$55*AZ55 -> 0 | BB55: =AZ55+BA55 -> 0 | BD55: =(BB55-BC55)+AX55 -> 0 | BG55: =$AF$55*BF55 -> 0 | BH55: =BF55+BG55 -> 0 | BJ55: =(BH55-BI55)+BD55 -> 0 | BM55: =$AF$55*BL55 -> 0 | BN55: =BL55+BM55 -> 0 | BP55: =(BN55-BO55)+BJ55 -> 0 | BS55: =$AF$55*BR55 -> 0 | BT55: =BR55+BS55 -> 0 | BV55: =(BT55-BU55)+BP55 -> 0 | BY55: =$AF$55*BX55 -> 0 | BZ55: =BX55+BY55 -> 0 | CB55: =(BZ55-CA55)+BV55 -> 0 | CE55: =$AF$55*CD55 -> 0 | CF55: =CD55+CE55 -> 0 | CH55: =(CF55-CG55)+CB55 -> 0 | CK55: =$AF$55*CJ55 -> 0 | CL55: =CJ55+CK55 -> 0 | CN55: =(CL55-CM55)+CH55 -> 0 | CQ55: =$AF$55*CP55 -> 0 | CR55: =CP55+CQ55 -> 0 | CT55: =(CR55-CS55)+CN55 -> 0 | CW55: =$AF$55*CV55 -> 0 | CX55: =CV55+CW55 -> 0 | CZ55: =(CX55-CY55)+CT55 -> 0 | DA55: =SUM(AG55,AM55,AS55,AY55,BE55,BK55,BQ55,BW55,CC55,CI55,CO55,CU55) -> 0 | DB55: =SUM(AH55,AN55,AT55,AZ55,BF55,BL55,BR55,BX55,CD55,CJ55,CP55,CV55) -> 0 | DC55: =SUM(AI55,AO55,AU55,BA55,BG55,BM55,BS55,BY55,CE55,CK55,CQ55,CW55) -> 0 | DD55: =SUM(AJ55,AP55,AV55,BB55,BH55,BN55,BT55,BZ55,CF55,CL55,CR55,CX55) -> 0 | DE55: =SUM(AK55,AQ55,AW55,BC55,BI55,BO55,BU55,CA55,CG55,CM55,CS55,CY55) -> 0 | DF55: =CZ55 -> 0
A56: ='Group-Savings'!A56 -> 0 | B56: ='Group-Savings'!B56 -> 0 | C56: ='Group-Savings'!C56 -> 0 | D56: ='Group-Savings'!D56 -> 0 | E56: ='Group-Savings'!E56 -> 0 | F56: ='Group-Savings'!F56 -> 0 | G56: ='Group-Savings'!G56 -> 0 | H56: ='Group-Savings'!H56 -> 0 | ... L56: ='Group-Savings'!L56 -> 0 | M56: =K56+L56 -> 0 | O56: 36 | R56: 33 | S56: 10 | U56: 0 | V56: =S56*U56 -> 0 | W56: 1120000 | X56: 1120000 | Y56: =W56-X56 -> 0 | Z56: 216000 | AI56: =$AF$56*AH56 -> 0 | AJ56: =AH56+AI56 -> 0 | AL56: =AJ56-AK56 -> 0 | AO56: =$AF$56*AN56 -> 0 | AP56: =AN56+AO56 -> 0 | AR56: =(AP56-AQ56)+AL56 -> 0 | AU56: =$AF$56*AT56 -> 0 | AV56: =AT56+AU56 -> 0 | AX56: =(AV56-AW56)+AR56 -> 0 | BA56: =$AF$56*AZ56 -> 0 | BB56: =AZ56+BA56 -> 0 | BD56: =(BB56-BC56)+AX56 -> 0 | BG56: =$AF$56*BF56 -> 0 | BH56: =BF56+BG56 -> 0 | BJ56: =(BH56-BI56)+BD56 -> 0 | BM56: =$AF$56*BL56 -> 0 | BN56: =BL56+BM56 -> 0 | BP56: =(BN56-BO56)+BJ56 -> 0 | BS56: =$AF$56*BR56 -> 0 | BT56: =BR56+BS56 -> 0 | BV56: =(BT56-BU56)+BP56 -> 0 | BY56: =$AF$56*BX56 -> 0 | BZ56: =BX56+BY56 -> 0 | CB56: =(BZ56-CA56)+BV56 -> 0 | CE56: =$AF$56*CD56 -> 0 | CF56: =CD56+CE56 -> 0 | CH56: =(CF56-CG56)+CB56 -> 0 | CK56: =$AF$56*CJ56 -> 0 | CL56: =CJ56+CK56 -> 0 | CN56: =(CL56-CM56)+CH56 -> 0 | CQ56: =$AF$56*CP56 -> 0 | CR56: =CP56+CQ56 -> 0 | CT56: =(CR56-CS56)+CN56 -> 0 | CW56: =$AF$56*CV56 -> 0 | CX56: =CV56+CW56 -> 0 | CZ56: =(CX56-CY56)+CT56 -> 0 | DA56: =SUM(AG56,AM56,AS56,AY56,BE56,BK56,BQ56,BW56,CC56,CI56,CO56,CU56) -> 0 | DB56: =SUM(AH56,AN56,AT56,AZ56,BF56,BL56,BR56,BX56,CD56,CJ56,CP56,CV56) -> 0 | DC56: =SUM(AI56,AO56,AU56,BA56,BG56,BM56,BS56,BY56,CE56,CK56,CQ56,CW56) -> 0 | DD56: =SUM(AJ56,AP56,AV56,BB56,BH56,BN56,BT56,BZ56,CF56,CL56,CR56,CX56) -> 0 | DE56: =SUM(AK56,AQ56,AW56,BC56,BI56,BO56,BU56,CA56,CG56,CM56,CS56,CY56) -> 0 | DF56: =CZ56 -> 0
A57: ='Group-Savings'!A57 -> 0 | B57: ='Group-Savings'!B57 -> 0 | C57: ='Group-Savings'!C57 -> 0 | D57: ='Group-Savings'!D57 -> 0 | E57: ='Group-Savings'!E57 -> 0 | F57: ='Group-Savings'!F57 -> 0 | G57: ='Group-Savings'!G57 -> 0 | H57: ='Group-Savings'!H57 -> 0 | ... L57: ='Group-Savings'!L57 -> 0 | M57: =K57+L57 -> 0 | O57: 32 | R57: 33 | S57: 10 | U57: 0 | V57: =S57*U57 -> 0 | W57: 774000 | X57: 429000 | Y57: =W57-X57 -> 345000 | Z57: 192000 | AI57: =$AF$57*AH57 -> 0 | AJ57: =AH57+AI57 -> 0 | AL57: =AJ57-AK57 -> 0 | AO57: =$AF$57*AN57 -> 0 | AP57: =AN57+AO57 -> 0 | AR57: =(AP57-AQ57)+AL57 -> 0 | AU57: =$AF$57*AT57 -> 0 | AV57: =AT57+AU57 -> 0 | AX57: =(AV57-AW57)+AR57 -> 0 | BA57: =$AF$57*AZ57 -> 0 | BB57: =AZ57+BA57 -> 0 | BD57: =(BB57-BC57)+AX57 -> 0 | BG57: =$AF$57*BF57 -> 0 | BH57: =BF57+BG57 -> 0 | BJ57: =(BH57-BI57)+BD57 -> 0 | BM57: =$AF$57*BL57 -> 0 | BN57: =BL57+BM57 -> 0 | BP57: =(BN57-BO57)+BJ57 -> 0 | BS57: =$AF$57*BR57 -> 0 | BT57: =BR57+BS57 -> 0 | BV57: =(BT57-BU57)+BP57 -> 0 | BY57: =$AF$57*BX57 -> 0 | BZ57: =BX57+BY57 -> 0 | CB57: =(BZ57-CA57)+BV57 -> 0 | CE57: =$AF$57*CD57 -> 0 | CF57: =CD57+CE57 -> 0 | CH57: =(CF57-CG57)+CB57 -> 0 | CK57: =$AF$57*CJ57 -> 0 | CL57: =CJ57+CK57 -> 0 | CN57: =(CL57-CM57)+CH57 -> 0 | CQ57: =$AF$57*CP57 -> 0 | CR57: =CP57+CQ57 -> 0 | CT57: =(CR57-CS57)+CN57 -> 0 | CW57: =$AF$57*CV57 -> 0 | CX57: =CV57+CW57 -> 0 | CZ57: =(CX57-CY57)+CT57 -> 0 | DA57: =SUM(AG57,AM57,AS57,AY57,BE57,BK57,BQ57,BW57,CC57,CI57,CO57,CU57) -> 0 | DB57: =SUM(AH57,AN57,AT57,AZ57,BF57,BL57,BR57,BX57,CD57,CJ57,CP57,CV57) -> 0 | DC57: =SUM(AI57,AO57,AU57,BA57,BG57,BM57,BS57,BY57,CE57,CK57,CQ57,CW57) -> 0 | DD57: =SUM(AJ57,AP57,AV57,BB57,BH57,BN57,BT57,BZ57,CF57,CL57,CR57,CX57) -> 0 | DE57: =SUM(AK57,AQ57,AW57,BC57,BI57,BO57,BU57,CA57,CG57,CM57,CS57,CY57) -> 0 | DF57: =CZ57 -> 0
A58: ='Group-Savings'!A58 -> 0 | B58: ='Group-Savings'!B58 -> 0 | C58: ='Group-Savings'!C58 -> 0 | D58: ='Group-Savings'!D58 -> 0 | E58: ='Group-Savings'!E58 -> 0 | F58: ='Group-Savings'!F58 -> 0 | G58: ='Group-Savings'!G58 -> 0 | H58: ='Group-Savings'!H58 -> 0 | ... L58: ='Group-Savings'!L58 -> 0 | M58: =K58+L58 -> 0 | O58: 32 | R58: 11 | S58: 10 | U58: 0 | V58: =S58*U58 -> 0 | W58: 300000 | X58: 150000 | Y58: =W58-X58 -> 150000 | Z58: 192000 | AI58: =$AF$58*AH58 -> 0 | AJ58: =AH58+AI58 -> 0 | AL58: =AJ58-AK58 -> 0 | AO58: =$AF$58*AN58 -> 0 | AP58: =AN58+AO58 -> 0 | AR58: =(AP58-AQ58)+AL58 -> 0 | AU58: =$AF$58*AT58 -> 0 | AV58: =AT58+AU58 -> 0 | AX58: =(AV58-AW58)+AR58 -> 0 | BA58: =$AF$58*AZ58 -> 0 | BB58: =AZ58+BA58 -> 0 | BD58: =(BB58-BC58)+AX58 -> 0 | BG58: =$AF$58*BF58 -> 0 | BH58: =BF58+BG58 -> 0 | BJ58: =(BH58-BI58)+BD58 -> 0 | BM58: =$AF$58*BL58 -> 0 | BN58: =BL58+BM58 -> 0 | BP58: =(BN58-BO58)+BJ58 -> 0 | BS58: =$AF$58*BR58 -> 0 | BT58: =BR58+BS58 -> 0 | BV58: =(BT58-BU58)+BP58 -> 0 | BY58: =$AF$58*BX58 -> 0 | BZ58: =BX58+BY58 -> 0 | CB58: =(BZ58-CA58)+BV58 -> 0 | CE58: =$AF$58*CD58 -> 0 | CF58: =CD58+CE58 -> 0 | CH58: =(CF58-CG58)+CB58 -> 0 | CK58: =$AF$58*CJ58 -> 0 | CL58: =CJ58+CK58 -> 0 | CN58: =(CL58-CM58)+CH58 -> 0 | CQ58: =$AF$58*CP58 -> 0 | CR58: =CP58+CQ58 -> 0 | CT58: =(CR58-CS58)+CN58 -> 0 | CW58: =$AF$58*CV58 -> 0 | CX58: =CV58+CW58 -> 0 | CZ58: =(CX58-CY58)+CT58 -> 0 | DA58: =SUM(AG58,AM58,AS58,AY58,BE58,BK58,BQ58,BW58,CC58,CI58,CO58,CU58) -> 0 | DB58: =SUM(AH58,AN58,AT58,AZ58,BF58,BL58,BR58,BX58,CD58,CJ58,CP58,CV58) -> 0 | DC58: =SUM(AI58,AO58,AU58,BA58,BG58,BM58,BS58,BY58,CE58,CK58,CQ58,CW58) -> 0 | DD58: =SUM(AJ58,AP58,AV58,BB58,BH58,BN58,BT58,BZ58,CF58,CL58,CR58,CX58) -> 0 | DE58: =SUM(AK58,AQ58,AW58,BC58,BI58,BO58,BU58,CA58,CG58,CM58,CS58,CY58) -> 0 | DF58: =CZ58 -> 0
A59: ='Group-Savings'!A59 -> 0 | B59: ='Group-Savings'!B59 -> 0 | C59: ='Group-Savings'!C59 -> 0 | D59: ='Group-Savings'!D59 -> 0 | E59: ='Group-Savings'!E59 -> 0 | F59: ='Group-Savings'!F59 -> 0 | G59: ='Group-Savings'!G59 -> 0 | H59: ='Group-Savings'!H59 -> 0 | ... L59: ='Group-Savings'!L59 -> 0 | M59: =K59+L59 -> 0 | O59: 32 | R59: 14 | S59: 10 | U59: 0 | V59: =S59*U59 -> 0 | W59: 9000000 | X59: 988000 | Y59: =W59-X59 -> 8012000 | Z59: 1175000 | AI59: =$AF$59*AH59 -> 0 | AJ59: =AH59+AI59 -> 0 | AL59: =AJ59-AK59 -> 0 | AO59: =$AF$59*AN59 -> 0 | AP59: =AN59+AO59 -> 0 | AR59: =(AP59-AQ59)+AL59 -> 0 | AU59: =$AF$59*AT59 -> 0 | AV59: =AT59+AU59 -> 0 | AX59: =(AV59-AW59)+AR59 -> 0 | BA59: =$AF$59*AZ59 -> 0 | BB59: =AZ59+BA59 -> 0 | BD59: =(BB59-BC59)+AX59 -> 0 | BG59: =$AF$59*BF59 -> 0 | BH59: =BF59+BG59 -> 0 | BJ59: =(BH59-BI59)+BD59 -> 0 | BM59: =$AF$59*BL59 -> 0 | BN59: =BL59+BM59 -> 0 | BP59: =(BN59-BO59)+BJ59 -> 0 | BS59: =$AF$59*BR59 -> 0 | BT59: =BR59+BS59 -> 0 | BV59: =(BT59-BU59)+BP59 -> 0 | BY59: =$AF$59*BX59 -> 0 | BZ59: =BX59+BY59 -> 0 | CB59: =(BZ59-CA59)+BV59 -> 0 | CE59: =$AF$59*CD59 -> 0 | CF59: =CD59+CE59 -> 0 | CH59: =(CF59-CG59)+CB59 -> 0 | CK59: =$AF$59*CJ59 -> 0 | CL59: =CJ59+CK59 -> 0 | CN59: =(CL59-CM59)+CH59 -> 0 | CQ59: =$AF$59*CP59 -> 0 | CR59: =CP59+CQ59 -> 0 | CT59: =(CR59-CS59)+CN59 -> 0 | CW59: =$AF$59*CV59 -> 0 | CX59: =CV59+CW59 -> 0 | CZ59: =(CX59-CY59)+CT59 -> 0 | DA59: =SUM(AG59,AM59,AS59,AY59,BE59,BK59,BQ59,BW59,CC59,CI59,CO59,CU59) -> 0 | DB59: =SUM(AH59,AN59,AT59,AZ59,BF59,BL59,BR59,BX59,CD59,CJ59,CP59,CV59) -> 0 | DC59: =SUM(AI59,AO59,AU59,BA59,BG59,BM59,BS59,BY59,CE59,CK59,CQ59,CW59) -> 0 | DD59: =SUM(AJ59,AP59,AV59,BB59,BH59,BN59,BT59,BZ59,CF59,CL59,CR59,CX59) -> 0 | DE59: =SUM(AK59,AQ59,AW59,BC59,BI59,BO59,BU59,CA59,CG59,CM59,CS59,CY59) -> 0 | DF59: =CZ59 -> 0
A60: ='Group-Savings'!A60 -> 0 | B60: ='Group-Savings'!B60 -> 0 | C60: ='Group-Savings'!C60 -> 0 | D60: ='Group-Savings'!D60 -> 0 | E60: ='Group-Savings'!E60 -> 0 | F60: ='Group-Savings'!F60 -> 0 | G60: ='Group-Savings'!G60 -> 0 | H60: ='Group-Savings'!H60 -> 0 | ... L60: ='Group-Savings'!L60 -> 0 | M60: =K60+L60 -> 0 | O60: 10 | R60: 30 | S60: 10 | U60: 0 | V60: =S60*U60 -> 0 | W60: 1491000 | X60: 709000 | Y60: =W60-X60 -> 782000 | Z60: 45800 | AI60: =$AF$60*AH60 -> 0 | AJ60: =AH60+AI60 -> 0 | AL60: =AJ60-AK60 -> 0 | AO60: =$AF$60*AN60 -> 0 | AP60: =AN60+AO60 -> 0 | AR60: =(AP60-AQ60)+AL60 -> 0 | AU60: =$AF$60*AT60 -> 0 | AV60: =AT60+AU60 -> 0 | AX60: =(AV60-AW60)+AR60 -> 0 | BA60: =$AF$60*AZ60 -> 0 | BB60: =AZ60+BA60 -> 0 | BD60: =(BB60-BC60)+AX60 -> 0 | BG60: =$AF$60*BF60 -> 0 | BH60: =BF60+BG60 -> 0 | BJ60: =(BH60-BI60)+BD60 -> 0 | BM60: =$AF$60*BL60 -> 0 | BN60: =BL60+BM60 -> 0 | BP60: =(BN60-BO60)+BJ60 -> 0 | BS60: =$AF$60*BR60 -> 0 | BT60: =BR60+BS60 -> 0 | BV60: =(BT60-BU60)+BP60 -> 0 | BY60: =$AF$60*BX60 -> 0 | BZ60: =BX60+BY60 -> 0 | CB60: =(BZ60-CA60)+BV60 -> 0 | CE60: =$AF$60*CD60 -> 0 | CF60: =CD60+CE60 -> 0 | CH60: =(CF60-CG60)+CB60 -> 0 | CK60: =$AF$60*CJ60 -> 0 | CL60: =CJ60+CK60 -> 0 | CN60: =(CL60-CM60)+CH60 -> 0 | CQ60: =$AF$60*CP60 -> 0 | CR60: =CP60+CQ60 -> 0 | CT60: =(CR60-CS60)+CN60 -> 0 | CW60: =$AF$60*CV60 -> 0 | CX60: =CV60+CW60 -> 0 | CZ60: =(CX60-CY60)+CT60 -> 0 | DA60: =SUM(AG60,AM60,AS60,AY60,BE60,BK60,BQ60,BW60,CC60,CI60,CO60,CU60) -> 0 | DB60: =SUM(AH60,AN60,AT60,AZ60,BF60,BL60,BR60,BX60,CD60,CJ60,CP60,CV60) -> 0 | DC60: =SUM(AI60,AO60,AU60,BA60,BG60,BM60,BS60,BY60,CE60,CK60,CQ60,CW60) -> 0 | DD60: =SUM(AJ60,AP60,AV60,BB60,BH60,BN60,BT60,BZ60,CF60,CL60,CR60,CX60) -> 0 | DE60: =SUM(AK60,AQ60,AW60,BC60,BI60,BO60,BU60,CA60,CG60,CM60,CS60,CY60) -> 0 | DF60: =CZ60 -> 0
A61: ='Group-Savings'!A61 -> 0 | B61: ='Group-Savings'!B61 -> 0 | C61: ='Group-Savings'!C61 -> 0 | D61: ='Group-Savings'!D61 -> 0 | E61: ='Group-Savings'!E61 -> 0 | F61: ='Group-Savings'!F61 -> 0 | G61: ='Group-Savings'!G61 -> 0 | H61: ='Group-Savings'!H61 -> 0 | ... L61: ='Group-Savings'!L61 -> 0 | M61: =K61+L61 -> 0 | O61: 26 | R61: 25 | S61: 10 | U61: 0 | V61: =S61*U61 -> 0 | W61: 3292000 | X61: 2957000 | Y61: =W61-X61 -> 335000 | Z61: 75000 | AI61: =$AF$61*AH61 -> 0 | AJ61: =AH61+AI61 -> 0 | AL61: =AJ61-AK61 -> 0 | AO61: =$AF$61*AN61 -> 0 | AP61: =AN61+AO61 -> 0 | AR61: =(AP61-AQ61)+AL61 -> 0 | AU61: =$AF$61*AT61 -> 0 | AV61: =AT61+AU61 -> 0 | AX61: =(AV61-AW61)+AR61 -> 0 | BA61: =$AF$61*AZ61 -> 0 | BB61: =AZ61+BA61 -> 0 | BD61: =(BB61-BC61)+AX61 -> 0 | BG61: =$AF$61*BF61 -> 0 | BH61: =BF61+BG61 -> 0 | BJ61: =(BH61-BI61)+BD61 -> 0 | BM61: =$AF$61*BL61 -> 0 | BN61: =BL61+BM61 -> 0 | BP61: =(BN61-BO61)+BJ61 -> 0 | BS61: =$AF$61*BR61 -> 0 | BT61: =BR61+BS61 -> 0 | BV61: =(BT61-BU61)+BP61 -> 0 | BY61: =$AF$61*BX61 -> 0 | BZ61: =BX61+BY61 -> 0 | CB61: =(BZ61-CA61)+BV61 -> 0 | CE61: =$AF$61*CD61 -> 0 | CF61: =CD61+CE61 -> 0 | CH61: =(CF61-CG61)+CB61 -> 0 | CK61: =$AF$61*CJ61 -> 0 | CL61: =CJ61+CK61 -> 0 | CN61: =(CL61-CM61)+CH61 -> 0 | CQ61: =$AF$61*CP61 -> 0 | CR61: =CP61+CQ61 -> 0 | CT61: =(CR61-CS61)+CN61 -> 0 | CW61: =$AF$61*CV61 -> 0 | CX61: =CV61+CW61 -> 0 | CZ61: =(CX61-CY61)+CT61 -> 0 | DA61: =SUM(AG61,AM61,AS61,AY61,BE61,BK61,BQ61,BW61,CC61,CI61,CO61,CU61) -> 0 | DB61: =SUM(AH61,AN61,AT61,AZ61,BF61,BL61,BR61,BX61,CD61,CJ61,CP61,CV61) -> 0 | DC61: =SUM(AI61,AO61,AU61,BA61,BG61,BM61,BS61,BY61,CE61,CK61,CQ61,CW61) -> 0 | DD61: =SUM(AJ61,AP61,AV61,BB61,BH61,BN61,BT61,BZ61,CF61,CL61,CR61,CX61) -> 0 | DE61: =SUM(AK61,AQ61,AW61,BC61,BI61,BO61,BU61,CA61,CG61,CM61,CS61,CY61) -> 0 | DF61: =CZ61 -> 0
A62: ='Group-Savings'!A62 -> 0 | B62: ='Group-Savings'!B62 -> 0 | C62: ='Group-Savings'!C62 -> 0 | D62: ='Group-Savings'!D62 -> 0 | E62: ='Group-Savings'!E62 -> 0 | F62: ='Group-Savings'!F62 -> 0 | G62: ='Group-Savings'!G62 -> 0 | H62: ='Group-Savings'!H62 -> 0 | ... L62: ='Group-Savings'!L62 -> 0 | M62: =K62+L62 -> 0 | O62: 32 | R62: 6 | S62: 10 | U62: 0 | V62: =S62*U62 -> 0 | W62: 300000 | X62: 300000 | Y62: =W62-X62 -> 0 | Z62: 36000 | AI62: =$AF$62*AH62 -> 0 | AJ62: =AH62+AI62 -> 0 | AL62: =AJ62-AK62 -> 0 | AO62: =$AF$62*AN62 -> 0 | AP62: =AN62+AO62 -> 0 | AR62: =(AP62-AQ62)+AL62 -> 0 | AU62: =$AF$62*AT62 -> 0 | AV62: =AT62+AU62 -> 0 | AX62: =(AV62-AW62)+AR62 -> 0 | BA62: =$AF$62*AZ62 -> 0 | BB62: =AZ62+BA62 -> 0 | BD62: =(BB62-BC62)+AX62 -> 0 | BG62: =$AF$62*BF62 -> 0 | BH62: =BF62+BG62 -> 0 | BJ62: =(BH62-BI62)+BD62 -> 0 | BM62: =$AF$62*BL62 -> 0 | BN62: =BL62+BM62 -> 0 | BP62: =(BN62-BO62)+BJ62 -> 0 | BS62: =$AF$62*BR62 -> 0 | BT62: =BR62+BS62 -> 0 | BV62: =(BT62-BU62)+BP62 -> 0 | BY62: =$AF$62*BX62 -> 0 | BZ62: =BX62+BY62 -> 0 | CB62: =(BZ62-CA62)+BV62 -> 0 | CE62: =$AF$62*CD62 -> 0 | CF62: =CD62+CE62 -> 0 | CH62: =(CF62-CG62)+CB62 -> 0 | CK62: =$AF$62*CJ62 -> 0 | CL62: =CJ62+CK62 -> 0 | CN62: =(CL62-CM62)+CH62 -> 0 | CQ62: =$AF$62*CP62 -> 0 | CR62: =CP62+CQ62 -> 0 | CT62: =(CR62-CS62)+CN62 -> 0 | CW62: =$AF$62*CV62 -> 0 | CX62: =CV62+CW62 -> 0 | CZ62: =(CX62-CY62)+CT62 -> 0 | DA62: =SUM(AG62,AM62,AS62,AY62,BE62,BK62,BQ62,BW62,CC62,CI62,CO62,CU62) -> 0 | DB62: =SUM(AH62,AN62,AT62,AZ62,BF62,BL62,BR62,BX62,CD62,CJ62,CP62,CV62) -> 0 | DC62: =SUM(AI62,AO62,AU62,BA62,BG62,BM62,BS62,BY62,CE62,CK62,CQ62,CW62) -> 0 | DD62: =SUM(AJ62,AP62,AV62,BB62,BH62,BN62,BT62,BZ62,CF62,CL62,CR62,CX62) -> 0 | DE62: =SUM(AK62,AQ62,AW62,BC62,BI62,BO62,BU62,CA62,CG62,CM62,CS62,CY62) -> 0 | DF62: =CZ62 -> 0
A63: ='Group-Savings'!A63 -> 0 | B63: ='Group-Savings'!B63 -> 0 | C63: ='Group-Savings'!C63 -> 0 | D63: ='Group-Savings'!D63 -> 0 | E63: ='Group-Savings'!E63 -> 0 | F63: ='Group-Savings'!F63 -> 0 | G63: ='Group-Savings'!G63 -> 0 | H63: ='Group-Savings'!H63 -> 0 | ... L63: ='Group-Savings'!L63 -> 0 | M63: =K63+L63 -> 0 | O63: 32 | R63: 26 | S63: 10 | U63: 0 | V63: =S63*U63 -> 0 | W63: 730000 | X63: 300000 | Y63: =W63-X63 -> 430000 | Z63: 52000 | AI63: =$AF$63*AH63 -> 0 | AJ63: =AH63+AI63 -> 0 | AL63: =AJ63-AK63 -> 0 | AO63: =$AF$63*AN63 -> 0 | AP63: =AN63+AO63 -> 0 | AR63: =(AP63-AQ63)+AL63 -> 0 | AU63: =$AF$63*AT63 -> 0 | AV63: =AT63+AU63 -> 0 | AX63: =(AV63-AW63)+AR63 -> 0 | BA63: =$AF$63*AZ63 -> 0 | BB63: =AZ63+BA63 -> 0 | BD63: =(BB63-BC63)+AX63 -> 0 | BG63: =$AF$63*BF63 -> 0 | BH63: =BF63+BG63 -> 0 | BJ63: =(BH63-BI63)+BD63 -> 0 | BM63: =$AF$63*BL63 -> 0 | BN63: =BL63+BM63 -> 0 | BP63: =(BN63-BO63)+BJ63 -> 0 | BS63: =$AF$63*BR63 -> 0 | BT63: =BR63+BS63 -> 0 | BV63: =(BT63-BU63)+BP63 -> 0 | BY63: =$AF$63*BX63 -> 0 | BZ63: =BX63+BY63 -> 0 | CB63: =(BZ63-CA63)+BV63 -> 0 | CE63: =$AF$63*CD63 -> 0 | CF63: =CD63+CE63 -> 0 | CH63: =(CF63-CG63)+CB63 -> 0 | CK63: =$AF$63*CJ63 -> 0 | CL63: =CJ63+CK63 -> 0 | CN63: =(CL63-CM63)+CH63 -> 0 | CQ63: =$AF$63*CP63 -> 0 | CR63: =CP63+CQ63 -> 0 | CT63: =(CR63-CS63)+CN63 -> 0 | CW63: =$AF$63*CV63 -> 0 | CX63: =CV63+CW63 -> 0 | CZ63: =(CX63-CY63)+CT63 -> 0 | DA63: =SUM(AG63,AM63,AS63,AY63,BE63,BK63,BQ63,BW63,CC63,CI63,CO63,CU63) -> 0 | DB63: =SUM(AH63,AN63,AT63,AZ63,BF63,BL63,BR63,BX63,CD63,CJ63,CP63,CV63) -> 0 | DC63: =SUM(AI63,AO63,AU63,BA63,BG63,BM63,BS63,BY63,CE63,CK63,CQ63,CW63) -> 0 | DD63: =SUM(AJ63,AP63,AV63,BB63,BH63,BN63,BT63,BZ63,CF63,CL63,CR63,CX63) -> 0 | DE63: =SUM(AK63,AQ63,AW63,BC63,BI63,BO63,BU63,CA63,CG63,CM63,CS63,CY63) -> 0 | DF63: =CZ63 -> 0
A64: ='Group-Savings'!A64 -> 0 | B64: ='Group-Savings'!B64 -> 0 | C64: ='Group-Savings'!C64 -> 0 | D64: ='Group-Savings'!D64 -> 0 | E64: ='Group-Savings'!E64 -> 0 | F64: ='Group-Savings'!F64 -> 0 | G64: ='Group-Savings'!G64 -> 0 | H64: ='Group-Savings'!H64 -> 0 | ... L64: ='Group-Savings'!L64 -> 0 | M64: =K64+L64 -> 0 | O64: 52 | R64: 32 | S64: 10 | U64: 0 | V64: =S64*U64 -> 0 | W64: 2483900 | X64: 2483900 | Y64: =W64-X64 -> 0 | Z64: 189800 | AI64: =$AF$64*AH64 -> 0 | AJ64: =AH64+AI64 -> 0 | AL64: =AJ64-AK64 -> 0 | AO64: =$AF$64*AN64 -> 0 | AP64: =AN64+AO64 -> 0 | AR64: =(AP64-AQ64)+AL64 -> 0 | AU64: =$AF$64*AT64 -> 0 | AV64: =AT64+AU64 -> 0 | AX64: =(AV64-AW64)+AR64 -> 0 | BA64: =$AF$64*AZ64 -> 0 | BB64: =AZ64+BA64 -> 0 | BD64: =(BB64-BC64)+AX64 -> 0 | BG64: =$AF$64*BF64 -> 0 | BH64: =BF64+BG64 -> 0 | BJ64: =(BH64-BI64)+BD64 -> 0 | BM64: =$AF$64*BL64 -> 0 | BN64: =BL64+BM64 -> 0 | BP64: =(BN64-BO64)+BJ64 -> 0 | BS64: =$AF$64*BR64 -> 0 | BT64: =BR64+BS64 -> 0 | BV64: =(BT64-BU64)+BP64 -> 0 | BY64: =$AF$64*BX64 -> 0 | BZ64: =BX64+BY64 -> 0 | CB64: =(BZ64-CA64)+BV64 -> 0 | CE64: =$AF$64*CD64 -> 0 | CF64: =CD64+CE64 -> 0 | CH64: =(CF64-CG64)+CB64 -> 0 | CK64: =$AF$64*CJ64 -> 0 | CL64: =CJ64+CK64 -> 0 | CN64: =(CL64-CM64)+CH64 -> 0 | CQ64: =$AF$64*CP64 -> 0 | CR64: =CP64+CQ64 -> 0 | CT64: =(CR64-CS64)+CN64 -> 0 | CW64: =$AF$64*CV64 -> 0 | CX64: =CV64+CW64 -> 0 | CZ64: =(CX64-CY64)+CT64 -> 0 | DA64: =SUM(AG64,AM64,AS64,AY64,BE64,BK64,BQ64,BW64,CC64,CI64,CO64,CU64) -> 0 | DB64: =SUM(AH64,AN64,AT64,AZ64,BF64,BL64,BR64,BX64,CD64,CJ64,CP64,CV64) -> 0 | DC64: =SUM(AI64,AO64,AU64,BA64,BG64,BM64,BS64,BY64,CE64,CK64,CQ64,CW64) -> 0 | DD64: =SUM(AJ64,AP64,AV64,BB64,BH64,BN64,BT64,BZ64,CF64,CL64,CR64,CX64) -> 0 | DE64: =SUM(AK64,AQ64,AW64,BC64,BI64,BO64,BU64,CA64,CG64,CM64,CS64,CY64) -> 0 | DF64: =CZ64 -> 0
A65: ='Group-Savings'!A65 -> 0 | B65: ='Group-Savings'!B65 -> 0 | C65: ='Group-Savings'!C65 -> 0 | D65: ='Group-Savings'!D65 -> 0 | E65: ='Group-Savings'!E65 -> 0 | F65: ='Group-Savings'!F65 -> 0 | G65: ='Group-Savings'!G65 -> 0 | H65: ='Group-Savings'!H65 -> 0 | ... L65: ='Group-Savings'!L65 -> 0 | M65: =K65+L65 -> 0 | O65: 10 | R65: 18 | S65: 10 | U65: 0 | V65: =S65*U65 -> 0 | W65: 1081000 | X65: 1081000 | Y65: =W65-X65 -> 0 | Z65: 143000 | AI65: =$AF$65*AH65 -> 0 | AJ65: =AH65+AI65 -> 0 | AL65: =AJ65-AK65 -> 0 | AO65: =$AF$65*AN65 -> 0 | AP65: =AN65+AO65 -> 0 | AR65: =(AP65-AQ65)+AL65 -> 0 | AU65: =$AF$65*AT65 -> 0 | AV65: =AT65+AU65 -> 0 | AX65: =(AV65-AW65)+AR65 -> 0 | BA65: =$AF$65*AZ65 -> 0 | BB65: =AZ65+BA65 -> 0 | BD65: =(BB65-BC65)+AX65 -> 0 | BG65: =$AF$65*BF65 -> 0 | BH65: =BF65+BG65 -> 0 | BJ65: =(BH65-BI65)+BD65 -> 0 | BM65: =$AF$65*BL65 -> 0 | BN65: =BL65+BM65 -> 0 | BP65: =(BN65-BO65)+BJ65 -> 0 | BS65: =$AF$65*BR65 -> 0 | BT65: =BR65+BS65 -> 0 | BV65: =(BT65-BU65)+BP65 -> 0 | BY65: =$AF$65*BX65 -> 0 | BZ65: =BX65+BY65 -> 0 | CB65: =(BZ65-CA65)+BV65 -> 0 | CE65: =$AF$65*CD65 -> 0 | CF65: =CD65+CE65 -> 0 | CH65: =(CF65-CG65)+CB65 -> 0 | CK65: =$AF$65*CJ65 -> 0 | CL65: =CJ65+CK65 -> 0 | CN65: =(CL65-CM65)+CH65 -> 0 | CQ65: =$AF$65*CP65 -> 0 | CR65: =CP65+CQ65 -> 0 | CT65: =(CR65-CS65)+CN65 -> 0 | CW65: =$AF$65*CV65 -> 0 | CX65: =CV65+CW65 -> 0 | CZ65: =(CX65-CY65)+CT65 -> 0 | DA65: =SUM(AG65,AM65,AS65,AY65,BE65,BK65,BQ65,BW65,CC65,CI65,CO65,CU65) -> 0 | DB65: =SUM(AH65,AN65,AT65,AZ65,BF65,BL65,BR65,BX65,CD65,CJ65,CP65,CV65) -> 0 | DC65: =SUM(AI65,AO65,AU65,BA65,BG65,BM65,BS65,BY65,CE65,CK65,CQ65,CW65) -> 0 | DD65: =SUM(AJ65,AP65,AV65,BB65,BH65,BN65,BT65,BZ65,CF65,CL65,CR65,CX65) -> 0 | DE65: =SUM(AK65,AQ65,AW65,BC65,BI65,BO65,BU65,CA65,CG65,CM65,CS65,CY65) -> 0 | DF65: =CZ65 -> 0
A66: ='Group-Savings'!A66 -> 0 | B66: ='Group-Savings'!B66 -> 0 | C66: ='Group-Savings'!C66 -> 0 | D66: ='Group-Savings'!D66 -> 0 | E66: ='Group-Savings'!E66 -> 0 | F66: ='Group-Savings'!F66 -> 0 | G66: ='Group-Savings'!G66 -> 0 | H66: ='Group-Savings'!H66 -> 0 | ... L66: ='Group-Savings'!L66 -> 0 | M66: =K66+L66 -> 0 | O66: 32 | R66: 11 | S66: 10 | U66: 0 | V66: =S66*U66 -> 0 | W66: 349000 | X66: 334000 | Y66: =W66-X66 -> 15000 | Z66: 160000 | AI66: =$AF$66*AH66 -> 0 | AJ66: =AH66+AI66 -> 0 | AL66: =AJ66-AK66 -> 0 | AO66: =$AF$66*AN66 -> 0 | AP66: =AN66+AO66 -> 0 | AR66: =(AP66-AQ66)+AL66 -> 0 | AU66: =$AF$66*AT66 -> 0 | AV66: =AT66+AU66 -> 0 | AX66: =(AV66-AW66)+AR66 -> 0 | BA66: =$AF$66*AZ66 -> 0 | BB66: =AZ66+BA66 -> 0 | BD66: =(BB66-BC66)+AX66 -> 0 | BG66: =$AF$66*BF66 -> 0 | BH66: =BF66+BG66 -> 0 | BJ66: =(BH66-BI66)+BD66 -> 0 | BM66: =$AF$66*BL66 -> 0 | BN66: =BL66+BM66 -> 0 | BP66: =(BN66-BO66)+BJ66 -> 0 | BS66: =$AF$66*BR66 -> 0 | BT66: =BR66+BS66 -> 0 | BV66: =(BT66-BU66)+BP66 -> 0 | BY66: =$AF$66*BX66 -> 0 | BZ66: =BX66+BY66 -> 0 | CB66: =(BZ66-CA66)+BV66 -> 0 | CE66: =$AF$66*CD66 -> 0 | CF66: =CD66+CE66 -> 0 | CH66: =(CF66-CG66)+CB66 -> 0 | CK66: =$AF$66*CJ66 -> 0 | CL66: =CJ66+CK66 -> 0 | CN66: =(CL66-CM66)+CH66 -> 0 | CQ66: =$AF$66*CP66 -> 0 | CR66: =CP66+CQ66 -> 0 | CT66: =(CR66-CS66)+CN66 -> 0 | CW66: =$AF$66*CV66 -> 0 | CX66: =CV66+CW66 -> 0 | CZ66: =(CX66-CY66)+CT66 -> 0 | DA66: =SUM(AG66,AM66,AS66,AY66,BE66,BK66,BQ66,BW66,CC66,CI66,CO66,CU66) -> 0 | DB66: =SUM(AH66,AN66,AT66,AZ66,BF66,BL66,BR66,BX66,CD66,CJ66,CP66,CV66) -> 0 | DC66: =SUM(AI66,AO66,AU66,BA66,BG66,BM66,BS66,BY66,CE66,CK66,CQ66,CW66) -> 0 | DD66: =SUM(AJ66,AP66,AV66,BB66,BH66,BN66,BT66,BZ66,CF66,CL66,CR66,CX66) -> 0 | DE66: =SUM(AK66,AQ66,AW66,BC66,BI66,BO66,BU66,CA66,CG66,CM66,CS66,CY66) -> 0 | DF66: =CZ66 -> 0
A69: The APFSs lend out the interest on the loans given out which again it comes with interest that is loaned out.
A71: Part of walfare is also loaned out for fear of the thieves of the boxes

Sheet Community Based Facilitators
A2: ID No | B2: District | C2: Sub-County | D2: Parish | E2: Home Village | F2: APFS name | G2: Name of CBF | H2: Sex | I2: NIN | J2: Position held at the WS association | K2: Other positions held in group | L2: Other positions held at community level | M2: Phone contacts | N2: Highest educ level | O2: Additional trainings/qualifications

Sheet Watershed Assoc members
A2: ID No | B2: District | C2: Sub-County | D2: Parish | E2: Micro-watershed | F2: Home Village | G2: Group name | H2: Name of WSA member | I2: Sex | J2: NIN | K2: Position held at network | L2: Other positions held in group | M2: Other positions held at community level | N2: Phone contacts | O2: Highest educ level | P2: Trainings received

Sheet FFS Network members
A2: ID No | B2: District | C2: Sub-County | D2: Parish | E2: Home Village | F2: APFS represented | G2: Name Network member | H2: Sex | I2: NIN | J2: Position held at network | K2: Other positions held in group | L2: Other positions held at community level | M2: Phone contacts | N2: Highest educ level | O2: Trainings received

Sheet Community Animal Health Workers
A2: ID No | B2: District | C2: Sub-County | D2: Parish | E2: Home Village | F2: FFS attached To | G2: Name of CAHWS | H2: Sex | I2: NIN | J2: Position held at the WS association | K2: Other positions held in group | L2: Other positions held at community level | M2: Phone contacts | N2: Highest educ level | O2: Additional trainings/qualifications
